Workbook

Sheet Ligand cost
I1: ChemScene | J1: $1850/kg ddFc
A3: 1. Synthesis of ddFc
A13: Chemicals | B13: Formula | C13: MW | D13: eq | E13: mol | F13: g | G13: Yield(%) | H13: Price ($) | I13: Unit Price | J13: Unit | K13: vol (ml) | L13: d (g/ml) | M13: Source
A14: Ferrocene | B14: C10H10Fe | C14: 186.03 | D14: 1 | E14: =F14/C14 -> 0.096758587 | F14: 18 | H14: =I14*F14/1000 -> 0.504 | I14: 28 | J14: $/kg | M14: https://www.chemicalbook.com/ProductDetail_EN_ferrocene_2034577.htm
A15: Dodecanoyl chloride | B15: C12H23ClO | C15: 218.76 | D15: 2 | E15: =F15/C15 -> 0.19349973 | F15: 42.33 | H15: =I15*F15/1000 -> 0.160854 | I15: 3.8 | J15: $/kg | K15: 45.9 | L15: 0.922 | M15: https://www.chemicalbook.com/ProductDetail_EN_991682.htm
A16: NaBH4 | B16: BH4Na | C16: 37.83 | D16: 2 | E16: =F16/C16 -> 0.19352366 | F16: 7.321 | H16: =I16*F16/1000 -> 0.102494 | I16: 14 | J16: $/kg | M16: https://www.alibaba.com/product-detail/Free-Sample-Sodium-Borocyanohydride-CAS-25895_10000026309495.html?spm=a2700.galleryofferlist.normal_offer.d_title.462413a0yX9EqR&priceId=0638c4062c394ca3b92a5c9dc07a2423 Organic Intermediate Sodium Cyanoborohydride Product on Alibaba.com
A17: Triethylene glycol dimethyl ether | B17: C8H18O4 | C17: 178.23 | D17: =E17/E14 -> 5.5322583 | E17: =F17/C17 -> 0.5352935 | F17: =K17*L17 -> 95.40536 | H17: =I17*F17/1000 -> 1.0112968 | I17: 10.6 | J17: $/kg | K17: 96.76 | L17: 0.986 | M17: https://www.chemicalbook.com/ProductDetail_EN_1414752.htm
A18: Aluminum trichloride | B18: AlCl3 | C18: 133.33 | D18: 2.2 | E18: =F18/C18 -> 0.21285532 | F18: 28.38 | H18: =I18*F18/1000 -> 0.05676 | I18: 2 | J18: $/kg | M18: https://www.chemicalbook.com/ProductDetail_EN_aluminum-chloride_2179085.htm
A19: Dichloromethane | B19: CH2Cl2 | C19: 84.93 | D19: =E19/E14 -> 80.922819 | E19: =F19/C19 -> 7.8299776 | F19: 665 | H19: =I19*F19/1000 -> 6.65 | I19: 10 | J19: $/kg | K19: 500 | L19: 1.33 | M19: https://www.chemicalbook.com/ProductDetail_EN_1480688.htm
A20: Bis(lauryl)ferrocene (ddFc) | B20: C34H58Fe | C20: 522.68 | F20: 27.81 | G20: 54.99 | H20: =SUM(H14:H19) -> 8.4854048 | J20: =H20/F20 -> 0.30512063
J21: $/g
A22: 2. Synthesis of deFc
J23: =J20*1000 -> 305.12063
A33: Chemicals | B33: Formula | C33: MW | D33: eq | E33: mol | F33: g | G33: Yield(%) | H33: Price ($) | I33: Unit Price | J33: Unit | K33: vol (ml) | L33: d (g/ml) | M33: Source
A34: Carbomethoxyferrocene | B34: C12H12FeO2 | C34: 244.07 | D34: 1 | E34: =F34/C34 -> 0.069652149 | F34: 17 | H34: =I34*F34/1000 -> 63.24 | I34: 3720 | J34: $/kg | M34: https://scifinder-n.cas.org/searchDetail/catalogItem/6972747ff639fa3449303d77/catalogItemDetails
A35: Dodecanoyl chloride | B35: C12H23ClO | C35: 218.76 | D35: 2 | E35: =F35/C35 -> 0.13933077 | F35: 30.48 | H35: =I35*F35/1000 -> 0.115824 | I35: 3.8 | J35: $/kg | K35: 33.1 | L35: 0.922 | M35: https://www.chemicalbook.com/ProductDetail_EN_991682.htm
A36: NaBH4 | B36: BH4Na | C36: 37.83 | D36: 2 | E36: =F36/C36 -> 0.13930743 | F36: 5.27 | H36: =I36*F36/1000 -> 0.07378 | I36: 14 | J36: $/kg | M36: https://www.alibaba.com/product-detail/Free-Sample-Sodium-Borocyanohydride-CAS-25895_10000026309495.html?spm=a2700.galleryofferlist.normal_offer.d_title.462413a0yX9EqR&priceId=0638c4062c394ca3b92a5c9dc07a2423 Organic Intermediate Sodium Cyanoborohydride Product on Alibaba.com
A37: Triethylene glycol dimethyl ether | B37: C8H18O4 | C37: 178.23 | D37: =E37/E34 -> 5.5320068 | E37: =F37/C37 -> 0.38531616 | F37: =K37*L37 -> 68.6749 | H37: =I37*F37/1000 -> 0.72795394 | I37: 10.6 | J37: $/kg | K37: 69.65 | L37: 0.986 | M37: https://www.chemicalbook.com/ProductDetail_EN_1414752.htm
A38: Aluminum trichloride | B38: AlCl3 | C38: 133.33 | D38: 2.2 | E38: =F38/C38 -> 0.15322883 | F38: 20.43 | H38: =I38*F38/1000 -> 0.04086 | I38: 2 | J38: $/kg | M38: https://www.chemicalbook.com/ProductDetail_EN_aluminum-chloride_2179085.htm
A39: Dichloromethane | B39: CH2Cl2 | C39: 84.93 | D39: =E39/E34 -> 89.93236 | E39: =F39/C39 -> 6.2639821 | F39: 532 | H39: =I39*F39/1000 -> 5.32 | I39: 10 | J39: $/kg | K39: 400 | L39: 1.33 | M39: https://www.chemicalbook.com/ProductDetail_EN_1480688.htm
A40: 1-lauryl-1'-carbomethoxy ferrocene | B40: 412.4 | F40: 19.77 | G40: 68.83 | H40: =SUM(H34:H39) -> 69.518418 | J40: =H40/F40 -> 3.516359
J41: $/g
A45: 3. Synthesis of coeFc
A47: Chemicals | B47: Formula | C47: MW | D47: eq | E47: mol | F47: g | G47: Yield(%) | H47: Price ($) | I47: Unit Price | J47: Unit | K47: vol (ml) | L47: d (g/ml) | M47: Source
A48: Ferrocene carboxaldehyde | B48: C11H10FeO | C48: 214.04 | D48: 1 | E48: 0.018688096 | F48: 4 | H48: =I48*F48/1000 -> 8.1888 | I48: 2047.2 | J48: $/kg | M48: https://store.apolloscientific.co.uk/product/ferrocenecarboxaldehyde
A49: Octyl cyanoacetate | B49: NCCH2CO2(CH2)7CH3 | C49: 197.27 | D49: 1.4 | E49: 0.026157044 | F49: 5.16 | H49: =I49*F49/1000 -> 0.0516 | I49: 10 | J49: $/kg | M49: https://www.chemicalbook.com/ProductList_En.aspx?kwd=15666-97-4
A50: Piperidine | B50: C5H11N | C50: 85.15 | D50: 0.1 | E50: 0.001867293 | F50: 0.159 | H50: =I50*F50/1000 -> 0.07155636 | I50: 450.04 | J50: $/kg | M50: https://scifinder-n.cas.org/searchDetail/catalogItem/69baf576d2558453e28ba6ad/catalogItemDetails
A51: Ethyl alcohol | B51: CH3CH2OH | C51: 46.07 | D51: 5.4706338 | E51: 0.10223573 | F51: 4.71 | H51: =I51*F51/1000 -> 0.0002355 | I51: 0.05 | J51: $/kg | K51: 6 | L51: 0.785 | M51: https://www.chemicalbook.com/ProductList_En.aspx?kwd=ethanol
A52: Dichloromethane | B52: CH2Cl2 | C52: 84.93 | D52: 83.796421 | E52: 1.5659955 | F52: 133 | H52: =I52*F52/1000 -> 1.33 | I52: 10 | J52: $/kg | K52: 100 | L52: 1.33 | M52: https://www.chemicalbook.com/ProductDetail_EN_1480688.htm
A53: Hydrochloric acid | B53: HCl | C53: 36.46 | D53: 14.46267 | E53: 0.27027976 | F53: 9.8544 | H53: =I53*F53/1000 -> 0.12367272 | I53: 12.55 | J53: $/kg | K53: 8.212 | L53: 1.2 | M53: https://scifinder-n.cas.org/searchDetail/catalogItem/69baf9c8d2558453e28bd0fe/catalogItemDetails
A54: n-hexane | B54: CH3(CH2)4CH3 | C54: 86.18 | D54: 294.16219 | E54: 5.4973312 | F54: 473.76 | H54: =I54*F54/1000 -> 4.7376 | I54: 10 | J54: $/kg | K54: 720 | L54: 0.658 | M54: https://www.chemicalbook.com/ProductList_En.aspx?kwd=%20110-54-3
A55: Ethyl acetate | B55: CH3COOC2H5 | C55: 88.11 | D55: 98.602697 | E55: 1.8426966 | F55: 162.36 | H55: =I55*F55/1000 -> 1.6236 | I55: 10 | J55: $/kg | K55: 180 | L55: 0.902 | M55: https://www.chemicalbook.com/ProductList_En.aspx?kwd=141-78-6
A56: coeFc | B56: 393.31 | F56: 6.23 | G56: 84.6 | H56: =SUM(H48:H55) -> 16.127065 | J56: =H56/F56 -> 2.5886139
J57: $/g
J59: =J56*1000 -> 2588.6139

Sheet Reagent cost
C1: Vol of solution | D1: 100 | E1: L | I1: 100
C3: %excess | D3: 1.2 | E3: 2.25 | M3: conc. | O3: volume
B4: 1 | D4: 8 | F4: 6 | H4: 3 | J4: 3 | L4: feed | O4: 100 | P4: L/min | S4: =_xlfn.T.INV(1-0.05/2,14) -> 2.1447867
B5: KIO3 | C5: + | D5: NaI | E5: + | F5: HClO4 | G5: = | H5: I3- | J5: H2O | L5: oxidant | M5: 100 | N5: mM | O5: 100 | P5: L
A6: Conc (mM): | B6: =(H6/3)*D3 -> 40 | D6: =(8*H6/3)*E3 -> 600 | F6: =H6*2 -> 200 | H6: 100 | I6: 10 | L6: reductant | M6: 100 | N6: mM | O6: 100 | P6: L | S6: =1822.191-2.145*300.199 -> 1178.2641
F7: Limiting Rctnt | L7: ligand | M7: 100 | N7: mM | O7: 300 | P7: L
L8: change salt to be included in PGM feed Salt of conc 0.1 M
S9: =0.2832+2.145*0.0106 -> 0.305937
A10: Chemicals | B10: Formula | C10: MW | D10: mol (M) | E10: kg | F10: vol (L) | G10: d (g/ml) | H10: Unit Price | I10: Unit | J10: Price | K10: Source
A11: Dichloromethane | B11: CH2Cl2 | C11: 84.93 | E11: =F11*G11 -> 132 | F11: 100 | G11: 1.32 | H11: 10 | I11: $/kg | J11: =E11*H11 -> 1320 | K11: https://www.chemicalbook.com/ProductList_En.aspx?kwd=dichloromethane
A12: ox | B12: KIO3 | C12: 214.001 | D12: 0.04 | E12: =D12*$D$1*C12/1000 -> 0.856004 | F12: 100 | H12: 10 | I12: $/kg | J12: =E12*H12 -> 8.56004 | K12: https://www.chemicalbook.com/ProductList_En.aspx?cbn=CB5854303
A13: ox | B13: NaI | C13: 149.8942 | D13: 0.6 | E13: =D13*$D$1*C13/1000 -> 8.993652 | F13: 100 | H13: 4 | I13: $/kg | J13: =E13*H13 -> 35.974608 | K13: https://www.chemicalbook.com/ProductList_En.aspx?cbn=CB6170714
A14: ox | B14: HClO4 | C14: 100.46 | D14: 0.2 | E14: =D14*$D$1*C14/1000 -> 2.0092 | F14: 100 | H14: 63.5 | I14: $/L | J14: =E14*H14 -> 127.5842 | K14: https://scifinder-n.cas.org/searchDetail/catalogItem/698a4af308f8b56fea0b2a9f/catalogItemDetails
K15: Perchloric acid, 0.1N in Acetic Acid Standardized Solution
A16: red | B16: K4Fe(CN)6∙3H2O | C16: 422.39 | D16: 0.1 | E16: =D16*$D$1*C16/1000 -> 4.2239 | F16: 100 | H16: 10 | I16: $/kg | J16: =E16*H16 -> 42.239 | K16: https://scifinder-n.cas.org/searchDetail/catalogItem/698a50ae08f8b56fea0b847a/catalogItemDetails
A17: salt | B17: NaCl | C17: 58.44 | D17: 0.1 | E17: =D17*$D$1*C17/1000 -> 0.5844 | F17: 100 | H17: 2 | I17: $/kg | J17: =E17*H17 -> 1.1688 | K17: https://www.chemicalbook.com/ProductList_En.aspx?cbn=CB4104636
A18: ddFc | B18: C34H58Fe | C18: 522.68 | D18: 0.1 | E18: =D18*F18*C18/1000 -> 15.6804 | F18: 300 | H18: ='Ligand cost'!J20*1000 -> 305.12063 | I18: $/kg | J18: =E18*H18 -> 4784.4136
A19: FeCl2 | C19: 126.75 | H19: 1 | I19: $/kg | K19: https://www.chemicalbook.com/ChemicalProductProperty_EN_CB5411955.htm
I20: sum | J20: =SUM(J11:J18) -> 6319.9402
A23: deFc | C23: 412.21 | D23: 0.1 | H23: 3267.1774 | I23: $/kg
I26: DCM 1% makeup, ligand 2% makeup
H27: reagent opex | J27: =(J11*0.01+J18*0.02)*300 -> 32666.481 | K27: $/year
B28: 50% wt perchloric acid
A29: 35.31 | B29: https://www.alibaba.com/product-detail/inorganic-acid-perchloric-acid-50-Purity_1601345200625.html?spm=a2700.7724857.0.0.798331f2XzNuo4
A32: Chemicals | B32: Formula | C32: Unit Price | D32: units
A33: Dichloromethane | B33: CH2Cl2 | D33: $/L
A34: ox | B34: KIO3 | C34: =H12/1000*C12 -> 2.14001 | D34: $/mol
A35: ox | B35: NaI | C35: =H13/1000*C13 -> 0.5995768 | D35: $/mol
A36: ox | B36: HClO4 | C36: =A29*2 -> 70.62 | D36: $/kg pure
A38: red | B38: K4Fe(CN)6∙3H2O | C38: =H16/1000*C16 -> 4.2239 | D38: $/mol
A39: salt | B39: NaCl | C39: =H17/1000*C17 -> 0.11688 | D39: $/mol
A40: ddFc | B40: C34H58Fe | C40: =H18/1000*C18 -> 159.48045 | D40: $/mol
A41: FeCl2 | D41: $/mol

Sheet Oxidant Feed Composition
A1: Chemical
D3: Vol of solution | E3: 100 | F3: L | G3: Mols Water Init --> | H3: 5550.84
D5: Water generated is negligible relative to vol--> can assume constant volume
A7: x excess: | B7: 1.2 | D7: 2.25
A8: Stoich: | B8: 1 | D8: 8 | F8: 6 | H8: 3 | J8: 3 | L8: 6 | N8: Assume K is analogous with Na for Atom balance check purposes
B9: NaIO3 | C9: + | D9: NaI | E9: + | F9: HClO4 | G9: = | H9: NaI3 | I9: + | J9: H2O | K9: + | L9: NaClO4 | N9: NaIO3 should really be KIO3, but we will use Na as a placeholder for all cations, so K4[Fe(CN)_6] will be assumed to be Na4[Fe(CN)_6]
A10: Conc (mM): | B10: =(H10/3)*B7 -> 40 | D10: =(8*H10/3)*D7 -> 600 | F10: =H10*2 -> 200 | H10: 100 | J10: 100 | L10: 200
A11: conc (M): | B11: =B10/1000 -> 0.04 | D11: =D10/1000 -> 0.6 | F11: =F10/1000 -> 0.2 | H11: =H10/1000 -> 0.1 | J11: =J10/1000 -> 0.1 | L11: =L10/1000 -> 0.2
A12: I (mol): | B12: =$E$3*B11 -> 4 | D12: =$E$3*D11 -> 60 | F12: =$E$3*F11 -> 20 | H12: 0 | J12: 0 | L12: 0
A13: delta (mol): | B13: =1/6*F13 -> -3.3333333 | D13: =4/3*F13 -> -26.666667 | F13: =-F12 -> -20 | H13: =-1/2*F13 -> 10 | J13: =-1/2*F13 -> 10 | L13: =-1*F13 -> 20
A14: F (mol): | B14: =B12+B13 -> 0.66666667 | D14: =D12+D13 -> 33.333333 | F14: =F12+F13 -> 0 | H14: =H12+H13 -> 10 | J14: =J12+J13 -> 10 | L14: =L12+L13 -> 20
A15: F Conc (M) | B15: =B14/$E$3 -> 0.0066666667 | D15: =D14/$E$3 -> 0.33333333 | F15: =F14/$E$3 -> 0 | H15: =H14/$E$3 -> 0.1 | J15: =J14/$E$3 -> 0.1 | L15: =L14/$E$3 -> 0.2
A18: Chemicals In Process | B18: Description | M18: Oxidant Feed Tank Composition
A19: H2[PtCl_6] | B19: Chloroplatinic Acid in OG Leachate Feed | M19: Chemical | N19: Conc [M] | O19: MW [g/mol]
A20: Na2[PdCl_4] | B20: Chloropalladic Acid in OG Leachate Feed | L20: really K | M20: NaIO3 | N20: =B15 -> 0.0066666667 | O20: 214.001 | P20: Kio3 MW
A21: Na3[RhCl_6] | B21: Chlororhodic Acid in OG Leachate Feed | M21: NaI | N21: =D15 -> 0.33333333 | O21: 149.89
A22: HCl | B22: Will Likely Be in Feed Leachate. Inert in eLLE | M22: NaI3 | N22: =H15 -> 0.1
A23: NaCl | B23: Will Likely Be in Feed Leachate. Also in aqueous reduction loop. Inert in eLLE | M23: NaClO4 | N23: =L15 -> 0.2
A24: KIO3 | B24: Enters in Aqueous Oxidant Loop | M24: Cost For 100 L of Feed Solution [$] | N24: =B12*'Reagent cost'!C34+D12*'Reagent cost'!C35+F12*'Reagent cost'!C36*'Reagent cost'!C14/1000 -> 186.42435
A25: NaI | B25: Enters in Aqueous Oxidant Loop | M25: Cost Ox Fresh Feed [$/L] | N25: =N24/100 -> 1.8642435
A26: NaI3 | B26: Enters in Aqueous Oxidant Loop | M26: Cost per mol NaI3- [$/mol] | N26: =N24/(100*N22) -> 18.642435
A27: NaClO4 | B27: Enters in Aqueous Oxidant Loop | M27: HClO4 | O27: 100.46
M28: Cost Ox Fresh Feed +50% ClO4 Price [$/L] | N28: =(B12*'Reagent cost'!C34+D12*'Reagent cost'!C35+F12*'Reagent cost'!C36*'Reagent cost'!C14/1000*1.5)/100 -> 2.573692
M29: Cost Ox Fresh Feed -50% ClO4 Price [$/L] | N29: =(B12*'Reagent cost'!C34+D12*'Reagent cost'!C35+F12*'Reagent cost'!C36*'Reagent cost'!C14/1000*0.5)/100 -> 1.154795
E39: assume ddFc of 1.89 mol/min (3 stages S1)
E40: =1.89/0.2 -> 9.45 | F40: =E40*0.006666666666 -> 0.063
B44: NaClO4 | C44: + | D44: NaI3 | E44: + | F44: ddFc | G44: = | H44: ddFcClO4 | I44: + | J44: NaI
B45: 1 | D45: 0.5 | F45: 1 | H45: 1 | J45: 1.5
A46: I (mol/min) | B46: 1.89 | D46: =F46*D45*1.2 -> 1.134 | F46: 1.89 | H46: 0 | J46: 3.78
A47: delta (mol/min) | B47: =$F$47*B45 -> -1.89 | D47: =$F$47*D45 -> -0.945 | F47: =-F46 -> -1.89 | H47: =-$F$47*H45 -> 1.89 | I47: =-$F$47*I45 -> 0 | J47: =-$F$47*J45 -> 2.835
A48: F (mol/min) | B48: =B46+B47 -> 0 | C48: =C46+C47 -> 0 | D48: =D46+D47 -> 0.189 | E48: =E46+E47 -> 0 | F48: =F46+F47 -> 0 | G48: =G46+G47 -> 0 | H48: =H46+H47 -> 1.89 | I48: =I46+I47 -> 0 | J48: =J46+J47 -> 6.615

Sheet PGM market prices
B1: Name | C1: price/kg (USD/kg) | D1: $/troy oz | F1: Source
B2: Pt | C2: =D2/0.031 -> 33730.323 | D2: 1045.64 | F2: PGM prices and trading | Johnson Matthey
B3: Pd | C3: =D3/0.031 -> 32929.677 | D3: 1020.82 | F3: assessed on August 11th 2025 last 12 months average price
B4: Rh | C4: =D4/0.031 -> 164946.13 | D4: 5113.33
B5: Ru | C5: =D5/0.031 -> 17831.613 | D5: 552.78
B6: Ir | C6: =D6/0.031 -> 142484.52 | D6: 4417.02
E9: 43200000
B10: 100 L/min feed 1000 ppm of PGM each | F10: =E9/2 -> 21600000 | G10: kg/year
D11: Pt | F11: =C2*$F$10 -> 7.2857497e+11 | G11: $
B12: 50% recovery assumed | D12: Pd | F12: =C3*$F$10 -> 7.1128103e+11 | G12: $
D13: Rh | F13: =C4*$F$10 -> 3.5628364e+12 | G13: $
D14: Ru | F14: =C5*$F$10 -> 3.8516284e+11 | G14: $
D15: Ir | F15: =C6*$F$10 -> 3.0776655e+12 | G15: $ | J15: Platinum PRICE Today | Platinum Spot Price Chart | Live Price of Platinum per Ounce | Markets Insider
J16: PGM prices and trading | Johnson Matthey
J17: USGS

Sheet CAPEX+OPEX
A1: Electrolyzer unit | D1: 00 21-0083-SI.fm | M1: Executive summary – Global Hydrogen Review 2025 – Analysis - IEA
A2: CAPEX | M2: The cost of making and installing an electrolyser outside of China in 2024 was USD 2 000 to USD 2 600 per kilowatt (kW)
A3: oxidant/reductant conc | C3: 0.1 | D3: mol/L
A4: volume | C4: 100 | D4: L | M4: Economics of converting renewable power to hydrogen | Nature Energy
A5: Q | C5: =C3*C4*96485 -> 964850 | D5: C | M5: Electrolyzer capital cost $550/kW-2640/kW
A6: current density | C6: 4 | D6: A/m2 | E6: 0.4 | F6: mA/cm2
A7: cell voltage | C7: 0.5 | D7: V | M7: Electrolyzer energy dominates separation costs in state-of-the-art CO2 electrolyzers: Implications for single-pass CO2 utilization: Joule
A8: area | C8: 0.0005 | D8: m2
A10: electrolyzer cost per area | C10: 31871 | D10: $/m2
A11: electricity | D11: $/kWh
A13: A=I/j=0.25I (m2)
L14: ICC=1.12(electrolyzer)+(0.15+0.08+0.02+0.15)(ICC)
A15: operating days | C15: 300 | D15: days/year
A16: operating hours | C16: =C15*24 -> 7200 | D16: h/year
A19: Pilot scale: 100 L/min feed | G19: Plant scale: 10000 L/min feed
A20: pilot scale area | C20: 4 | D20: m2 | G20: plant scale area | I20: 400 | J20: m2
A21: current | C21: 20 | D21: A | E21: 0.5 mA/cm2 | G21: current | I21: 2000 | J21: A | K21: j | L21: 0.5 mA/cm2
A22: power | C22: =C21*C7/1000 -> 0.01 | D22: kW | G22: power | I22: =I21*C7/1000 -> 1 | J22: kW
A24: Electrolyzer | C24: =SUM(P25:P26) -> 127488 | D24: $ | G24: Electrolyzer | I24: =C10*I20 -> 12748400 | J24: $ | P24: 4m2 | Q24: 400m2
M25: Cell stack cost | O25: 14980 | P25: =4*O25 -> 59920 | Q25: =O25*400 -> 5992000
A26: Installation | C26: 12 | D26: % of equipment | F26: =0.12*C24 -> 15298.56 | G26: Installation | I26: 12 | J26: % of equipment | L26: =0.12*I24 -> 1529808 | M26: Balance of plant cost | O26: 16892 | P26: =4*O26 -> 67568 | Q26: =O26*400 -> 6756800
A27: up-front permitting | C27: 15 | D27: % of installed capital cost | F27: =0.15*$P$29 -> 35696.64 | G27: up-front permitting | I27: 15 | J27: % of installed capital cost | L27: =0.15*$Q$29 -> 3569552
A28: Engineering & design | C28: 8 | D28: % of ICC | F28: =0.08*$P$29 -> 19038.208 | G28: Engineering & design | I28: 8 | J28: % of ICC | L28: =0.08*$Q$29 -> 1903761.1
A29: site prep | C29: 2 | D29: % of ICC | F29: =0.02*$P$29 -> 4759.552 | G29: site prep | I29: 2 | J29: % of ICC | L29: =0.02*$Q$29 -> 475940.27 | M29: ICC | P29: =(1.12/0.6)*C24 -> 237977.6 | Q29: =(1.12/0.6)*I24 -> 23797013
A30: contingency | C30: 15 | D30: % of ICC | F30: =0.15*$P$29 -> 35696.64 | G30: contingency | I30: 15 | J30: % of ICC | L30: =0.15*$Q$29 -> 3569552
A32: CAPEX | C32: =SUM(F26:F30)+SUM(P25:P26) -> 237977.6 | D32: $ | G32: CAPEX | I32: =1.87*I24 -> 23839508 | J32: $
A35: OPEX
A36: Electricity | B36: 0.07 | C36: $/kWh | E36: Sustainable waste-nitrogen upcycling enabled by low-concentration nitrate electrodialysis and high-performance ammonia electrosynthesis - EES Catalysis (RSC Publishing)
A38: Electricity price | C38: =C22*C16*$B$36 -> 5.04 | D38: $/year | G38: Electricity price | I38: =I22*C16*$B$36 -> 504 | J38: $/year
A39: Replacement cost | C39: 15 | D39: % of ICC | G39: Replacement cost | I39: 15 | J39: % of ICC
A40: (every 7year) | C40: =C32*0.15/7 -> 5099.52 | D40: $/year | G40: (every 7year) | I40: =I32*0.15/7 -> 510846.6 | J40: $/year
A41: fixed operation and maintenance | D41: 3% of CAPEXassumed | G41: fixed operation and maintenance | J41: 3% of CAPEXassumed
C42: =C32*0.03 -> 7139.328 | D42: $/year | I42: =I32*0.03 -> 715185.24 | J42: $/year
A44: OPEX | C44: =SUM(C38,C40,C42) -> 12243.888 | D44: $/year | G44: OPEX | I44: =SUM(I38,I40,I42) -> 1226535.8 | J44: $/year
A47: Solvent extraction+electrowinning unit | F47: report.pdf
L48: SX plants are usually expressed in gallons per min ute (gal/min)
A49: 6000-70000 st/d ore tonnage capacity | M49: 1 liter | N49: 0.264172 | O49: gallon
A50: 0.4% Cu and recovery of 50% | E50: assumption
L51: 100 | M51: L/min | N51: = | O51: =L51*N49*15 -> 396.258 | P51: st/d
L54: 6000 | M54: 70000 | N54: st/d
A55: site development | L55: =L54/(15*0.264172) -> 1514.165 | M55: =M54/(15*0.264172) -> 17665.258 | N55: L/min
A56: utility installation
A57: pregnant leach solution pumps
A58: raffinate pond
A59: mixer-settlers
A60: organic tanks and pumps
A61: initial fill of diluent and extractant
A65: Pilot scale: 100 L/min feed | D65: 396.258 | H65: Plant scale: 10000 L/min feed | K65: 39625.8 | M65: =1/3.78541*15 -> 3.9625827
C66: SX+EW capex | E66: SX+EW opex | F66: $ | J66: SX+EW capex | L66: SX+EW opex | M66: $
A67: Labor | C67: =J67*(0.01^0.72) -> 166516.33 | E67: =0.499*($D$65^(-0.146)) -> 0.20835108 | F67: =E67*$C$15*$D$65 -> 24768.234 | H67: Labor | J67: =2510*($K$65^0.571)+89*$K$65 -> 4586240.7 | L67: =0.499*($K$65^(-0.146)) -> 0.10636427 | M67: =L67*$C$15*$K$65 -> 1264430.8
A68: Equipment | C68: =J68*(0.01^0.72) -> 428244.3 | E68: =0.248*($D$65^(-0.144)) -> 0.10479555 | F68: =E68*$C$15*$D$65 -> 12457.823 | H68: Equipment | J68: =4810*($K$65^0.6)+228*$K$65 -> 11794827 | L68: =0.248*($K$65^(-0.144)) -> 0.053993669 | M68: =L68*$C$15*$K$65 -> 641862.7
A69: Steel | C69: =J69*(0.01^0.72) -> 82607.802 | E69: =0.105*($D$65^(-0.144)) -> 0.044369084 | F69: =E69*$C$15*$D$65 -> 5274.4813 | H69: Steel | J69: =1030*($K$65^0.59)+44*$K$65 -> 2275207.8 | L69: =0.105*($K$65^(-0.144)) -> 0.022860223 | M69: =L69*$C$15*$K$65 -> 271756.39
A70: Lube | E70: =0.058*($D$65^(-0.151)) -> 0.023503542 | F70: =E70*$C$15*$D$65 -> 2794.0399 | H70: Lube | L70: =0.058*($K$65^(-0.151)) -> 0.011725552 | M70: =L70*$C$15*$K$65 -> 139390.32
A71: Construction | C71: =J71*(0.01^0.72) -> 511355.71 | H71: Construction | J71: =5640*($K$65^0.602)+272*$K$65 -> 14083906 | M71: =L71*$C$15*$K$65 -> 0
A72: Electricity | E72: =1.45*($D$65^(-0.145)) -> 0.60906155 | F72: =E72*$C$15*$D$65 -> 72403.654 | H72: Electricity | L72: =1.45*($K$65^(-0.145)) -> 0.31236415 | M72: =L72*$C$15*$K$65 -> 3713303.8
A73: Sales tax | C73: =J73*(0.01^0.72) -> 60373.486 | E73: =0.056*($D$65^(-0.144)) -> 0.023663511 | F73: =E73*$C$15*$D$65 -> 2813.0567 | H73: Sales tax | J73: =688*($K$65^0.6)+32*$K$65 -> 1662823.9 | L73: =0.056*($K$65^(-0.144)) -> 0.012192119 | M73: =L73*$C$15*$K$65 -> 144936.74
A75: total | B75: CAPEX | C75: =J75*(0.01^0.72) -> 1249097.6 | D75: $ | E75: OPEX | F75: =SUM(F67:F73) -> 120511.29 | G75: $/year | H75: total | I75: CAPEX | J75: =SUM(J67:J74) -> 34403006 | K75: $ | L75: OPEX | M75: =SUM(M67:M73) -> 6175680.7 | N75: $/year
A77: reagent | E77: =0.583*($D$65^(-0.143)) -> 0.24783218 | F77: =E77*$C$15*$D$65 -> 29461.645 | H77: reagent | L77: =0.583*($K$65^(-0.143)) -> 0.12827963 | M77: =L77*$C$15*$K$65 -> 1524954.9
E78: sum | F78: =SUM(F77,F75) -> 149972.93 | L78: sum | M78: =SUM(M75:M77) -> 7700635.6
A80: scale factor | C80: 0.72
A81: Development of techno-economic models for assessment of solvent-based bitumen extraction technology - ScienceDirect
H84: https://www.training.itservices.manchester.ac.uk/public/gced/CEPCI.html?reactors/CEPCI/index.html
A96: baseline SX fraction of 60% assumed for SX only cost, electricity 20% assumed
A97: Pilot scale: 100 L/min feed | D97: 396.258 | H97: Plant scale: 10000 L/min feed | K97: 39625.8
C98: SX capex | E98: SX opex | F98: $ | J98: SX capex | L98: SX opex | M98: $
A99: Labor | C99: =0.6*C67 -> 99909.8 | E99: =0.6*E67 -> 0.12501065 | F99: =0.6*F67 -> 14860.941 | H99: Labor | J99: =0.6*J67 -> 2751744.4 | L99: =0.6*L67 -> 0.06381856 | M99: =0.6*M67 -> 758658.45
A100: Equipment | C100: =0.6*C68 -> 256946.58 | E100: =0.6*E68 -> 0.06287733 | F100: =0.6*F68 -> 7474.6935 | H100: Equipment | J100: =0.6*J68 -> 7076896.5 | L100: =0.6*L68 -> 0.032396202 | M100: =0.6*M68 -> 385117.62
A101: Steel | C101: =0.6*C69 -> 49564.681 | E101: =0.6*E69 -> 0.02662145 | F101: =0.6*F69 -> 3164.6888 | H101: Steel | J101: =0.6*J69 -> 1365124.7 | L101: =0.6*L69 -> 0.013716134 | M101: =0.6*M69 -> 163053.83
A102: Lube | E102: =0.6*E70 -> 0.014102125 | F102: =0.6*F70 -> 1676.424 | H102: Lube | L102: =0.6*L70 -> 0.0070353314 | M102: =0.6*M70 -> 83634.19
A103: Construction | C103: =0.6*C71 -> 306813.43 | H103: Construction | J103: =0.6*J71 -> 8450343.5
A104: Electricity | E104: =0.2*E72 -> 0.12181231 | F104: =0.2*F72 -> 14480.731 | H104: Electricity | L104: =0.2*L72 -> 0.06247283 | M104: =0.2*M72 -> 742660.76
A105: Sales tax | C105: =0.6*C73 -> 36224.092 | E105: =0.6*E73 -> 0.014198107 | F105: =0.6*F73 -> 1687.834 | H105: Sales tax | J105: =0.6*J73 -> 997694.33 | L105: =0.6*L73 -> 0.0073152713 | M105: =0.6*M73 -> 86962.044
A106: Reagent | C106: 2847.8193 | F106: 11833.756 | H106: Reagent | J106: =C106*100 -> 284781.93 | M106: =F106*100 -> 1183375.6
A108: total | B108: CAPEX | C108: =SUM(C99:C106) -> 752306.4 | D108: $ | E108: OPEX | F108: =SUM(F99:F106) -> 55179.068 | G108: $/year | H108: total | I108: CAPEX | J108: =SUM(J99:J106) -> 20926585 | K108: $ | L108: OPEX | M108: =SUM(M99:M106) -> 3403462.5 | N108: $/year
E111: 2021 | F111: Reactor Correlation Source: | G111: https://www.mdpi.com/1996-1073/14/9/2665?type=check_update&version=1
F112: CEPCI | G112: https://www.training.itservices.manchester.ac.uk/public/gced/CEPCI.html?reactors/CEPCI/index.html
F113: 2025 src | G113: https://www.chemengonline.com/plant-cost-index-beta/
F114: 1992 | G114: 358.2
F115: 2021 | G115: 708.8
F116: 2025 | G116: 836
K117: =4586243*(100/10000)^0.72*(4/3)^0.6*0.6*(836/358.2) -> 277110.03
F118: $/L
E119: Process Water | F119: =0.27/1000 -> 0.00027 | G119: SSL
E121: 15% more than rctr cost (5% for the site prep, 10% for the startup, (assume labor included in the SX))
E122: 1.15x
G126: =7963.6*(11.335/1000)^0.6*836/708.8*1.7 -> 1086.1601

Sheet Sheet2
B1: Pilot scale | C1: Plant scale | D1: Unit
A2: Feed input | B2: 100 | C2: 10000 | D2: L/min | G2: Operating days: 300 days/year
A3: Solvent extraction CAPEX | G3: Solvent loss: DCM 1% make up daily
A4: Labor | B4: 99909.8 | C4: 2751744.4 | D4: $ | G4: Ligand loss: ddFc 2% make up daily
A5: Equipment | B5: 256946.58 | C5: 7076896.5 | D5: $
A6: Steel | B6: 49564.68 | C6: 1365124.7 | D6: $
A7: Construction | B7: 306813.43 | C7: 8450343.5 | D7: $
A8: Sales tax | B8: 36224.09 | C8: 997694.34 | D8: $
A9: Initial reagent input | B9: 2847.82 | C9: 284781.93 | D9: $
A10: Total | B10: 752306.4 | C10: 20926585 | D10: $
A11: Solvent extraction OPEX
A12: Labor | B12: 14860.94 | C12: 758658.45 | D12: $/year
A13: Equipment | B13: 7474.69 | C13: 385117.62 | D13: $/year
A14: Steel | B14: 3164.89 | C14: 163053.83 | D14: $/year
A15: Lube | B15: 1676.42 | C15: 83634.19 | D15: $/year
A16: Electricity | B16: 14480.73 | C16: 742660.76 | D16: $/year
A17: Sales tax | B17: 1687.83 | C17: 86962.04 | D17: $/year
A18: Reagent make up | B18: 11833.76 | C18: 1183375.6 | D18: $/year
A19: Total | B19: 55179.26 | C19: 3403462.5 | D19: $/year
A20: Electrolyzer CAPEX
A21: Cell stack cost | B21: 59920 | C21: 5992000 | D21: $
A22: Balance of plant cost | B22: 67568 | C22: 6756800 | D22: $
A23: Installation | B23: 15298.08 | C23: 1529808 | D23: $
A24: Up-front permitting | B24: 35695.52 | C24: 3569552 | D24: $
A25: Engineering & design | B25: 19037.61 | C25: 1903761.1 | D25: $
A26: Site preparation expenses | B26: 4759.4 | C26: 475940.27 | D26: $
A27: Contingency expenses | B27: 35695.52 | C27: 3569552 | D27: $
A28: Total | B28: =SUM(B21:B27) -> 237974.13 | C28: =SUM(C21:C27) -> 23797413 | D28: $
A29: Electrolyzer OPEX
A30: Electricity | B30: 5.04 | C30: 504 | D30: $/year
A31: Replacement cost (every 7 year) | B31: 5108.47 | C31: 510846.6 | D31: $/year
A32: Fixed operation and maintenance | B32: 7151.85 | C32: 715182.24 | D32: $/year
A33: Total | B33: 12265.36 | C33: 1226535.8 | D33: $/year

Sheet Costing 100 Lmin Feed Orig
A1: S1 Stages | B1: S1 C_Pt_in [M] | C1: S1 C_Pd_in [M] | D1: S1 C_Rh_in [M] | E1: S1 q_Pt_in [mol PGM/mol ligand] | F1: S1 q_Pd_in [mol PGM/mol ligand] | G1: S1 q_Rh_in [mol PGM/mol ligand] | H1: S1 C_Pt_out [M] | I1: S1 C_Pd_out [M] | J1: S1 C_Rh_out [M] | K1: S1 q_Pt_out [mol PGM/mol ligand] | L1: S1 q_Pd_out [mol PGM/mol ligand] | M1: S1 q_Rh_out [mol PGM/mol ligand] | N1: S1 Material Residual Pt [mol PGM/time] | O1: S1 Material Residual Pd [mol PGM/time] | P1: S1 Material Residual Rh [mol PGM/time] | Q1: S1 Q_org [L/time] | R1: S1 PGM Recovery [%] | S1: S1 PPM Mass Total Feed [mg/L] | T1: S1 PGM Relative Purity [%] | U1: S1 Q_aq [L/time] | V1: S1 C_lig [L/time] | W1: S1 Q_aq/(Q_org*C_lig) [1/M] | X1: S1 Ligand | Y1: S1 ier | Z1: S1 q_max_Pt | AA1: S1 q_max_Pd | AB1: S1 q_max_Rh | AC1: S1 K_eq_Pt | AD1: S1 K_eq_Pd | AE1: S1 K_eq_Rh | AF1: S2 Stages | AG1: S2 C_Pt_in [M] | AH1: S2 C_Pd_in [M] | AI1: S2 C_Rh_in [M] | AJ1: S2 q_Pt_in [mol PGM/mol ligand] | AK1: S2 q_Pd_in [mol PGM/mol ligand] | AL1: S2 q_Rh_in [mol PGM/mol ligand] | AM1: S2 C_Pt_out [M] | AN1: S2 C_Pd_out [M] | AO1: S2 C_Rh_out [M] | AP1: S2 q_Pt_out [mol PGM/mol ligand] | AQ1: S2 q_Pd_out [mol PGM/mol ligand] | AR1: S2 q_Rh_out [mol PGM/mol ligand] | AS1: S2 Material Residual Pt [mol PGM/time] | AT1: S2 Material Residual Pd [mol PGM/time] | AU1: S2 Material Residual Rh [mol PGM/time] | AV1: S2 Q_org [L/time] | AW1: S2 PGM Recovery [%] | AX1: S2 PPM Mass Total Feed [mg/L] | AY1: S2 PGM Relative Purity [%] | AZ1: S2 Q_aq [L/time] | BA1: S2 C_lig [L/time] | BB1: S2 Q_aq/(Q_org*C_lig) [1/M] | BC1: S2 Ligand | BD1: S2 ier | BE1: S2 q_max_Pt | BF1: S2 q_max_Pd | BG1: S2 q_max_Rh | BH1: S2 K_eq_Pt | BI1: S2 K_eq_Pd | BJ1: S2 K_eq_Rh | BK1: S1 Q_aq Costing [L/min] | BL1: S1 Q_org Costing [L/min] | BM1: S2 Q_aq Costing [L/min] | BN1: S2 Q_org Costing [L/min] | BO1: I- in S1 [mol/min] | BP1: IO3- in S1 [mol/min] | BQ1: H+ in S1 [mol/min] | BR1: I3- [mol/min] | BS1: mols ddFc [mol/min] | BT1: Volume of Ox Prep Reactor [L] | BU1: Vol of Ox RCTR [L] | BV1: Sol Vol Reduction [L/min] | BW1: DI Water Needed in Red [L/min] | BX1: Vol of Red RCTR [L] | BY1: Vol of Precip RCTR [L] | BZ1: mol flow FeCl2 [mol/min] | CA1: ox prep | CB1: ox | CC1: red | CD1: precip | CE1: charge org [L] | CF1: charge lig [mol] | CG1: I- in S2 [mol/min] | CH1: IO3- in S2 [mol/min] | CI1: H+ in S2 [mol/min] | CJ1: I3- [mol/min] | CK1: mols coeFc [mol/min] | CL1: Volume of Ox Prep Reactor [L] | CM1: Vol of Ox RCTR [L] | CN1: Sol Vol Reduction [L/min] | CO1: DI Water Needed in Red [L/min] | CP1: Vol of Red RCTR [L] | CQ1: Vol of Precip RCTR [L] | CR1: mol flow FeCl2 [mol/min] | CS1: ox prep | CT1: ox | CU1: red | CV1: precip | CW1: charge org [L] | CX1: charge lig [mol] | CY1: salt flow S1 [mol/min] | CZ1: salt flow S2 [mol/min] | DA1: cost org chrg S1 | DB1: cost org chrg S2 | DC1: cost lig chrg S1 | DD1: cost lig chrg S2 | DE1: 10000 L/min to ST [for costing] | DK1: S1 labor | DL1: S1 Equip | DM1: S1 Steel | DN1: S1 Const | DO1: S1 Tax | DP1: CAPEX S1 | DQ1: S2 labor | DR1: S2 Equip | DS1: S2 Steel | DT1: S2 Const | DU1: S2 Tax | DV1: CAPEX S2 | DW1: Total CAPEX (2025$) | DX1: Annualized CAPEX assuming 15 year lifetime | DY1: I- in S1 [$/yr] | DZ1: IO3- in S1 [$/yr] | EA1: H+ in S1 [$/yr] | EB1: DCM Makeup S1 [$/yr] | EC1: ddFc Makeup [$/yr] | ED1: Salt S1 [$/yr] | EE1: Reductant S1 [$/yr] | EF1: FeCl2 Precip 1 [$/yr] | EG1: Waste S1 [$/yr] | EH1: I- in S2 [$/yr] | EI1: IO3- in S2 [$/yr] | EJ1: H+ in S2 [$/yr] | EK1: DCM Makeup S2 [$/yr] | EL1: coeFc Makeup [$/yr] | EM1: Salt S2 [$/yr] | EN1: Reductant S2 [$/yr] | EO1: FeCl2 Precip 2 [$/yr] | EP1: Waste S2 [$/yr] | EQ1: chemical opex with tariffs [$/yr] | ER1: total waste [$/yr] | ES1: opex labor S1 | ET1: opex equip S1 | EU1: opex steel S1 | EV1: opex lube S1 | EW1: opex sales tax S1 | EX1: opex S1 | EY1: opex labor S2 | EZ1: opex equip S2 | FA1: opex steel S2 | FB1: opex lube S2 | FC1: opex sales tax S2 | FD1: opex S2 | FE1: opex | FF1: TAC | FG1: Pt | FH1: Pd | FI1: Rh | FJ1: MAX Sales | FK1: PUB | FL1: Cost [$/L feed Process] | FM1: Cost [$/kg Pt Recov] | FN1: Cost [$/kg Pd Recov] | FO1: Cost [$/kg Rh Recov]
A2: 3 | B2: 0.0015414359 | C2: 0.0015414359 | D2: 0.0003425413 | E2: 0 | F2: 0 | G2: 0 | H2: 1.6300359e-05 | I2: 7.447486e-07 | J2: 0.00032385704 | K2: 0.080727109 | L2: 0.081550485 | M2: 0.00098897849 | N2: -9.8011876e-17 | O2: 1.9428903e-16 | P2: -4.3537493e-18 | Q2: 0.18892482 | R2: 94.5454 | S2: 500 | T2: 95 | U2: 1 | V2: 0.1 | W2: 52.931107 | X2: ddFc | Y2: 1 | Z2: 0.28318429 | AA2: 0.56945643 | AB2: 0.0037698629 | AC2: 1822.2108 | AD2: 2662.6059 | AE2: 2401.5031 | AF2: 4 | AG2: 0.0016455479 | AH2: 0.0016623316 | AI2: 2.0159417e-05 | AJ2: 0 | AK2: 0 | AL2: 0 | AM2: 0.0015983351 | AN2: 6.4131851e-05 | AO2: 1.999105e-05 | AP2: 0.0020409859 | AQ2: 0.069089456 | AR2: 7.2784255e-06 | AS2: -1.4297916e-18 | AT2: 2.4286129e-17 | AU2: -3.7851785e-21 | AV2: 0.21439626 | AW2: 99.164823 | AX2: 500 | AY2: 95 | AZ2: 0.92682535 | BA2: 0.1 | BB2: 43.229549 | BC2: coeFc | BD2: 1 | BE2: 0.018775015 | BF2: 0.10492961 | BG2: 0.001814625 | BH2: 285.19514 | BI2: 2169.8945 | BJ2: 866.49409 | BK2: =U2*100 -> 100 | BL2: =Q2*100 -> 18.892482 | BM2: =AZ2*100 -> 92.682535 | BN2: =AV2*100 -> 21.439626 | BO2: =0.6*1.2*BL2/2 -> 6.8012937 | BP2: =0.04*1.2*BL2/2 -> 0.45341958 | BQ2: =0.2*1.2*BL2/2 -> 2.2670979 | BR2: =0.1*1.2*BL2/2 -> 1.1335489 | BS2: =V2*BL2 -> 1.8892482 | BT2: =0.6*BL2*1 -> 11.335489 | BU2: =1.6*BL2*1 -> 30.227972 | BV2: =1*V2*BL2/0.2 -> 9.4462412 | BW2: =BM2-BV2 -> 83.236294 | BX2: =(SUM(BV2:BW2)+BL2)*1 -> 111.57502 | BY2: =BM2 -> 92.682535 | BZ2: =BL2*0.1*1.4 -> 2.6449475 | CA2: =7963.6*(BT2/1000)^0.6*1.7*('CAPEX+OPEX'!$G$116/'CAPEX+OPEX'!$G$115) -> 1086.1882 | CB2: =7963.6*(BU2/1000)^0.6*1.7*('CAPEX+OPEX'!$G$116/'CAPEX+OPEX'!$G$115) -> 1956.5292 | CC2: =7963.6*(BX2/1000)^0.6*1.7*('CAPEX+OPEX'!$G$116/'CAPEX+OPEX'!$G$115) -> 4283.3258 | CD2: =7963.6*(BY2/1000)^0.6*1.7*('CAPEX+OPEX'!$G$116/'CAPEX+OPEX'!$G$115) -> 3832.125 | CE2: 300 | CF2: 30 | CG2: =0.6*1.2*BN2/2 -> 7.7182652 | CH2: =0.04*1.2*BN2/2 -> 0.51455101 | CI2: =0.2*1.2*BN2/2 -> 2.5727551 | CJ2: =0.1*1.2*BN2/2 -> 1.2863775 | CK2: =0.1*BN2 -> 2.1439626 | CL2: =0.6*BN2*1 -> 12.863775 | CM2: =1.6*BN2*1 -> 34.303401 | CN2: =1*BA2*BN2/0.2 -> 10.719813 | CO2: 0 | CP2: =(SUM(CN2:CO2)+BN2)*1 -> 32.159438 | CQ2: =CN2 -> 10.719813 | CR2: =BN2*0.1*1.4 -> 3.0015476 | CS2: =7963.6*(CL2/1000)^0.6*1.7*('CAPEX+OPEX'!$G$116/'CAPEX+OPEX'!$G$115) -> 1171.8229 | CT2: =7963.6*(CM2/1000)^0.6*1.7*('CAPEX+OPEX'!$G$116/'CAPEX+OPEX'!$G$115) -> 2110.7813 | CU2: =7963.6*(CP2/1000)^0.6*1.7*('CAPEX+OPEX'!$G$116/'CAPEX+OPEX'!$G$115) -> 2030.6076 | CV2: =7963.6*(CQ2/1000)^0.6*1.7*('CAPEX+OPEX'!$G$116/'CAPEX+OPEX'!$G$115) -> 1050.3965 | CW2: 300 | CX2: =0.1*CW2 -> 30 | CY2: =0.1*BK2 -> 10 | CZ2: =0.1*BM2 -> 9.2682535 | DA2: =CE2*1.32*10 -> 3960 | DB2: =CW2*1.32*10 -> 3960 | DC2: =CF2*'Reagent cost'!$C$18/1000*'Reagent cost'!$H$18 -> 4784.4136 | DD2: =CX2*'Ligand cost'!$B$56*'Ligand cost'!$J$56 -> 30543.832 | DE2: =10000*1/3.78541*15 -> 39625.827 | DF2: =2510*(DE2^0.571)+89*DE2 -> 4586243.4 | DG2: =4810*(DE2^0.6)+228*DE2 -> 11794835 | DH2: =1030*(DE2^0.59)+44*DE2 -> 2275209.2 | DI2: =5640*(DE2^0.602)+272*DE2 -> 14083914 | DJ2: =688*(DE2^0.6)+32*DE2 -> 1662824.9 | DK2: =DF2*($BK$2/10000)^0.72*0.6*((A2+1)/3)^0.6*('CAPEX+OPEX'!$G$116/'CAPEX+OPEX'!$G$114) -> 277110.06 | DL2: =DG2*($BK$2/10000)^0.72*0.6*((A2+1)/3)^0.6*('CAPEX+OPEX'!$G$116/'CAPEX+OPEX'!$G$114) -> 712667.65 | DM2: =DH2*($BK$2/10000)^0.72*0.6*((A2+1)/3)^0.6*('CAPEX+OPEX'!$G$116/'CAPEX+OPEX'!$G$114) -> 137472.72 | DN2: =DI2*($BK$2/10000)^0.72*0.6*((A2+1)/3)^0.6*('CAPEX+OPEX'!$G$116/'CAPEX+OPEX'!$G$114) -> 850978.45 | DO2: =DJ2*($BK$2/10000)^0.72*0.6*((A2+1)/3)^0.6*('CAPEX+OPEX'!$G$116/'CAPEX+OPEX'!$G$114) -> 100471.23 | DP2: =SUM(DK2:DO2) -> 2078700.1 | DQ2: =DF2*(BM2/10000)^0.72*0.6*((AF2+1)/3)^0.6*('CAPEX+OPEX'!$G$116/'CAPEX+OPEX'!$G$114) -> 299941.66 | DR2: =DG2*(BM2/10000)^0.72*0.6*((AF2+1)/3)^0.6*('CAPEX+OPEX'!$G$116/'CAPEX+OPEX'!$G$114) -> 771385.63 | DS2: =DH2*(BM2/10000)^0.72*0.6*((AF2+1)/3)^0.6*('CAPEX+OPEX'!$G$116/'CAPEX+OPEX'!$G$114) -> 148799.34 | DT2: =DI2*(BM2/10000)^0.72*0.6*((AF2+1)/3)^0.6*('CAPEX+OPEX'!$G$116/'CAPEX+OPEX'!$G$114) -> 921092.11 | DU2: =DJ2*(BM2/10000)^0.72*0.6*((AF2+1)/3)^0.6*('CAPEX+OPEX'!$G$116/'CAPEX+OPEX'!$G$114) -> 108749.23 | DV2: =SUM(DQ2:DU2) -> 2249968 | DW2: =DV2+DP2+SUM(DA2:DD2)*1.15+SUM(CS2:CV2)*1.15+SUM(CA2:CD2)*1.15 -> 4398553.6 | DX2: =DW2/15 -> 293236.91 | DY2: =BO2*'Reagent cost'!$C$35*60*7200 -> 1761651.9 | DZ2: =BP2*'Reagent cost'!$C$34*60*7200 -> 419179.29 | EA2: =BQ2*'Reagent cost'!$C$14*'Reagent cost'!$C$36/1000*60*7200 -> 6948241.5 | EB2: =DA2*0.01 -> 39.6 | EC2: =DC2*0.02 -> 95.688272 | ED2: =0.1*BK2*60*7200*'Reagent cost'!$H$17*'Reagent cost'!$C$17/1000 -> 504921.6 | EE2: =BV2*0.1*'Reagent cost'!$C$16/1000*'Reagent cost'!$H$16*60*7200 -> 1723679.1 | EF2: =BZ2/1000*'Reagent cost'!$H$19*'Reagent cost'!$C$19*60*7200 -> 144826.75 | EG2: =0.33*('Costing 100 Lmin Feed Orig'!BO2*'Reagent cost'!$C$13+'Costing 100 Lmin Feed Orig'!BP2*'Reagent cost'!$C$12+'Costing 100 Lmin Feed Orig'!BQ2*'Reagent cost'!$C$14+'Costing 100 Lmin Feed Orig'!BV2*0.1*'Reagent cost'!$C$16+'Costing 100 Lmin Feed Orig'!BZ2*'Reagent cost'!$C$19)/1000*60*7200 -> 296311.85 | EH2: =CG2*'Reagent cost'!$C$35*60*7200 -> 1999163.3 | EI2: =CH2*'Reagent cost'!$C$34*60*7200 -> 475694.34 | EJ2: =CI2*'Reagent cost'!$C$14*'Reagent cost'!$C$36/1000*60*7200 -> 7885025 | EK2: =DB2*0.01 -> 39.6 | EL2: =DD2*0.02 -> 610.87664 | EM2: =0.1*BM2*60*7200*'Reagent cost'!$H$17*'Reagent cost'!$C$17/1000 -> 467974.14 | EN2: =CN2*0.1*'Reagent cost'!$C$16/1000*'Reagent cost'!$H$16*60*7200 -> 1956070.8 | EO2: =CR2/1000*'Reagent cost'!$H$19*'Reagent cost'!$C$19*60*7200 -> 164352.74 | EP2: =0.33*(CG2*'Reagent cost'!$C$13+CH2*'Reagent cost'!$C$12+CI2*'Reagent cost'!$C$14+CN2*0.1*'Reagent cost'!$C$16+CR2*'Reagent cost'!$C$19)/1000*60*7200 -> 336261.54 | EQ2: =(SUM(DY2:EF2)+SUM(EH2:EO2))*1.2 -> 29341879 | ER2: =EG2+EP2 -> 632573.39 | ES2: =0.499*((BK2/3.78541*15)^(-0.146))*BK2/3.78541*15*300*(1+(A2-2)/9) -> 27520.276 | ET2: =0.248*((BK2/3.78541*15)^(-0.144))*BK2/3.78541*15*300*(1+(A2-2)/3) -> 16610.44 | EU2: =0.105*((BK2/3.78541*15)^(-0.144))*BK2/3.78541*15*300*(1+(A2-2)/3) -> 7032.6458 | EV2: =0.058*((BK2/3.78541*15)^(-0.151))*BK2/3.78541*15*300*(1+(A2-2)/3) -> 3725.3887 | EW2: =0.056*((BK2/3.78541*15)^(-0.144))*BK2/3.78541*15*300*(1+(A2-2)/3) -> 3750.7444 | EX2: =SUM(ES2:EW2) -> 58639.495 | EY2: =0.499*((BM2/3.78541*15)^(-0.146))*BM2/3.78541*15*300*(1+(AF2-2)/9) -> 28370.153 | EZ2: =0.248*((BM2/3.78541*15)^(-0.144))*BM2/3.78541*15*300*(1+(AF2-2)/3) -> 19455.453 | FA2: =0.105*((BM2/3.78541*15)^(-0.144))*BM2/3.78541*15*300*(1+(AF2-2)/3) -> 8237.1877 | FB2: =0.058*((BM2/3.78541*15)^(-0.151))*BM2/3.78541*15*300*(1+(AF2-2)/3) -> 4365.7898 | FC2: =0.056*((BM2/3.78541*15)^(-0.144))*BM2/3.78541*15*300*(1+(AF2-2)/3) -> 4393.1668 | FD2: =SUM(EY2:FC2) -> 64821.751 | FE2: =EQ2+ER2+EX2+FD2 -> 30097914 | FF2: =FE2+DX2 -> 30391151 | FG2: =BM2*AM2*195.08/1000*'PGM market prices'!$C$2*60*7200 -> 4.2109757e+08 | FH2: =BN2*AQ2*BA2*106.42/1000*'PGM market prices'!$C$3*60*7200 -> 2.2424535e+08 | FI2: =BK2*J2*102.91/1000*'PGM market prices'!$C$4*60*7200 -> 2.3748534e+08 | FJ2: =SUM(FG2:FI2) -> 8.8282826e+08 | FK2: =(1-0.26)*(FJ2-FF2) -> 6.3080346e+08 | FL2: =FF2/(BK2*60*7200) -> 0.70349887 | FM2: =FF2/7200/60/(BM2*AM2*195.08/1000) -> 2434.3606 | FN2: =FF2/7200/60/(BN2*BA2*AQ2*106.42/1000) -> 4462.8385 | FO2: =FF2/(J2*BK2*102.91/1000*60*7200) -> 21108.262
A3: 3 | B3: 0.0015414359 | C3: 0.0015414359 | D3: 0.0003425413 | E3: 0 | F3: 0 | G3: 0 | H3: 1.6300359e-05 | I3: 7.447486e-07 | J3: 0.00032385704 | K3: 0.080727109 | L3: 0.081550485 | M3: 0.00098897849 | N3: -9.8011876e-17 | O3: 1.9428903e-16 | P3: -4.3537493e-18 | Q3: 0.18892482 | R3: 94.5454 | S3: 500 | T3: 95 | U3: 1 | V3: 0.1 | W3: 52.931107 | X3: ddFc | Y3: 1 | Z3: 0.28318429 | AA3: 0.56945643 | AB3: 0.0037698629 | AC3: 1822.2108 | AD3: 2662.6059 | AE3: 2401.5031 | AF3: 5 | AG3: 0.0016455479 | AH3: 0.0016623316 | AI3: 2.0159417e-05 | AJ3: 0 | AK3: 0 | AL3: 0 | AM3: 0.0016052842 | AN3: 6.4473619e-05 | AO3: 2.0015023e-05 | AP3: 0.0018300134 | AQ3: 0.072623818 | AR3: 6.562807e-06 | AS3: -1.0199429e-15 | AT3: -2.9988815e-14 | AU3: -1.2040044e-18 | AV3: 0.20391868 | AW3: 99.28374 | AX3: 500 | AY3: 95 | AZ3: 0.92682535 | BA3: 0.1 | BB3: 45.450733 | BC3: coeFc | BD3: 1 | BE3: 0.018775015 | BF3: 0.10492961 | BG3: 0.001814625 | BH3: 285.19514 | BI3: 2169.8945 | BJ3: 866.49409 | BK3: =U3*100 -> 100 | BL3: =Q3*100 -> 18.892482 | BM3: =AZ3*100 -> 92.682535 | BN3: =AV3*100 -> 20.391868 | BO3: =0.6*1.2*BL3/2 -> 6.8012937 | BP3: =0.04*1.2*BL3/2 -> 0.45341958 | BQ3: =0.2*1.2*BL3/2 -> 2.2670979 | BR3: =0.1*1.2*BL3/2 -> 1.1335489 | BS3: =V3*BL3 -> 1.8892482 | BT3: =0.6*BL3*1 -> 11.335489 | BU3: =1.6*BL3*1 -> 30.227972 | BV3: =1*V3*BL3/0.2 -> 9.4462412 | BW3: =BM3-BV3 -> 83.236294 | BX3: =(SUM(BV3:BW3)+BL3)*1 -> 111.57502 | BY3: =BM3 -> 92.682535 | BZ3: =BL3*0.1*1.4 -> 2.6449475 | CA3: =7963.6*(BT3/1000)^0.6*1.7*('CAPEX+OPEX'!$G$116/'CAPEX+OPEX'!$G$115) -> 1086.1882 | CB3: =7963.6*(BU3/1000)^0.6*1.7*('CAPEX+OPEX'!$G$116/'CAPEX+OPEX'!$G$115) -> 1956.5292 | CC3: =7963.6*(BX3/1000)^0.6*1.7*('CAPEX+OPEX'!$G$116/'CAPEX+OPEX'!$G$115) -> 4283.3258 | CD3: =7963.6*(BY3/1000)^0.6*1.7*('CAPEX+OPEX'!$G$116/'CAPEX+OPEX'!$G$115) -> 3832.125 | CE3: 300 | CF3: 30 | CG3: =0.6*1.2*BN3/2 -> 7.3410725 | CH3: =0.04*1.2*BN3/2 -> 0.48940483 | CI3: =0.2*1.2*BN3/2 -> 2.4470242 | CJ3: =0.1*1.2*BN3/2 -> 1.2235121 | CK3: =0.1*BN3 -> 2.0391868 | CL3: =0.6*BN3*1 -> 12.235121 | CM3: =1.6*BN3*1 -> 32.626989 | CN3: =1*BA3*BN3/0.2 -> 10.195934 | CO3: 0 | CP3: =(SUM(CN3:CO3)+BN3)*1 -> 30.587802 | CQ3: =CN3 -> 10.195934 | CR3: =BN3*0.1*1.4 -> 2.8548615 | CS3: =7963.6*(CL3/1000)^0.6*1.7*('CAPEX+OPEX'!$G$116/'CAPEX+OPEX'!$G$115) -> 1137.1189 | CT3: =7963.6*(CM3/1000)^0.6*1.7*('CAPEX+OPEX'!$G$116/'CAPEX+OPEX'!$G$115) -> 2048.2696 | CU3: =7963.6*(CP3/1000)^0.6*1.7*('CAPEX+OPEX'!$G$116/'CAPEX+OPEX'!$G$115) -> 1970.4703 | CV3: =7963.6*(CQ3/1000)^0.6*1.7*('CAPEX+OPEX'!$G$116/'CAPEX+OPEX'!$G$115) -> 1019.2885 | CW3: 300 | CX3: =0.1*CW3 -> 30 | CY3: =0.1*BK3 -> 10 | CZ3: =0.1*BM3 -> 9.2682535 | DA3: =CE3*1.32*10 -> 3960 | DB3: =CW3*1.32*10 -> 3960 | DC3: =CF3*'Reagent cost'!$C$18/1000*'Reagent cost'!$H$18 -> 4784.4136 | DD3: =CX3*'Ligand cost'!$B$56*'Ligand cost'!$J$56 -> 30543.832 | DE3: =10000*1/3.78541*15 -> 39625.827 | DF3: =2510*(DE3^0.571)+89*DE3 -> 4586243.4 | DG3: =4810*(DE3^0.6)+228*DE3 -> 11794835 | DH3: =1030*(DE3^0.59)+44*DE3 -> 2275209.2 | DI3: =5640*(DE3^0.602)+272*DE3 -> 14083914 | DJ3: =688*(DE3^0.6)+32*DE3 -> 1662824.9 | DK3: =DF3*($BK$2/10000)^0.72*0.6*((A3+1)/3)^0.6*('CAPEX+OPEX'!$G$116/'CAPEX+OPEX'!$G$114) -> 277110.06 | DL3: =DG3*($BK$2/10000)^0.72*0.6*((A3+1)/3)^0.6*('CAPEX+OPEX'!$G$116/'CAPEX+OPEX'!$G$114) -> 712667.65 | DM3: =DH3*($BK$2/10000)^0.72*0.6*((A3+1)/3)^0.6*('CAPEX+OPEX'!$G$116/'CAPEX+OPEX'!$G$114) -> 137472.72 | DN3: =DI3*($BK$2/10000)^0.72*0.6*((A3+1)/3)^0.6*('CAPEX+OPEX'!$G$116/'CAPEX+OPEX'!$G$114) -> 850978.45 | DO3: =DJ3*($BK$2/10000)^0.72*0.6*((A3+1)/3)^0.6*('CAPEX+OPEX'!$G$116/'CAPEX+OPEX'!$G$114) -> 100471.23 | DP3: =SUM(DK3:DO3) -> 2078700.1 | DQ3: =DF3*(BM3/10000)^0.72*0.6*((AF3+1)/3)^0.6*('CAPEX+OPEX'!$G$116/'CAPEX+OPEX'!$G$114) -> 334615.1 | DR3: =DG3*(BM3/10000)^0.72*0.6*((AF3+1)/3)^0.6*('CAPEX+OPEX'!$G$116/'CAPEX+OPEX'!$G$114) -> 860558.29 | DS3: =DH3*(BM3/10000)^0.72*0.6*((AF3+1)/3)^0.6*('CAPEX+OPEX'!$G$116/'CAPEX+OPEX'!$G$114) -> 166000.64 | DT3: =DI3*(BM3/10000)^0.72*0.6*((AF3+1)/3)^0.6*('CAPEX+OPEX'!$G$116/'CAPEX+OPEX'!$G$114) -> 1027570.9 | DU3: =DJ3*(BM3/10000)^0.72*0.6*((AF3+1)/3)^0.6*('CAPEX+OPEX'!$G$116/'CAPEX+OPEX'!$G$114) -> 121320.71 | DV3: =SUM(DQ3:DU3) -> 2510065.7 | DW3: =DV3+DP3+SUM(DA3:DD3)*1.15+SUM(CS3:CV3)*1.15+SUM(CA3:CD3)*1.15 -> 4658434.6 | DX3: =DW3/15 -> 310562.3 | DY3: =BO3*'Reagent cost'!$C$35*60*7200 -> 1761651.9 | DZ3: =BP3*'Reagent cost'!$C$34*60*7200 -> 419179.29 | EA3: =BQ3*'Reagent cost'!$C$14*'Reagent cost'!$C$36/1000*60*7200 -> 6948241.5 | EB3: =DA3*0.01 -> 39.6 | EC3: =DC3*0.02 -> 95.688272 | ED3: =0.1*BK3*60*7200*'Reagent cost'!$H$17*'Reagent cost'!$C$17/1000 -> 504921.6 | EE3: =BV3*0.1*'Reagent cost'!$C$16/1000*'Reagent cost'!$H$16*60*7200 -> 1723679.1 | EF3: =BZ3/1000*'Reagent cost'!$H$19*'Reagent cost'!$C$19*60*7200 -> 144826.75 | EG3: =0.33*('Costing 100 Lmin Feed Orig'!BO3*'Reagent cost'!$C$13+'Costing 100 Lmin Feed Orig'!BP3*'Reagent cost'!$C$12+'Costing 100 Lmin Feed Orig'!BQ3*'Reagent cost'!$C$14+'Costing 100 Lmin Feed Orig'!BV3*0.1*'Reagent cost'!$C$16+'Costing 100 Lmin Feed Orig'!BZ3*'Reagent cost'!$C$19)/1000*60*7200 -> 296311.85 | EH3: =CG3*'Reagent cost'!$C$35*60*7200 -> 1901463.9 | EI3: =CH3*'Reagent cost'!$C$34*60*7200 -> 452447.09 | EJ3: =CI3*'Reagent cost'!$C$14*'Reagent cost'!$C$36/1000*60*7200 -> 7499682.7 | EK3: =DB3*0.01 -> 39.6 | EL3: =DD3*0.02 -> 610.87664 | EM3: =0.1*BM3*60*7200*'Reagent cost'!$H$17*'Reagent cost'!$C$17/1000 -> 467974.14 | EN3: =CN3*0.1*'Reagent cost'!$C$16/1000*'Reagent cost'!$H$16*60*7200 -> 1860477.4 | EO3: =CR3/1000*'Reagent cost'!$H$19*'Reagent cost'!$C$19*60*7200 -> 156320.8 | EP3: =0.33*(CG3*'Reagent cost'!$C$13+CH3*'Reagent cost'!$C$12+CI3*'Reagent cost'!$C$14+CN3*0.1*'Reagent cost'!$C$16+CR3*'Reagent cost'!$C$19)/1000*60*7200 -> 319828.39 | EQ3: =(SUM(DY3:EF3)+SUM(EH3:EO3))*1.2 -> 28609982 | ER3: =EG3+EP3 -> 616140.24 | ES3: =0.499*((BK3/3.78541*15)^(-0.146))*BK3/3.78541*15*300*(1+(A3-2)/9) -> 27520.276 | ET3: =0.248*((BK3/3.78541*15)^(-0.144))*BK3/3.78541*15*300*(1+(A3-2)/3) -> 16610.44 | EU3: =0.105*((BK3/3.78541*15)^(-0.144))*BK3/3.78541*15*300*(1+(A3-2)/3) -> 7032.6458 | EV3: =0.058*((BK3/3.78541*15)^(-0.151))*BK3/3.78541*15*300*(1+(A3-2)/3) -> 3725.3887 | EW3: =0.056*((BK3/3.78541*15)^(-0.144))*BK3/3.78541*15*300*(1+(A3-2)/3) -> 3750.7444 | EX3: =SUM(ES3:EW3) -> 58639.495 | EY3: =0.499*((BM3/3.78541*15)^(-0.146))*BM3/3.78541*15*300*(1+(AF3-2)/9) -> 30949.258 | EZ3: =0.248*((BM3/3.78541*15)^(-0.144))*BM3/3.78541*15*300*(1+(AF3-2)/3) -> 23346.544 | FA3: =0.105*((BM3/3.78541*15)^(-0.144))*BM3/3.78541*15*300*(1+(AF3-2)/3) -> 9884.6253 | FB3: =0.058*((BM3/3.78541*15)^(-0.151))*BM3/3.78541*15*300*(1+(AF3-2)/3) -> 5238.9478 | FC3: =0.056*((BM3/3.78541*15)^(-0.144))*BM3/3.78541*15*300*(1+(AF3-2)/3) -> 5271.8002 | FD3: =SUM(EY3:FC3) -> 74691.175 | FE3: =EQ3+ER3+EX3+FD3 -> 29359453 | FF3: =FE3+DX3 -> 29670015 | FG3: =BM3*AM3*195.08/1000*'PGM market prices'!$C$2*60*7200 -> 4.2292838e+08 | FH3: =BN3*AQ3*BA3*106.42/1000*'PGM market prices'!$C$3*60*7200 -> 2.241974e+08 | FI3: =BK3*J3*102.91/1000*'PGM market prices'!$C$4*60*7200 -> 2.3748534e+08 | FJ3: =SUM(FG3:FI3) -> 8.8461111e+08 | FK3: =(1-0.26)*(FJ3-FF3) -> 6.3265641e+08 | FL3: =FF3/(BK3*60*7200) -> 0.68680591 | FM3: =FF3/7200/60/(BM3*AM3*195.08/1000) -> 2366.3089 | FN3: =FF3/7200/60/(BN3*BA3*AQ3*106.42/1000) -> 4357.8741 | FO3: =FF3/(J3*BK3*102.91/1000*60*7200) -> 20607.395
A4: 3 | B4: 0.0015414359 | C4: 0.0015414359 | D4: 0.0003425413 | E4: 0 | F4: 0 | G4: 0 | H4: 1.6300359e-05 | I4: 7.447486e-07 | J4: 0.00032385704 | K4: 0.080727109 | L4: 0.081550485 | M4: 0.00098897849 | N4: -9.8011876e-17 | O4: 1.9428903e-16 | P4: -4.3537493e-18 | Q4: 0.18892482 | R4: 94.5454 | S4: 500 | T4: 95 | U4: 1 | V4: 0.1 | W4: 52.931107 | X4: ddFc | Y4: 1 | Z4: 0.28318429 | AA4: 0.56945643 | AB4: 0.0037698629 | AC4: 1822.2108 | AD4: 2662.6059 | AE4: 2401.5031 | AF4: 6 | AG4: 0.0016455479 | AH4: 0.0016623316 | AI4: 2.0159417e-05 | AJ4: 0 | AK4: 0 | AL4: 0 | AM4: 0.0016074437 | AN4: 6.4579829e-05 | AO4: 2.0022473e-05 | AP4: 0.0017599626 | AQ4: 0.073797327 | AR4: 6.3252067e-06 | AS4: -1.5043305e-18 | AT4: 1.517883e-17 | AU4: -9.2908926e-21 | AV4: 0.20066267 | AW4: 99.320694 | AX4: 500 | AY4: 95 | AZ4: 0.92682535 | BA4: 0.1 | BB4: 46.18823 | BC4: coeFc | BD4: 1 | BE4: 0.018775015 | BF4: 0.10492961 | BG4: 0.001814625 | BH4: 285.19514 | BI4: 2169.8945 | BJ4: 866.49409 | BK4: =U4*100 -> 100 | BL4: =Q4*100 -> 18.892482 | BM4: =AZ4*100 -> 92.682535 | BN4: =AV4*100 -> 20.066267 | BO4: =0.6*1.2*BL4/2 -> 6.8012937 | BP4: =0.04*1.2*BL4/2 -> 0.45341958 | BQ4: =0.2*1.2*BL4/2 -> 2.2670979 | BR4: =0.1*1.2*BL4/2 -> 1.1335489 | BS4: =V4*BL4 -> 1.8892482 | BT4: =0.6*BL4*1 -> 11.335489 | BU4: =1.6*BL4*1 -> 30.227972 | BV4: =1*V4*BL4/0.2 -> 9.4462412 | BW4: =BM4-BV4 -> 83.236294 | BX4: =(SUM(BV4:BW4)+BL4)*1 -> 111.57502 | BY4: =BM4 -> 92.682535 | BZ4: =BL4*0.1*1.4 -> 2.6449475 | CA4: =7963.6*(BT4/1000)^0.6*1.7*('CAPEX+OPEX'!$G$116/'CAPEX+OPEX'!$G$115) -> 1086.1882 | CB4: =7963.6*(BU4/1000)^0.6*1.7*('CAPEX+OPEX'!$G$116/'CAPEX+OPEX'!$G$115) -> 1956.5292 | CC4: =7963.6*(BX4/1000)^0.6*1.7*('CAPEX+OPEX'!$G$116/'CAPEX+OPEX'!$G$115) -> 4283.3258 | CD4: =7963.6*(BY4/1000)^0.6*1.7*('CAPEX+OPEX'!$G$116/'CAPEX+OPEX'!$G$115) -> 3832.125 | CE4: 300 | CF4: 30 | CG4: =0.6*1.2*BN4/2 -> 7.2238562 | CH4: =0.04*1.2*BN4/2 -> 0.48159041 | CI4: =0.2*1.2*BN4/2 -> 2.4079521 | CJ4: =0.1*1.2*BN4/2 -> 1.203976 | CK4: =0.1*BN4 -> 2.0066267 | CL4: =0.6*BN4*1 -> 12.03976 | CM4: =1.6*BN4*1 -> 32.106027 | CN4: =1*BA4*BN4/0.2 -> 10.033134 | CO4: 0 | CP4: =(SUM(CN4:CO4)+BN4)*1 -> 30.099401 | CQ4: =CN4 -> 10.033134 | CR4: =BN4*0.1*1.4 -> 2.8092774 | CS4: =7963.6*(CL4/1000)^0.6*1.7*('CAPEX+OPEX'!$G$116/'CAPEX+OPEX'!$G$115) -> 1126.1899 | CT4: =7963.6*(CM4/1000)^0.6*1.7*('CAPEX+OPEX'!$G$116/'CAPEX+OPEX'!$G$115) -> 2028.5834 | CU4: =7963.6*(CP4/1000)^0.6*1.7*('CAPEX+OPEX'!$G$116/'CAPEX+OPEX'!$G$115) -> 1951.5318 | CV4: =7963.6*(CQ4/1000)^0.6*1.7*('CAPEX+OPEX'!$G$116/'CAPEX+OPEX'!$G$115) -> 1009.492 | CW4: 300 | CX4: =0.1*CW4 -> 30 | CY4: =0.1*BK4 -> 10 | CZ4: =0.1*BM4 -> 9.2682535 | DA4: =CE4*1.32*10 -> 3960 | DB4: =CW4*1.32*10 -> 3960 | DC4: =CF4*'Reagent cost'!$C$18/1000*'Reagent cost'!$H$18 -> 4784.4136 | DD4: =CX4*'Ligand cost'!$B$56*'Ligand cost'!$J$56 -> 30543.832 | DE4: =10000*1/3.78541*15 -> 39625.827 | DF4: =2510*(DE4^0.571)+89*DE4 -> 4586243.4 | DG4: =4810*(DE4^0.6)+228*DE4 -> 11794835 | DH4: =1030*(DE4^0.59)+44*DE4 -> 2275209.2 | DI4: =5640*(DE4^0.602)+272*DE4 -> 14083914 | DJ4: =688*(DE4^0.6)+32*DE4 -> 1662824.9 | DK4: =DF4*($BK$2/10000)^0.72*0.6*((A4+1)/3)^0.6*('CAPEX+OPEX'!$G$116/'CAPEX+OPEX'!$G$114) -> 277110.06 | DL4: =DG4*($BK$2/10000)^0.72*0.6*((A4+1)/3)^0.6*('CAPEX+OPEX'!$G$116/'CAPEX+OPEX'!$G$114) -> 712667.65 | DM4: =DH4*($BK$2/10000)^0.72*0.6*((A4+1)/3)^0.6*('CAPEX+OPEX'!$G$116/'CAPEX+OPEX'!$G$114) -> 137472.72 | DN4: =DI4*($BK$2/10000)^0.72*0.6*((A4+1)/3)^0.6*('CAPEX+OPEX'!$G$116/'CAPEX+OPEX'!$G$114) -> 850978.45 | DO4: =DJ4*($BK$2/10000)^0.72*0.6*((A4+1)/3)^0.6*('CAPEX+OPEX'!$G$116/'CAPEX+OPEX'!$G$114) -> 100471.23 | DP4: =SUM(DK4:DO4) -> 2078700.1 | DQ4: =DF4*(BM4/10000)^0.72*0.6*((AF4+1)/3)^0.6*('CAPEX+OPEX'!$G$116/'CAPEX+OPEX'!$G$114) -> 367040.18 | DR4: =DG4*(BM4/10000)^0.72*0.6*((AF4+1)/3)^0.6*('CAPEX+OPEX'!$G$116/'CAPEX+OPEX'!$G$114) -> 943948.64 | DS4: =DH4*(BM4/10000)^0.72*0.6*((AF4+1)/3)^0.6*('CAPEX+OPEX'!$G$116/'CAPEX+OPEX'!$G$114) -> 182086.54 | DT4: =DI4*(BM4/10000)^0.72*0.6*((AF4+1)/3)^0.6*('CAPEX+OPEX'!$G$116/'CAPEX+OPEX'!$G$114) -> 1127145.2 | DU4: =DJ4*(BM4/10000)^0.72*0.6*((AF4+1)/3)^0.6*('CAPEX+OPEX'!$G$116/'CAPEX+OPEX'!$G$114) -> 133077.01 | DV4: =SUM(DQ4:DU4) -> 2753297.6 | DW4: =DV4+DP4+SUM(DA4:DD4)*1.15+SUM(CS4:CV4)*1.15+SUM(CA4:CD4)*1.15 -> 4901598.3 | DX4: =DW4/15 -> 326773.22 | DY4: =BO4*'Reagent cost'!$C$35*60*7200 -> 1761651.9 | DZ4: =BP4*'Reagent cost'!$C$34*60*7200 -> 419179.29 | EA4: =BQ4*'Reagent cost'!$C$14*'Reagent cost'!$C$36/1000*60*7200 -> 6948241.5 | EB4: =DA4*0.01 -> 39.6 | EC4: =DC4*0.02 -> 95.688272 | ED4: =0.1*BK4*60*7200*'Reagent cost'!$H$17*'Reagent cost'!$C$17/1000 -> 504921.6 | EE4: =BV4*0.1*'Reagent cost'!$C$16/1000*'Reagent cost'!$H$16*60*7200 -> 1723679.1 | EF4: =BZ4/1000*'Reagent cost'!$H$19*'Reagent cost'!$C$19*60*7200 -> 144826.75 | EG4: =0.33*('Costing 100 Lmin Feed Orig'!BO4*'Reagent cost'!$C$13+'Costing 100 Lmin Feed Orig'!BP4*'Reagent cost'!$C$12+'Costing 100 Lmin Feed Orig'!BQ4*'Reagent cost'!$C$14+'Costing 100 Lmin Feed Orig'!BV4*0.1*'Reagent cost'!$C$16+'Costing 100 Lmin Feed Orig'!BZ4*'Reagent cost'!$C$19)/1000*60*7200 -> 296311.85 | EH4: =CG4*'Reagent cost'!$C$35*60*7200 -> 1871102.8 | EI4: =CH4*'Reagent cost'!$C$34*60*7200 -> 445222.78 | EJ4: =CI4*'Reagent cost'!$C$14*'Reagent cost'!$C$36/1000*60*7200 -> 7379933.9 | EK4: =DB4*0.01 -> 39.6 | EL4: =DD4*0.02 -> 610.87664 | EM4: =0.1*BM4*60*7200*'Reagent cost'!$H$17*'Reagent cost'!$C$17/1000 -> 467974.14 | EN4: =CN4*0.1*'Reagent cost'!$C$16/1000*'Reagent cost'!$H$16*60*7200 -> 1830770.8 | EO4: =CR4/1000*'Reagent cost'!$H$19*'Reagent cost'!$C$19*60*7200 -> 153824.79 | EP4: =0.33*(CG4*'Reagent cost'!$C$13+CH4*'Reagent cost'!$C$12+CI4*'Reagent cost'!$C$14+CN4*0.1*'Reagent cost'!$C$16+CR4*'Reagent cost'!$C$19)/1000*60*7200 -> 314721.63 | EQ4: =(SUM(DY4:EF4)+SUM(EH4:EO4))*1.2 -> 28382538 | ER4: =EG4+EP4 -> 611033.48 | ES4: =0.499*((BK4/3.78541*15)^(-0.146))*BK4/3.78541*15*300*(1+(A4-2)/9) -> 27520.276 | ET4: =0.248*((BK4/3.78541*15)^(-0.144))*BK4/3.78541*15*300*(1+(A4-2)/3) -> 16610.44 | EU4: =0.105*((BK4/3.78541*15)^(-0.144))*BK4/3.78541*15*300*(1+(A4-2)/3) -> 7032.6458 | EV4: =0.058*((BK4/3.78541*15)^(-0.151))*BK4/3.78541*15*300*(1+(A4-2)/3) -> 3725.3887 | EW4: =0.056*((BK4/3.78541*15)^(-0.144))*BK4/3.78541*15*300*(1+(A4-2)/3) -> 3750.7444 | EX4: =SUM(ES4:EW4) -> 58639.495 | EY4: =0.499*((BM4/3.78541*15)^(-0.146))*BM4/3.78541*15*300*(1+(AF4-2)/9) -> 33528.363 | EZ4: =0.248*((BM4/3.78541*15)^(-0.144))*BM4/3.78541*15*300*(1+(AF4-2)/3) -> 27237.634 | FA4: =0.105*((BM4/3.78541*15)^(-0.144))*BM4/3.78541*15*300*(1+(AF4-2)/3) -> 11532.063 | FB4: =0.058*((BM4/3.78541*15)^(-0.151))*BM4/3.78541*15*300*(1+(AF4-2)/3) -> 6112.1058 | FC4: =0.056*((BM4/3.78541*15)^(-0.144))*BM4/3.78541*15*300*(1+(AF4-2)/3) -> 6150.4335 | FD4: =SUM(EY4:FC4) -> 84560.599 | FE4: =EQ4+ER4+EX4+FD4 -> 29136772 | FF4: =FE4+DX4 -> 29463545 | FG4: =BM4*AM4*195.08/1000*'PGM market prices'!$C$2*60*7200 -> 4.2349733e+08 | FH4: =BN4*AQ4*BA4*106.42/1000*'PGM market prices'!$C$3*60*7200 -> 2.241825e+08 | FI4: =BK4*J4*102.91/1000*'PGM market prices'!$C$4*60*7200 -> 2.3748534e+08 | FJ4: =SUM(FG4:FI4) -> 8.8516516e+08 | FK4: =(1-0.26)*(FJ4-FF4) -> 6.332192e+08 | FL4: =FF4/(BK4*60*7200) -> 0.6820265 | FM4: =FF4/7200/60/(BM4*AM4*195.08/1000) -> 2346.6851 | FN4: =FF4/7200/60/(BN4*BA4*AQ4*106.42/1000) -> 4327.8358 | FO4: =FF4/(J4*BK4*102.91/1000*60*7200) -> 20463.991
A5: 3 | B5: 0.0015414359 | C5: 0.0015414359 | D5: 0.0003425413 | E5: 0 | F5: 0 | G5: 0 | H5: 1.6300359e-05 | I5: 7.447486e-07 | J5: 0.00032385704 | K5: 0.080727109 | L5: 0.081550485 | M5: 0.00098897849 | N5: -9.8011876e-17 | O5: 1.9428903e-16 | P5: -4.3537493e-18 | Q5: 0.18892482 | R5: 94.5454 | S5: 500 | T5: 95 | U5: 1 | V5: 0.1 | W5: 52.931107 | X5: ddFc | Y5: 1 | Z5: 0.28318429 | AA5: 0.56945643 | AB5: 0.0037698629 | AC5: 1822.2108 | AD5: 2662.6059 | AE5: 2401.5031 | AF5: 7 | AG5: 0.0016455479 | AH5: 0.0016623316 | AI5: 2.0159417e-05 | AJ5: 0 | AK5: 0 | AL5: 0 | AM5: 0.0016080895 | AN5: 6.4611589e-05 | AO5: 2.00247e-05 | AP5: 0.0017385721 | AQ5: 0.074155665 | AR5: 6.2526541e-06 | AS5: -2.2083843e-17 | AT5: -3.749388e-15 | AU5: -5.9159957e-20 | AV5: 0.19968905 | AW5: 99.331744 | AX5: 500 | AY5: 95 | AZ5: 0.92682535 | BA5: 0.1 | BB5: 46.413428 | BC5: coeFc | BD5: 1 | BE5: 0.018775015 | BF5: 0.10492961 | BG5: 0.001814625 | BH5: 285.19514 | BI5: 2169.8945 | BJ5: 866.49409 | BK5: =U5*100 -> 100 | BL5: =Q5*100 -> 18.892482 | BM5: =AZ5*100 -> 92.682535 | BN5: =AV5*100 -> 19.968905 | BO5: =0.6*1.2*BL5/2 -> 6.8012937 | BP5: =0.04*1.2*BL5/2 -> 0.45341958 | BQ5: =0.2*1.2*BL5/2 -> 2.2670979 | BR5: =0.1*1.2*BL5/2 -> 1.1335489 | BS5: =V5*BL5 -> 1.8892482 | BT5: =0.6*BL5*1 -> 11.335489 | BU5: =1.6*BL5*1 -> 30.227972 | BV5: =1*V5*BL5/0.2 -> 9.4462412 | BW5: =BM5-BV5 -> 83.236294 | BX5: =(SUM(BV5:BW5)+BL5)*1 -> 111.57502 | BY5: =BM5 -> 92.682535 | BZ5: =BL5*0.1*1.4 -> 2.6449475 | CA5: =7963.6*(BT5/1000)^0.6*1.7*('CAPEX+OPEX'!$G$116/'CAPEX+OPEX'!$G$115) -> 1086.1882 | CB5: =7963.6*(BU5/1000)^0.6*1.7*('CAPEX+OPEX'!$G$116/'CAPEX+OPEX'!$G$115) -> 1956.5292 | CC5: =7963.6*(BX5/1000)^0.6*1.7*('CAPEX+OPEX'!$G$116/'CAPEX+OPEX'!$G$115) -> 4283.3258 | CD5: =7963.6*(BY5/1000)^0.6*1.7*('CAPEX+OPEX'!$G$116/'CAPEX+OPEX'!$G$115) -> 3832.125 | CE5: 300 | CF5: 30 | CG5: =0.6*1.2*BN5/2 -> 7.1888059 | CH5: =0.04*1.2*BN5/2 -> 0.47925373 | CI5: =0.2*1.2*BN5/2 -> 2.3962686 | CJ5: =0.1*1.2*BN5/2 -> 1.1981343 | CK5: =0.1*BN5 -> 1.9968905 | CL5: =0.6*BN5*1 -> 11.981343 | CM5: =1.6*BN5*1 -> 31.950248 | CN5: =1*BA5*BN5/0.2 -> 9.9844526 | CO5: 0 | CP5: =(SUM(CN5:CO5)+BN5)*1 -> 29.953358 | CQ5: =CN5 -> 9.9844526 | CR5: =BN5*0.1*1.4 -> 2.7956467 | CS5: =7963.6*(CL5/1000)^0.6*1.7*('CAPEX+OPEX'!$G$116/'CAPEX+OPEX'!$G$115) -> 1122.9081 | CT5: =7963.6*(CM5/1000)^0.6*1.7*('CAPEX+OPEX'!$G$116/'CAPEX+OPEX'!$G$115) -> 2022.672 | CU5: =7963.6*(CP5/1000)^0.6*1.7*('CAPEX+OPEX'!$G$116/'CAPEX+OPEX'!$G$115) -> 1945.845 | CV5: =7963.6*(CQ5/1000)^0.6*1.7*('CAPEX+OPEX'!$G$116/'CAPEX+OPEX'!$G$115) -> 1006.5503 | CW5: 300 | CX5: =0.1*CW5 -> 30 | CY5: =0.1*BK5 -> 10 | CZ5: =0.1*BM5 -> 9.2682535 | DA5: =CE5*1.32*10 -> 3960 | DB5: =CW5*1.32*10 -> 3960 | DC5: =CF5*'Reagent cost'!$C$18/1000*'Reagent cost'!$H$18 -> 4784.4136 | DD5: =CX5*'Ligand cost'!$B$56*'Ligand cost'!$J$56 -> 30543.832 | DE5: =10000*1/3.78541*15 -> 39625.827 | DF5: =2510*(DE5^0.571)+89*DE5 -> 4586243.4 | DG5: =4810*(DE5^0.6)+228*DE5 -> 11794835 | DH5: =1030*(DE5^0.59)+44*DE5 -> 2275209.2 | DI5: =5640*(DE5^0.602)+272*DE5 -> 14083914 | DJ5: =688*(DE5^0.6)+32*DE5 -> 1662824.9 | DK5: =DF5*($BK$2/10000)^0.72*0.6*((A5+1)/3)^0.6*('CAPEX+OPEX'!$G$116/'CAPEX+OPEX'!$G$114) -> 277110.06 | DL5: =DG5*($BK$2/10000)^0.72*0.6*((A5+1)/3)^0.6*('CAPEX+OPEX'!$G$116/'CAPEX+OPEX'!$G$114) -> 712667.65 | DM5: =DH5*($BK$2/10000)^0.72*0.6*((A5+1)/3)^0.6*('CAPEX+OPEX'!$G$116/'CAPEX+OPEX'!$G$114) -> 137472.72 | DN5: =DI5*($BK$2/10000)^0.72*0.6*((A5+1)/3)^0.6*('CAPEX+OPEX'!$G$116/'CAPEX+OPEX'!$G$114) -> 850978.45 | DO5: =DJ5*($BK$2/10000)^0.72*0.6*((A5+1)/3)^0.6*('CAPEX+OPEX'!$G$116/'CAPEX+OPEX'!$G$114) -> 100471.23 | DP5: =SUM(DK5:DO5) -> 2078700.1 | DQ5: =DF5*(BM5/10000)^0.72*0.6*((AF5+1)/3)^0.6*('CAPEX+OPEX'!$G$116/'CAPEX+OPEX'!$G$114) -> 397657.14 | DR5: =DG5*(BM5/10000)^0.72*0.6*((AF5+1)/3)^0.6*('CAPEX+OPEX'!$G$116/'CAPEX+OPEX'!$G$114) -> 1022688.9 | DS5: =DH5*(BM5/10000)^0.72*0.6*((AF5+1)/3)^0.6*('CAPEX+OPEX'!$G$116/'CAPEX+OPEX'!$G$114) -> 197275.43 | DT5: =DI5*(BM5/10000)^0.72*0.6*((AF5+1)/3)^0.6*('CAPEX+OPEX'!$G$116/'CAPEX+OPEX'!$G$114) -> 1221167 | DU5: =DJ5*(BM5/10000)^0.72*0.6*((AF5+1)/3)^0.6*('CAPEX+OPEX'!$G$116/'CAPEX+OPEX'!$G$114) -> 144177.73 | DV5: =SUM(DQ5:DU5) -> 2982966.2 | DW5: =DV5+DP5+SUM(DA5:DD5)*1.15+SUM(CS5:CV5)*1.15+SUM(CA5:CD5)*1.15 -> 5131246.3 | DX5: =DW5/15 -> 342083.09 | DY5: =BO5*'Reagent cost'!$C$35*60*7200 -> 1761651.9 | DZ5: =BP5*'Reagent cost'!$C$34*60*7200 -> 419179.29 | EA5: =BQ5*'Reagent cost'!$C$14*'Reagent cost'!$C$36/1000*60*7200 -> 6948241.5 | EB5: =DA5*0.01 -> 39.6 | EC5: =DC5*0.02 -> 95.688272 | ED5: =0.1*BK5*60*7200*'Reagent cost'!$H$17*'Reagent cost'!$C$17/1000 -> 504921.6 | EE5: =BV5*0.1*'Reagent cost'!$C$16/1000*'Reagent cost'!$H$16*60*7200 -> 1723679.1 | EF5: =BZ5/1000*'Reagent cost'!$H$19*'Reagent cost'!$C$19*60*7200 -> 144826.75 | EG5: =0.33*('Costing 100 Lmin Feed Orig'!BO5*'Reagent cost'!$C$13+'Costing 100 Lmin Feed Orig'!BP5*'Reagent cost'!$C$12+'Costing 100 Lmin Feed Orig'!BQ5*'Reagent cost'!$C$14+'Costing 100 Lmin Feed Orig'!BV5*0.1*'Reagent cost'!$C$16+'Costing 100 Lmin Feed Orig'!BZ5*'Reagent cost'!$C$19)/1000*60*7200 -> 296311.85 | EH5: =CG5*'Reagent cost'!$C$35*60*7200 -> 1862024.2 | EI5: =CH5*'Reagent cost'!$C$34*60*7200 -> 443062.56 | EJ5: =CI5*'Reagent cost'!$C$14*'Reagent cost'!$C$36/1000*60*7200 -> 7344126.3 | EK5: =DB5*0.01 -> 39.6 | EL5: =DD5*0.02 -> 610.87664 | EM5: =0.1*BM5*60*7200*'Reagent cost'!$H$17*'Reagent cost'!$C$17/1000 -> 467974.14 | EN5: =CN5*0.1*'Reagent cost'!$C$16/1000*'Reagent cost'!$H$16*60*7200 -> 1821887.8 | EO5: =CR5/1000*'Reagent cost'!$H$19*'Reagent cost'!$C$19*60*7200 -> 153078.43 | EP5: =0.33*(CG5*'Reagent cost'!$C$13+CH5*'Reagent cost'!$C$12+CI5*'Reagent cost'!$C$14+CN5*0.1*'Reagent cost'!$C$16+CR5*'Reagent cost'!$C$19)/1000*60*7200 -> 313194.59 | EQ5: =(SUM(DY5:EF5)+SUM(EH5:EO5))*1.2 -> 28314527 | ER5: =EG5+EP5 -> 609506.44 | ES5: =0.499*((BK5/3.78541*15)^(-0.146))*BK5/3.78541*15*300*(1+(A5-2)/9) -> 27520.276 | ET5: =0.248*((BK5/3.78541*15)^(-0.144))*BK5/3.78541*15*300*(1+(A5-2)/3) -> 16610.44 | EU5: =0.105*((BK5/3.78541*15)^(-0.144))*BK5/3.78541*15*300*(1+(A5-2)/3) -> 7032.6458 | EV5: =0.058*((BK5/3.78541*15)^(-0.151))*BK5/3.78541*15*300*(1+(A5-2)/3) -> 3725.3887 | EW5: =0.056*((BK5/3.78541*15)^(-0.144))*BK5/3.78541*15*300*(1+(A5-2)/3) -> 3750.7444 | EX5: =SUM(ES5:EW5) -> 58639.495 | EY5: =0.499*((BM5/3.78541*15)^(-0.146))*BM5/3.78541*15*300*(1+(AF5-2)/9) -> 36107.468 | EZ5: =0.248*((BM5/3.78541*15)^(-0.144))*BM5/3.78541*15*300*(1+(AF5-2)/3) -> 31128.725 | FA5: =0.105*((BM5/3.78541*15)^(-0.144))*BM5/3.78541*15*300*(1+(AF5-2)/3) -> 13179.5 | FB5: =0.058*((BM5/3.78541*15)^(-0.151))*BM5/3.78541*15*300*(1+(AF5-2)/3) -> 6985.2637 | FC5: =0.056*((BM5/3.78541*15)^(-0.144))*BM5/3.78541*15*300*(1+(AF5-2)/3) -> 7029.0669 | FD5: =SUM(EY5:FC5) -> 94430.024 | FE5: =EQ5+ER5+EX5+FD5 -> 29077103 | FF5: =FE5+DX5 -> 29419186 | FG5: =BM5*AM5*195.08/1000*'PGM market prices'!$C$2*60*7200 -> 4.2366746e+08 | FH5: =BN5*AQ5*BA5*106.42/1000*'PGM market prices'!$C$3*60*7200 -> 2.2417804e+08 | FI5: =BK5*J5*102.91/1000*'PGM market prices'!$C$4*60*7200 -> 2.3748534e+08 | FJ5: =SUM(FG5:FI5) -> 8.8533083e+08 | FK5: =(1-0.26)*(FJ5-FF5) -> 6.3337462e+08 | FL5: =FF5/(BK5*60*7200) -> 0.68099968 | FM5: =FF5/7200/60/(BM5*AM5*195.08/1000) -> 2342.2111 | FN5: =FF5/7200/60/(BN5*BA5*AQ5*106.42/1000) -> 4321.4059 | FO5: =FF5/(J5*BK5*102.91/1000*60*7200) -> 20433.181
A6: 3 | B6: 0.0015414359 | C6: 0.0015414359 | D6: 0.0003425413 | E6: 0 | F6: 0 | G6: 0 | H6: 1.6300359e-05 | I6: 7.447486e-07 | J6: 0.00032385704 | K6: 0.080727109 | L6: 0.081550485 | M6: 0.00098897849 | N6: -9.8011876e-17 | O6: 1.9428903e-16 | P6: -4.3537493e-18 | Q6: 0.18892482 | R6: 94.5454 | S6: 500 | T6: 95 | U6: 1 | V6: 0.1 | W6: 52.931107 | X6: ddFc | Y6: 1 | Z6: 0.28318429 | AA6: 0.56945643 | AB6: 0.0037698629 | AC6: 1822.2108 | AD6: 2662.6059 | AE6: 2401.5031 | AF6: 8 | AG6: 0.0016455479 | AH6: 0.0016623316 | AI6: 2.0159417e-05 | AJ6: 0 | AK6: 0 | AL6: 0 | AM6: 0.0016082777 | AN6: 6.4620844e-05 | AO6: 2.002535e-05 | AP6: 0.0017322992 | AQ6: 0.074260751 | AR6: 6.2313774e-06 | AS6: 8.2236735e-17 | AT6: -2.2797736e-14 | AU6: -1.8290618e-20 | AV6: 0.19940532 | AW6: 99.334964 | AX6: 500 | AY6: 95 | AZ6: 0.92682535 | BA6: 0.1 | BB6: 46.47947 | BC6: coeFc | BD6: 1 | BE6: 0.018775015 | BF6: 0.10492961 | BG6: 0.001814625 | BH6: 285.19514 | BI6: 2169.8945 | BJ6: 866.49409 | BK6: =U6*100 -> 100 | BL6: =Q6*100 -> 18.892482 | BM6: =AZ6*100 -> 92.682535 | BN6: =AV6*100 -> 19.940532 | BO6: =0.6*1.2*BL6/2 -> 6.8012937 | BP6: =0.04*1.2*BL6/2 -> 0.45341958 | BQ6: =0.2*1.2*BL6/2 -> 2.2670979 | BR6: =0.1*1.2*BL6/2 -> 1.1335489 | BS6: =V6*BL6 -> 1.8892482 | BT6: =0.6*BL6*1 -> 11.335489 | BU6: =1.6*BL6*1 -> 30.227972 | BV6: =1*V6*BL6/0.2 -> 9.4462412 | BW6: =BM6-BV6 -> 83.236294 | BX6: =(SUM(BV6:BW6)+BL6)*1 -> 111.57502 | BY6: =BM6 -> 92.682535 | BZ6: =BL6*0.1*1.4 -> 2.6449475 | CA6: =7963.6*(BT6/1000)^0.6*1.7*('CAPEX+OPEX'!$G$116/'CAPEX+OPEX'!$G$115) -> 1086.1882 | CB6: =7963.6*(BU6/1000)^0.6*1.7*('CAPEX+OPEX'!$G$116/'CAPEX+OPEX'!$G$115) -> 1956.5292 | CC6: =7963.6*(BX6/1000)^0.6*1.7*('CAPEX+OPEX'!$G$116/'CAPEX+OPEX'!$G$115) -> 4283.3258 | CD6: =7963.6*(BY6/1000)^0.6*1.7*('CAPEX+OPEX'!$G$116/'CAPEX+OPEX'!$G$115) -> 3832.125 | CE6: 300 | CF6: 30 | CG6: =0.6*1.2*BN6/2 -> 7.1785915 | CH6: =0.04*1.2*BN6/2 -> 0.47857277 | CI6: =0.2*1.2*BN6/2 -> 2.3928638 | CJ6: =0.1*1.2*BN6/2 -> 1.1964319 | CK6: =0.1*BN6 -> 1.9940532 | CL6: =0.6*BN6*1 -> 11.964319 | CM6: =1.6*BN6*1 -> 31.904851 | CN6: =1*BA6*BN6/0.2 -> 9.9702659 | CO6: 0 | CP6: =(SUM(CN6:CO6)+BN6)*1 -> 29.910798 | CQ6: =CN6 -> 9.9702659 | CR6: =BN6*0.1*1.4 -> 2.7916745 | CS6: =7963.6*(CL6/1000)^0.6*1.7*('CAPEX+OPEX'!$G$116/'CAPEX+OPEX'!$G$115) -> 1121.9506 | CT6: =7963.6*(CM6/1000)^0.6*1.7*('CAPEX+OPEX'!$G$116/'CAPEX+OPEX'!$G$115) -> 2020.9472 | CU6: =7963.6*(CP6/1000)^0.6*1.7*('CAPEX+OPEX'!$G$116/'CAPEX+OPEX'!$G$115) -> 1944.1856 | CV6: =7963.6*(CQ6/1000)^0.6*1.7*('CAPEX+OPEX'!$G$116/'CAPEX+OPEX'!$G$115) -> 1005.6919 | CW6: 300 | CX6: =0.1*CW6 -> 30 | CY6: =0.1*BK6 -> 10 | CZ6: =0.1*BM6 -> 9.2682535 | DA6: =CE6*1.32*10 -> 3960 | DB6: =CW6*1.32*10 -> 3960 | DC6: =CF6*'Reagent cost'!$C$18/1000*'Reagent cost'!$H$18 -> 4784.4136 | DD6: =CX6*'Ligand cost'!$B$56*'Ligand cost'!$J$56 -> 30543.832 | DE6: =10000*1/3.78541*15 -> 39625.827 | DF6: =2510*(DE6^0.571)+89*DE6 -> 4586243.4 | DG6: =4810*(DE6^0.6)+228*DE6 -> 11794835 | DH6: =1030*(DE6^0.59)+44*DE6 -> 2275209.2 | DI6: =5640*(DE6^0.602)+272*DE6 -> 14083914 | DJ6: =688*(DE6^0.6)+32*DE6 -> 1662824.9 | DK6: =DF6*($BK$2/10000)^0.72*0.6*((A6+1)/3)^0.6*('CAPEX+OPEX'!$G$116/'CAPEX+OPEX'!$G$114) -> 277110.06 | DL6: =DG6*($BK$2/10000)^0.72*0.6*((A6+1)/3)^0.6*('CAPEX+OPEX'!$G$116/'CAPEX+OPEX'!$G$114) -> 712667.65 | DM6: =DH6*($BK$2/10000)^0.72*0.6*((A6+1)/3)^0.6*('CAPEX+OPEX'!$G$116/'CAPEX+OPEX'!$G$114) -> 137472.72 | DN6: =DI6*($BK$2/10000)^0.72*0.6*((A6+1)/3)^0.6*('CAPEX+OPEX'!$G$116/'CAPEX+OPEX'!$G$114) -> 850978.45 | DO6: =DJ6*($BK$2/10000)^0.72*0.6*((A6+1)/3)^0.6*('CAPEX+OPEX'!$G$116/'CAPEX+OPEX'!$G$114) -> 100471.23 | DP6: =SUM(DK6:DO6) -> 2078700.1 | DQ6: =DF6*(BM6/10000)^0.72*0.6*((AF6+1)/3)^0.6*('CAPEX+OPEX'!$G$116/'CAPEX+OPEX'!$G$114) -> 426776.3 | DR6: =DG6*(BM6/10000)^0.72*0.6*((AF6+1)/3)^0.6*('CAPEX+OPEX'!$G$116/'CAPEX+OPEX'!$G$114) -> 1097577.1 | DS6: =DH6*(BM6/10000)^0.72*0.6*((AF6+1)/3)^0.6*('CAPEX+OPEX'!$G$116/'CAPEX+OPEX'!$G$114) -> 211721.28 | DT6: =DI6*(BM6/10000)^0.72*0.6*((AF6+1)/3)^0.6*('CAPEX+OPEX'!$G$116/'CAPEX+OPEX'!$G$114) -> 1310589.1 | DU6: =DJ6*(BM6/10000)^0.72*0.6*((AF6+1)/3)^0.6*('CAPEX+OPEX'!$G$116/'CAPEX+OPEX'!$G$114) -> 154735.41 | DV6: =SUM(DQ6:DU6) -> 3201399.3 | DW6: =DV6+DP6+SUM(DA6:DD6)*1.15+SUM(CS6:CV6)*1.15+SUM(CA6:CD6)*1.15 -> 5349673.4 | DX6: =DW6/15 -> 356644.9 | DY6: =BO6*'Reagent cost'!$C$35*60*7200 -> 1761651.9 | DZ6: =BP6*'Reagent cost'!$C$34*60*7200 -> 419179.29 | EA6: =BQ6*'Reagent cost'!$C$14*'Reagent cost'!$C$36/1000*60*7200 -> 6948241.5 | EB6: =DA6*0.01 -> 39.6 | EC6: =DC6*0.02 -> 95.688272 | ED6: =0.1*BK6*60*7200*'Reagent cost'!$H$17*'Reagent cost'!$C$17/1000 -> 504921.6 | EE6: =BV6*0.1*'Reagent cost'!$C$16/1000*'Reagent cost'!$H$16*60*7200 -> 1723679.1 | EF6: =BZ6/1000*'Reagent cost'!$H$19*'Reagent cost'!$C$19*60*7200 -> 144826.75 | EG6: =0.33*('Costing 100 Lmin Feed Orig'!BO6*'Reagent cost'!$C$13+'Costing 100 Lmin Feed Orig'!BP6*'Reagent cost'!$C$12+'Costing 100 Lmin Feed Orig'!BQ6*'Reagent cost'!$C$14+'Costing 100 Lmin Feed Orig'!BV6*0.1*'Reagent cost'!$C$16+'Costing 100 Lmin Feed Orig'!BZ6*'Reagent cost'!$C$19)/1000*60*7200 -> 296311.85 | EH6: =CG6*'Reagent cost'!$C$35*60*7200 -> 1859378.5 | EI6: =CH6*'Reagent cost'!$C$34*60*7200 -> 442433.02 | EJ6: =CI6*'Reagent cost'!$C$14*'Reagent cost'!$C$36/1000*60*7200 -> 7333691.2 | EK6: =DB6*0.01 -> 39.6 | EL6: =DD6*0.02 -> 610.87664 | EM6: =0.1*BM6*60*7200*'Reagent cost'!$H$17*'Reagent cost'!$C$17/1000 -> 467974.14 | EN6: =CN6*0.1*'Reagent cost'!$C$16/1000*'Reagent cost'!$H$16*60*7200 -> 1819299.2 | EO6: =CR6/1000*'Reagent cost'!$H$19*'Reagent cost'!$C$19*60*7200 -> 152860.93 | EP6: =0.33*(CG6*'Reagent cost'!$C$13+CH6*'Reagent cost'!$C$12+CI6*'Reagent cost'!$C$14+CN6*0.1*'Reagent cost'!$C$16+CR6*'Reagent cost'!$C$19)/1000*60*7200 -> 312749.58 | EQ6: =(SUM(DY6:EF6)+SUM(EH6:EO6))*1.2 -> 28294707 | ER6: =EG6+EP6 -> 609061.43 | ES6: =0.499*((BK6/3.78541*15)^(-0.146))*BK6/3.78541*15*300*(1+(A6-2)/9) -> 27520.276 | ET6: =0.248*((BK6/3.78541*15)^(-0.144))*BK6/3.78541*15*300*(1+(A6-2)/3) -> 16610.44 | EU6: =0.105*((BK6/3.78541*15)^(-0.144))*BK6/3.78541*15*300*(1+(A6-2)/3) -> 7032.6458 | EV6: =0.058*((BK6/3.78541*15)^(-0.151))*BK6/3.78541*15*300*(1+(A6-2)/3) -> 3725.3887 | EW6: =0.056*((BK6/3.78541*15)^(-0.144))*BK6/3.78541*15*300*(1+(A6-2)/3) -> 3750.7444 | EX6: =SUM(ES6:EW6) -> 58639.495 | EY6: =0.499*((BM6/3.78541*15)^(-0.146))*BM6/3.78541*15*300*(1+(AF6-2)/9) -> 38686.573 | EZ6: =0.248*((BM6/3.78541*15)^(-0.144))*BM6/3.78541*15*300*(1+(AF6-2)/3) -> 35019.815 | FA6: =0.105*((BM6/3.78541*15)^(-0.144))*BM6/3.78541*15*300*(1+(AF6-2)/3) -> 14826.938 | FB6: =0.058*((BM6/3.78541*15)^(-0.151))*BM6/3.78541*15*300*(1+(AF6-2)/3) -> 7858.4217 | FC6: =0.056*((BM6/3.78541*15)^(-0.144))*BM6/3.78541*15*300*(1+(AF6-2)/3) -> 7907.7002 | FD6: =SUM(EY6:FC6) -> 104299.45 | FE6: =EQ6+ER6+EX6+FD6 -> 29066708 | FF6: =FE6+DX6 -> 29423353 | FG6: =BM6*AM6*195.08/1000*'PGM market prices'!$C$2*60*7200 -> 4.2371704e+08 | FH6: =BN6*AQ6*BA6*106.42/1000*'PGM market prices'!$C$3*60*7200 -> 2.2417674e+08 | FI6: =BK6*J6*102.91/1000*'PGM market prices'!$C$4*60*7200 -> 2.3748534e+08 | FJ6: =SUM(FG6:FI6) -> 8.8537911e+08 | FK6: =(1-0.26)*(FJ6-FF6) -> 6.3340726e+08 | FL6: =FF6/(BK6*60*7200) -> 0.68109613 | FM6: =FF6/7200/60/(BM6*AM6*195.08/1000) -> 2342.2687 | FN6: =FF6/7200/60/(BN6*BA6*AQ6*106.42/1000) -> 4322.043 | FO6: =FF6/(J6*BK6*102.91/1000*60*7200) -> 20436.075
A7: 3 | B7: 0.0015414359 | C7: 0.0015414359 | D7: 0.0003425413 | E7: 0 | F7: 0 | G7: 0 | H7: 1.6300359e-05 | I7: 7.447486e-07 | J7: 0.00032385704 | K7: 0.080727109 | L7: 0.081550485 | M7: 0.00098897849 | N7: -9.8011876e-17 | O7: 1.9428903e-16 | P7: -4.3537493e-18 | Q7: 0.18892482 | R7: 94.5454 | S7: 500 | T7: 95 | U7: 1 | V7: 0.1 | W7: 52.931107 | X7: ddFc | Y7: 1 | Z7: 0.28318429 | AA7: 0.56945643 | AB7: 0.0037698629 | AC7: 1822.2108 | AD7: 2662.6059 | AE7: 2401.5031 | AF7: 9 | AG7: 0.0016455479 | AH7: 0.0016623316 | AI7: 2.0159417e-05 | AJ7: 0 | AK7: 0 | AL7: 0 | AM7: 0.0016083319 | AN7: 6.4623509e-05 | AO7: 2.0025537e-05 | AP7: 0.0017304893 | AQ7: 0.074291069 | AR7: 6.2252388e-06 | AS7: 2.1027559e-15 | AT7: -3.1233609e-13 | AU7: 8.7085575e-21 | AV7: 0.19932361 | AW7: 99.335892 | AX7: 500 | AY7: 95 | AZ7: 0.92682535 | BA7: 0.1 | BB7: 46.498524 | BC7: coeFc | BD7: 1 | BE7: 0.018775015 | BF7: 0.10492961 | BG7: 0.001814625 | BH7: 285.19514 | BI7: 2169.8945 | BJ7: 866.49409 | BK7: =U7*100 -> 100 | BL7: =Q7*100 -> 18.892482 | BM7: =AZ7*100 -> 92.682535 | BN7: =AV7*100 -> 19.932361 | BO7: =0.6*1.2*BL7/2 -> 6.8012937 | BP7: =0.04*1.2*BL7/2 -> 0.45341958 | BQ7: =0.2*1.2*BL7/2 -> 2.2670979 | BR7: =0.1*1.2*BL7/2 -> 1.1335489 | BS7: =V7*BL7 -> 1.8892482 | BT7: =0.6*BL7*1 -> 11.335489 | BU7: =1.6*BL7*1 -> 30.227972 | BV7: =1*V7*BL7/0.2 -> 9.4462412 | BW7: =BM7-BV7 -> 83.236294 | BX7: =(SUM(BV7:BW7)+BL7)*1 -> 111.57502 | BY7: =BM7 -> 92.682535 | BZ7: =BL7*0.1*1.4 -> 2.6449475 | CA7: =7963.6*(BT7/1000)^0.6*1.7*('CAPEX+OPEX'!$G$116/'CAPEX+OPEX'!$G$115) -> 1086.1882 | CB7: =7963.6*(BU7/1000)^0.6*1.7*('CAPEX+OPEX'!$G$116/'CAPEX+OPEX'!$G$115) -> 1956.5292 | CC7: =7963.6*(BX7/1000)^0.6*1.7*('CAPEX+OPEX'!$G$116/'CAPEX+OPEX'!$G$115) -> 4283.3258 | CD7: =7963.6*(BY7/1000)^0.6*1.7*('CAPEX+OPEX'!$G$116/'CAPEX+OPEX'!$G$115) -> 3832.125 | CE7: 300 | CF7: 30 | CG7: =0.6*1.2*BN7/2 -> 7.1756499 | CH7: =0.04*1.2*BN7/2 -> 0.47837666 | CI7: =0.2*1.2*BN7/2 -> 2.3918833 | CJ7: =0.1*1.2*BN7/2 -> 1.1959416 | CK7: =0.1*BN7 -> 1.9932361 | CL7: =0.6*BN7*1 -> 11.959416 | CM7: =1.6*BN7*1 -> 31.891777 | CN7: =1*BA7*BN7/0.2 -> 9.9661804 | CO7: 0 | CP7: =(SUM(CN7:CO7)+BN7)*1 -> 29.898541 | CQ7: =CN7 -> 9.9661804 | CR7: =BN7*0.1*1.4 -> 2.7905305 | CS7: =7963.6*(CL7/1000)^0.6*1.7*('CAPEX+OPEX'!$G$116/'CAPEX+OPEX'!$G$115) -> 1121.6747 | CT7: =7963.6*(CM7/1000)^0.6*1.7*('CAPEX+OPEX'!$G$116/'CAPEX+OPEX'!$G$115) -> 2020.4503 | CU7: =7963.6*(CP7/1000)^0.6*1.7*('CAPEX+OPEX'!$G$116/'CAPEX+OPEX'!$G$115) -> 1943.7076 | CV7: =7963.6*(CQ7/1000)^0.6*1.7*('CAPEX+OPEX'!$G$116/'CAPEX+OPEX'!$G$115) -> 1005.4447 | CW7: 300 | CX7: =0.1*CW7 -> 30 | CY7: =0.1*BK7 -> 10 | CZ7: =0.1*BM7 -> 9.2682535 | DA7: =CE7*1.32*10 -> 3960 | DB7: =CW7*1.32*10 -> 3960 | DC7: =CF7*'Reagent cost'!$C$18/1000*'Reagent cost'!$H$18 -> 4784.4136 | DD7: =CX7*'Ligand cost'!$B$56*'Ligand cost'!$J$56 -> 30543.832 | DE7: =10000*1/3.78541*15 -> 39625.827 | DF7: =2510*(DE7^0.571)+89*DE7 -> 4586243.4 | DG7: =4810*(DE7^0.6)+228*DE7 -> 11794835 | DH7: =1030*(DE7^0.59)+44*DE7 -> 2275209.2 | DI7: =5640*(DE7^0.602)+272*DE7 -> 14083914 | DJ7: =688*(DE7^0.6)+32*DE7 -> 1662824.9 | DK7: =DF7*($BK$2/10000)^0.72*0.6*((A7+1)/3)^0.6*('CAPEX+OPEX'!$G$116/'CAPEX+OPEX'!$G$114) -> 277110.06 | DL7: =DG7*($BK$2/10000)^0.72*0.6*((A7+1)/3)^0.6*('CAPEX+OPEX'!$G$116/'CAPEX+OPEX'!$G$114) -> 712667.65 | DM7: =DH7*($BK$2/10000)^0.72*0.6*((A7+1)/3)^0.6*('CAPEX+OPEX'!$G$116/'CAPEX+OPEX'!$G$114) -> 137472.72 | DN7: =DI7*($BK$2/10000)^0.72*0.6*((A7+1)/3)^0.6*('CAPEX+OPEX'!$G$116/'CAPEX+OPEX'!$G$114) -> 850978.45 | DO7: =DJ7*($BK$2/10000)^0.72*0.6*((A7+1)/3)^0.6*('CAPEX+OPEX'!$G$116/'CAPEX+OPEX'!$G$114) -> 100471.23 | DP7: =SUM(DK7:DO7) -> 2078700.1 | DQ7: =DF7*(BM7/10000)^0.72*0.6*((AF7+1)/3)^0.6*('CAPEX+OPEX'!$G$116/'CAPEX+OPEX'!$G$114) -> 454626.54 | DR7: =DG7*(BM7/10000)^0.72*0.6*((AF7+1)/3)^0.6*('CAPEX+OPEX'!$G$116/'CAPEX+OPEX'!$G$114) -> 1169202 | DS7: =DH7*(BM7/10000)^0.72*0.6*((AF7+1)/3)^0.6*('CAPEX+OPEX'!$G$116/'CAPEX+OPEX'!$G$114) -> 225537.63 | DT7: =DI7*(BM7/10000)^0.72*0.6*((AF7+1)/3)^0.6*('CAPEX+OPEX'!$G$116/'CAPEX+OPEX'!$G$114) -> 1396114.6 | DU7: =DJ7*(BM7/10000)^0.72*0.6*((AF7+1)/3)^0.6*('CAPEX+OPEX'!$G$116/'CAPEX+OPEX'!$G$114) -> 164833.02 | DV7: =SUM(DQ7:DU7) -> 3410313.7 | DW7: =DV7+DP7+SUM(DA7:DD7)*1.15+SUM(CS7:CV7)*1.15+SUM(CA7:CD7)*1.15 -> 5558586.2 | DX7: =DW7/15 -> 370572.41 | DY7: =BO7*'Reagent cost'!$C$35*60*7200 -> 1761651.9 | DZ7: =BP7*'Reagent cost'!$C$34*60*7200 -> 419179.29 | EA7: =BQ7*'Reagent cost'!$C$14*'Reagent cost'!$C$36/1000*60*7200 -> 6948241.5 | EB7: =DA7*0.01 -> 39.6 | EC7: =DC7*0.02 -> 95.688272 | ED7: =0.1*BK7*60*7200*'Reagent cost'!$H$17*'Reagent cost'!$C$17/1000 -> 504921.6 | EE7: =BV7*0.1*'Reagent cost'!$C$16/1000*'Reagent cost'!$H$16*60*7200 -> 1723679.1 | EF7: =BZ7/1000*'Reagent cost'!$H$19*'Reagent cost'!$C$19*60*7200 -> 144826.75 | EG7: =0.33*('Costing 100 Lmin Feed Orig'!BO7*'Reagent cost'!$C$13+'Costing 100 Lmin Feed Orig'!BP7*'Reagent cost'!$C$12+'Costing 100 Lmin Feed Orig'!BQ7*'Reagent cost'!$C$14+'Costing 100 Lmin Feed Orig'!BV7*0.1*'Reagent cost'!$C$16+'Costing 100 Lmin Feed Orig'!BZ7*'Reagent cost'!$C$19)/1000*60*7200 -> 296311.85 | EH7: =CG7*'Reagent cost'!$C$35*60*7200 -> 1858616.6 | EI7: =CH7*'Reagent cost'!$C$34*60*7200 -> 442251.72 | EJ7: =CI7*'Reagent cost'!$C$14*'Reagent cost'!$C$36/1000*60*7200 -> 7330686 | EK7: =DB7*0.01 -> 39.6 | EL7: =DD7*0.02 -> 610.87664 | EM7: =0.1*BM7*60*7200*'Reagent cost'!$H$17*'Reagent cost'!$C$17/1000 -> 467974.14 | EN7: =CN7*0.1*'Reagent cost'!$C$16/1000*'Reagent cost'!$H$16*60*7200 -> 1818553.7 | EO7: =CR7/1000*'Reagent cost'!$H$19*'Reagent cost'!$C$19*60*7200 -> 152798.29 | EP7: =0.33*(CG7*'Reagent cost'!$C$13+CH7*'Reagent cost'!$C$12+CI7*'Reagent cost'!$C$14+CN7*0.1*'Reagent cost'!$C$16+CR7*'Reagent cost'!$C$19)/1000*60*7200 -> 312621.42 | EQ7: =(SUM(DY7:EF7)+SUM(EH7:EO7))*1.2 -> 28289000 | ER7: =EG7+EP7 -> 608933.27 | ES7: =0.499*((BK7/3.78541*15)^(-0.146))*BK7/3.78541*15*300*(1+(A7-2)/9) -> 27520.276 | ET7: =0.248*((BK7/3.78541*15)^(-0.144))*BK7/3.78541*15*300*(1+(A7-2)/3) -> 16610.44 | EU7: =0.105*((BK7/3.78541*15)^(-0.144))*BK7/3.78541*15*300*(1+(A7-2)/3) -> 7032.6458 | EV7: =0.058*((BK7/3.78541*15)^(-0.151))*BK7/3.78541*15*300*(1+(A7-2)/3) -> 3725.3887 | EW7: =0.056*((BK7/3.78541*15)^(-0.144))*BK7/3.78541*15*300*(1+(A7-2)/3) -> 3750.7444 | EX7: =SUM(ES7:EW7) -> 58639.495 | EY7: =0.499*((BM7/3.78541*15)^(-0.146))*BM7/3.78541*15*300*(1+(AF7-2)/9) -> 41265.678 | EZ7: =0.248*((BM7/3.78541*15)^(-0.144))*BM7/3.78541*15*300*(1+(AF7-2)/3) -> 38910.906 | FA7: =0.105*((BM7/3.78541*15)^(-0.144))*BM7/3.78541*15*300*(1+(AF7-2)/3) -> 16474.375 | FB7: =0.058*((BM7/3.78541*15)^(-0.151))*BM7/3.78541*15*300*(1+(AF7-2)/3) -> 8731.5797 | FC7: =0.056*((BM7/3.78541*15)^(-0.144))*BM7/3.78541*15*300*(1+(AF7-2)/3) -> 8786.3336 | FD7: =SUM(EY7:FC7) -> 114168.87 | FE7: =EQ7+ER7+EX7+FD7 -> 29070741 | FF7: =FE7+DX7 -> 29441314 | FG7: =BM7*AM7*195.08/1000*'PGM market prices'!$C$2*60*7200 -> 4.2373132e+08 | FH7: =BN7*AQ7*BA7*106.42/1000*'PGM market prices'!$C$3*60*7200 -> 2.2417637e+08 | FI7: =BK7*J7*102.91/1000*'PGM market prices'!$C$4*60*7200 -> 2.3748534e+08 | FJ7: =SUM(FG7:FI7) -> 8.8539302e+08 | FK7: =(1-0.26)*(FJ7-FF7) -> 6.3340426e+08 | FL7: =FF7/(BK7*60*7200) -> 0.68151189 | FM7: =FF7/7200/60/(BM7*AM7*195.08/1000) -> 2343.6196 | FN7: =FF7/7200/60/(BN7*BA7*AQ7*106.42/1000) -> 4324.6885 | FO7: =FF7/(J7*BK7*102.91/1000*60*7200) -> 20448.55
A8: 3 | B8: 0.0015414359 | C8: 0.0015414359 | D8: 0.0003425413 | E8: 0 | F8: 0 | G8: 0 | H8: 1.6300359e-05 | I8: 7.447486e-07 | J8: 0.00032385704 | K8: 0.080727109 | L8: 0.081550485 | M8: 0.00098897849 | N8: -9.8011876e-17 | O8: 1.9428903e-16 | P8: -4.3537493e-18 | Q8: 0.18892482 | R8: 94.5454 | S8: 500 | T8: 95 | U8: 1 | V8: 0.1 | W8: 52.931107 | X8: ddFc | Y8: 1 | Z8: 0.28318429 | AA8: 0.56945643 | AB8: 0.0037698629 | AC8: 1822.2108 | AD8: 2662.6059 | AE8: 2401.5031 | AF8: 10 | AG8: 0.0016455479 | AH8: 0.0016623316 | AI8: 2.0159417e-05 | AJ8: 0 | AK8: 0 | AL8: 0 | AM8: 0.0016083474 | AN8: 6.4624273e-05 | AO8: 2.002559e-05 | AP8: 0.0017299703 | AQ8: 0.074299765 | AR8: 6.2234782e-06 | AS8: 1.84992e-18 | AT8: -4.3780084e-16 | AU8: -4.9498488e-21 | AV8: 0.19930019 | AW8: 99.336158 | AX8: 500 | AY8: 95 | AZ8: 0.92682535 | BA8: 0.1 | BB8: 46.503988 | BC8: coeFc | BD8: 1 | BE8: 0.018775015 | BF8: 0.10492961 | BG8: 0.001814625 | BH8: 285.19514 | BI8: 2169.8945 | BJ8: 866.49409 | BK8: =U8*100 -> 100 | BL8: =Q8*100 -> 18.892482 | BM8: =AZ8*100 -> 92.682535 | BN8: =AV8*100 -> 19.930019 | BO8: =0.6*1.2*BL8/2 -> 6.8012937 | BP8: =0.04*1.2*BL8/2 -> 0.45341958 | BQ8: =0.2*1.2*BL8/2 -> 2.2670979 | BR8: =0.1*1.2*BL8/2 -> 1.1335489 | BS8: =V8*BL8 -> 1.8892482 | BT8: =0.6*BL8*1 -> 11.335489 | BU8: =1.6*BL8*1 -> 30.227972 | BV8: =1*V8*BL8/0.2 -> 9.4462412 | BW8: =BM8-BV8 -> 83.236294 | BX8: =(SUM(BV8:BW8)+BL8)*1 -> 111.57502 | BY8: =BM8 -> 92.682535 | BZ8: =BL8*0.1*1.4 -> 2.6449475 | CA8: =7963.6*(BT8/1000)^0.6*1.7*('CAPEX+OPEX'!$G$116/'CAPEX+OPEX'!$G$115) -> 1086.1882 | CB8: =7963.6*(BU8/1000)^0.6*1.7*('CAPEX+OPEX'!$G$116/'CAPEX+OPEX'!$G$115) -> 1956.5292 | CC8: =7963.6*(BX8/1000)^0.6*1.7*('CAPEX+OPEX'!$G$116/'CAPEX+OPEX'!$G$115) -> 4283.3258 | CD8: =7963.6*(BY8/1000)^0.6*1.7*('CAPEX+OPEX'!$G$116/'CAPEX+OPEX'!$G$115) -> 3832.125 | CE8: 300 | CF8: 30 | CG8: =0.6*1.2*BN8/2 -> 7.1748067 | CH8: =0.04*1.2*BN8/2 -> 0.47832045 | CI8: =0.2*1.2*BN8/2 -> 2.3916022 | CJ8: =0.1*1.2*BN8/2 -> 1.1958011 | CK8: =0.1*BN8 -> 1.9930019 | CL8: =0.6*BN8*1 -> 11.958011 | CM8: =1.6*BN8*1 -> 31.88803 | CN8: =1*BA8*BN8/0.2 -> 9.9650093 | CO8: 0 | CP8: =(SUM(CN8:CO8)+BN8)*1 -> 29.895028 | CQ8: =CN8 -> 9.9650093 | CR8: =BN8*0.1*1.4 -> 2.7902026 | CS8: =7963.6*(CL8/1000)^0.6*1.7*('CAPEX+OPEX'!$G$116/'CAPEX+OPEX'!$G$115) -> 1121.5956 | CT8: =7963.6*(CM8/1000)^0.6*1.7*('CAPEX+OPEX'!$G$116/'CAPEX+OPEX'!$G$115) -> 2020.3078 | CU8: =7963.6*(CP8/1000)^0.6*1.7*('CAPEX+OPEX'!$G$116/'CAPEX+OPEX'!$G$115) -> 1943.5705 | CV8: =7963.6*(CQ8/1000)^0.6*1.7*('CAPEX+OPEX'!$G$116/'CAPEX+OPEX'!$G$115) -> 1005.3738 | CW8: 300 | CX8: =0.1*CW8 -> 30 | CY8: =0.1*BK8 -> 10 | CZ8: =0.1*BM8 -> 9.2682535 | DA8: =CE8*1.32*10 -> 3960 | DB8: =CW8*1.32*10 -> 3960 | DC8: =CF8*'Reagent cost'!$C$18/1000*'Reagent cost'!$H$18 -> 4784.4136 | DD8: =CX8*'Ligand cost'!$B$56*'Ligand cost'!$J$56 -> 30543.832 | DE8: =10000*1/3.78541*15 -> 39625.827 | DF8: =2510*(DE8^0.571)+89*DE8 -> 4586243.4 | DG8: =4810*(DE8^0.6)+228*DE8 -> 11794835 | DH8: =1030*(DE8^0.59)+44*DE8 -> 2275209.2 | DI8: =5640*(DE8^0.602)+272*DE8 -> 14083914 | DJ8: =688*(DE8^0.6)+32*DE8 -> 1662824.9 | DK8: =DF8*($BK$2/10000)^0.72*0.6*((A8+1)/3)^0.6*('CAPEX+OPEX'!$G$116/'CAPEX+OPEX'!$G$114) -> 277110.06 | DL8: =DG8*($BK$2/10000)^0.72*0.6*((A8+1)/3)^0.6*('CAPEX+OPEX'!$G$116/'CAPEX+OPEX'!$G$114) -> 712667.65 | DM8: =DH8*($BK$2/10000)^0.72*0.6*((A8+1)/3)^0.6*('CAPEX+OPEX'!$G$116/'CAPEX+OPEX'!$G$114) -> 137472.72 | DN8: =DI8*($BK$2/10000)^0.72*0.6*((A8+1)/3)^0.6*('CAPEX+OPEX'!$G$116/'CAPEX+OPEX'!$G$114) -> 850978.45 | DO8: =DJ8*($BK$2/10000)^0.72*0.6*((A8+1)/3)^0.6*('CAPEX+OPEX'!$G$116/'CAPEX+OPEX'!$G$114) -> 100471.23 | DP8: =SUM(DK8:DO8) -> 2078700.1 | DQ8: =DF8*(BM8/10000)^0.72*0.6*((AF8+1)/3)^0.6*('CAPEX+OPEX'!$G$116/'CAPEX+OPEX'!$G$114) -> 481382.61 | DR8: =DG8*(BM8/10000)^0.72*0.6*((AF8+1)/3)^0.6*('CAPEX+OPEX'!$G$116/'CAPEX+OPEX'!$G$114) -> 1238012.8 | DS8: =DH8*(BM8/10000)^0.72*0.6*((AF8+1)/3)^0.6*('CAPEX+OPEX'!$G$116/'CAPEX+OPEX'!$G$114) -> 238811.16 | DT8: =DI8*(BM8/10000)^0.72*0.6*((AF8+1)/3)^0.6*('CAPEX+OPEX'!$G$116/'CAPEX+OPEX'!$G$114) -> 1478279.9 | DU8: =DJ8*(BM8/10000)^0.72*0.6*((AF8+1)/3)^0.6*('CAPEX+OPEX'!$G$116/'CAPEX+OPEX'!$G$114) -> 174533.91 | DV8: =SUM(DQ8:DU8) -> 3611020.4 | DW8: =DV8+DP8+SUM(DA8:DD8)*1.15+SUM(CS8:CV8)*1.15+SUM(CA8:CD8)*1.15 -> 5759292.4 | DX8: =DW8/15 -> 383952.83 | DY8: =BO8*'Reagent cost'!$C$35*60*7200 -> 1761651.9 | DZ8: =BP8*'Reagent cost'!$C$34*60*7200 -> 419179.29 | EA8: =BQ8*'Reagent cost'!$C$14*'Reagent cost'!$C$36/1000*60*7200 -> 6948241.5 | EB8: =DA8*0.01 -> 39.6 | EC8: =DC8*0.02 -> 95.688272 | ED8: =0.1*BK8*60*7200*'Reagent cost'!$H$17*'Reagent cost'!$C$17/1000 -> 504921.6 | EE8: =BV8*0.1*'Reagent cost'!$C$16/1000*'Reagent cost'!$H$16*60*7200 -> 1723679.1 | EF8: =BZ8/1000*'Reagent cost'!$H$19*'Reagent cost'!$C$19*60*7200 -> 144826.75 | EG8: =0.33*('Costing 100 Lmin Feed Orig'!BO8*'Reagent cost'!$C$13+'Costing 100 Lmin Feed Orig'!BP8*'Reagent cost'!$C$12+'Costing 100 Lmin Feed Orig'!BQ8*'Reagent cost'!$C$14+'Costing 100 Lmin Feed Orig'!BV8*0.1*'Reagent cost'!$C$16+'Costing 100 Lmin Feed Orig'!BZ8*'Reagent cost'!$C$19)/1000*60*7200 -> 296311.85 | EH8: =CG8*'Reagent cost'!$C$35*60*7200 -> 1858398.2 | EI8: =CH8*'Reagent cost'!$C$34*60*7200 -> 442199.75 | EJ8: =CI8*'Reagent cost'!$C$14*'Reagent cost'!$C$36/1000*60*7200 -> 7329824.6 | EK8: =DB8*0.01 -> 39.6 | EL8: =DD8*0.02 -> 610.87664 | EM8: =0.1*BM8*60*7200*'Reagent cost'!$H$17*'Reagent cost'!$C$17/1000 -> 467974.14 | EN8: =CN8*0.1*'Reagent cost'!$C$16/1000*'Reagent cost'!$H$16*60*7200 -> 1818340 | EO8: =CR8/1000*'Reagent cost'!$H$19*'Reagent cost'!$C$19*60*7200 -> 152780.33 | EP8: =0.33*(CG8*'Reagent cost'!$C$13+CH8*'Reagent cost'!$C$12+CI8*'Reagent cost'!$C$14+CN8*0.1*'Reagent cost'!$C$16+CR8*'Reagent cost'!$C$19)/1000*60*7200 -> 312584.69 | EQ8: =(SUM(DY8:EF8)+SUM(EH8:EO8))*1.2 -> 28287363 | ER8: =EG8+EP8 -> 608896.54 | ES8: =0.499*((BK8/3.78541*15)^(-0.146))*BK8/3.78541*15*300*(1+(A8-2)/9) -> 27520.276 | ET8: =0.248*((BK8/3.78541*15)^(-0.144))*BK8/3.78541*15*300*(1+(A8-2)/3) -> 16610.44 | EU8: =0.105*((BK8/3.78541*15)^(-0.144))*BK8/3.78541*15*300*(1+(A8-2)/3) -> 7032.6458 | EV8: =0.058*((BK8/3.78541*15)^(-0.151))*BK8/3.78541*15*300*(1+(A8-2)/3) -> 3725.3887 | EW8: =0.056*((BK8/3.78541*15)^(-0.144))*BK8/3.78541*15*300*(1+(A8-2)/3) -> 3750.7444 | EX8: =SUM(ES8:EW8) -> 58639.495 | EY8: =0.499*((BM8/3.78541*15)^(-0.146))*BM8/3.78541*15*300*(1+(AF8-2)/9) -> 43844.783 | EZ8: =0.248*((BM8/3.78541*15)^(-0.144))*BM8/3.78541*15*300*(1+(AF8-2)/3) -> 42801.996 | FA8: =0.105*((BM8/3.78541*15)^(-0.144))*BM8/3.78541*15*300*(1+(AF8-2)/3) -> 18121.813 | FB8: =0.058*((BM8/3.78541*15)^(-0.151))*BM8/3.78541*15*300*(1+(AF8-2)/3) -> 9604.7376 | FC8: =0.056*((BM8/3.78541*15)^(-0.144))*BM8/3.78541*15*300*(1+(AF8-2)/3) -> 9664.9669 | FD8: =SUM(EY8:FC8) -> 124038.3 | FE8: =EQ8+ER8+EX8+FD8 -> 29078938 | FF8: =FE8+DX8 -> 29462891 | FG8: =BM8*AM8*195.08/1000*'PGM market prices'!$C$2*60*7200 -> 4.2373541e+08 | FH8: =BN8*AQ8*BA8*106.42/1000*'PGM market prices'!$C$3*60*7200 -> 2.2417626e+08 | FI8: =BK8*J8*102.91/1000*'PGM market prices'!$C$4*60*7200 -> 2.3748534e+08 | FJ8: =SUM(FG8:FI8) -> 8.85397e+08 | FK8: =(1-0.26)*(FJ8-FF8) -> 6.3339124e+08 | FL8: =FF8/(BK8*60*7200) -> 0.68201136 | FM8: =FF8/7200/60/(BM8*AM8*195.08/1000) -> 2345.3145 | FN8: =FF8/7200/60/(BN8*BA8*AQ8*106.42/1000) -> 4327.8601 | FO8: =FF8/(J8*BK8*102.91/1000*60*7200) -> 20463.536
A9: 3 | B9: 0.0015414359 | C9: 0.0015414359 | D9: 0.0003425413 | E9: 0 | F9: 0 | G9: 0 | H9: 1.6300359e-05 | I9: 7.447486e-07 | J9: 0.00032385704 | K9: 0.080727109 | L9: 0.081550485 | M9: 0.00098897849 | N9: -9.8011876e-17 | O9: 1.9428903e-16 | P9: -4.3537493e-18 | Q9: 0.18892482 | R9: 94.5454 | S9: 500 | T9: 95 | U9: 1 | V9: 0.1 | W9: 52.931107 | X9: ddFc | Y9: 1 | Z9: 0.28318429 | AA9: 0.56945643 | AB9: 0.0037698629 | AC9: 1822.2108 | AD9: 2662.6059 | AE9: 2401.5031 | AF9: 11 | AG9: 0.0016455479 | AH9: 0.0016623316 | AI9: 2.0159417e-05 | AJ9: 0 | AK9: 0 | AL9: 0 | AM9: 0.0016083519 | AN9: 6.4624492e-05 | AO9: 2.0025606e-05 | AP9: 0.0017298217 | AQ9: 0.074302253 | AR9: 6.2229743e-06 | AS9: 1.3552527e-19 | AT9: -2.1684043e-19 | AU9: 2.4616895e-21 | AV9: 0.19929348 | AW9: 99.336234 | AX9: 500 | AY9: 95 | AZ9: 0.92682535 | BA9: 0.1 | BB9: 46.505552 | BC9: coeFc | BD9: 1 | BE9: 0.018775015 | BF9: 0.10492961 | BG9: 0.001814625 | BH9: 285.19514 | BI9: 2169.8945 | BJ9: 866.49409 | BK9: =U9*100 -> 100 | BL9: =Q9*100 -> 18.892482 | BM9: =AZ9*100 -> 92.682535 | BN9: =AV9*100 -> 19.929348 | BO9: =0.6*1.2*BL9/2 -> 6.8012937 | BP9: =0.04*1.2*BL9/2 -> 0.45341958 | BQ9: =0.2*1.2*BL9/2 -> 2.2670979 | BR9: =0.1*1.2*BL9/2 -> 1.1335489 | BS9: =V9*BL9 -> 1.8892482 | BT9: =0.6*BL9*1 -> 11.335489 | BU9: =1.6*BL9*1 -> 30.227972 | BV9: =1*V9*BL9/0.2 -> 9.4462412 | BW9: =BM9-BV9 -> 83.236294 | BX9: =(SUM(BV9:BW9)+BL9)*1 -> 111.57502 | BY9: =BM9 -> 92.682535 | BZ9: =BL9*0.1*1.4 -> 2.6449475 | CA9: =7963.6*(BT9/1000)^0.6*1.7*('CAPEX+OPEX'!$G$116/'CAPEX+OPEX'!$G$115) -> 1086.1882 | CB9: =7963.6*(BU9/1000)^0.6*1.7*('CAPEX+OPEX'!$G$116/'CAPEX+OPEX'!$G$115) -> 1956.5292 | CC9: =7963.6*(BX9/1000)^0.6*1.7*('CAPEX+OPEX'!$G$116/'CAPEX+OPEX'!$G$115) -> 4283.3258 | CD9: =7963.6*(BY9/1000)^0.6*1.7*('CAPEX+OPEX'!$G$116/'CAPEX+OPEX'!$G$115) -> 3832.125 | CE9: 300 | CF9: 30 | CG9: =0.6*1.2*BN9/2 -> 7.1745654 | CH9: =0.04*1.2*BN9/2 -> 0.47830436 | CI9: =0.2*1.2*BN9/2 -> 2.3915218 | CJ9: =0.1*1.2*BN9/2 -> 1.1957609 | CK9: =0.1*BN9 -> 1.9929348 | CL9: =0.6*BN9*1 -> 11.957609 | CM9: =1.6*BN9*1 -> 31.886957 | CN9: =1*BA9*BN9/0.2 -> 9.9646742 | CO9: 0 | CP9: =(SUM(CN9:CO9)+BN9)*1 -> 29.894022 | CQ9: =CN9 -> 9.9646742 | CR9: =BN9*0.1*1.4 -> 2.7901088 | CS9: =7963.6*(CL9/1000)^0.6*1.7*('CAPEX+OPEX'!$G$116/'CAPEX+OPEX'!$G$115) -> 1121.573 | CT9: =7963.6*(CM9/1000)^0.6*1.7*('CAPEX+OPEX'!$G$116/'CAPEX+OPEX'!$G$115) -> 2020.267 | CU9: =7963.6*(CP9/1000)^0.6*1.7*('CAPEX+OPEX'!$G$116/'CAPEX+OPEX'!$G$115) -> 1943.5313 | CV9: =7963.6*(CQ9/1000)^0.6*1.7*('CAPEX+OPEX'!$G$116/'CAPEX+OPEX'!$G$115) -> 1005.3535 | CW9: 300 | CX9: =0.1*CW9 -> 30 | CY9: =0.1*BK9 -> 10 | CZ9: =0.1*BM9 -> 9.2682535 | DA9: =CE9*1.32*10 -> 3960 | DB9: =CW9*1.32*10 -> 3960 | DC9: =CF9*'Reagent cost'!$C$18/1000*'Reagent cost'!$H$18 -> 4784.4136 | DD9: =CX9*'Ligand cost'!$B$56*'Ligand cost'!$J$56 -> 30543.832 | DE9: =10000*1/3.78541*15 -> 39625.827 | DF9: =2510*(DE9^0.571)+89*DE9 -> 4586243.4 | DG9: =4810*(DE9^0.6)+228*DE9 -> 11794835 | DH9: =1030*(DE9^0.59)+44*DE9 -> 2275209.2 | DI9: =5640*(DE9^0.602)+272*DE9 -> 14083914 | DJ9: =688*(DE9^0.6)+32*DE9 -> 1662824.9 | DK9: =DF9*($BK$2/10000)^0.72*0.6*((A9+1)/3)^0.6*('CAPEX+OPEX'!$G$116/'CAPEX+OPEX'!$G$114) -> 277110.06 | DL9: =DG9*($BK$2/10000)^0.72*0.6*((A9+1)/3)^0.6*('CAPEX+OPEX'!$G$116/'CAPEX+OPEX'!$G$114) -> 712667.65 | DM9: =DH9*($BK$2/10000)^0.72*0.6*((A9+1)/3)^0.6*('CAPEX+OPEX'!$G$116/'CAPEX+OPEX'!$G$114) -> 137472.72 | DN9: =DI9*($BK$2/10000)^0.72*0.6*((A9+1)/3)^0.6*('CAPEX+OPEX'!$G$116/'CAPEX+OPEX'!$G$114) -> 850978.45 | DO9: =DJ9*($BK$2/10000)^0.72*0.6*((A9+1)/3)^0.6*('CAPEX+OPEX'!$G$116/'CAPEX+OPEX'!$G$114) -> 100471.23 | DP9: =SUM(DK9:DO9) -> 2078700.1 | DQ9: =DF9*(BM9/10000)^0.72*0.6*((AF9+1)/3)^0.6*('CAPEX+OPEX'!$G$116/'CAPEX+OPEX'!$G$114) -> 507181.65 | DR9: =DG9*(BM9/10000)^0.72*0.6*((AF9+1)/3)^0.6*('CAPEX+OPEX'!$G$116/'CAPEX+OPEX'!$G$114) -> 1304362.4 | DS9: =DH9*(BM9/10000)^0.72*0.6*((AF9+1)/3)^0.6*('CAPEX+OPEX'!$G$116/'CAPEX+OPEX'!$G$114) -> 251609.92 | DT9: =DI9*(BM9/10000)^0.72*0.6*((AF9+1)/3)^0.6*('CAPEX+OPEX'!$G$116/'CAPEX+OPEX'!$G$114) -> 1557506.3 | DU9: =DJ9*(BM9/10000)^0.72*0.6*((AF9+1)/3)^0.6*('CAPEX+OPEX'!$G$116/'CAPEX+OPEX'!$G$114) -> 183887.81 | DV9: =SUM(DQ9:DU9) -> 3804548.1 | DW9: =DV9+DP9+SUM(DA9:DD9)*1.15+SUM(CS9:CV9)*1.15+SUM(CA9:CD9)*1.15 -> 5952819.9 | DX9: =DW9/15 -> 396854.66 | DY9: =BO9*'Reagent cost'!$C$35*60*7200 -> 1761651.9 | DZ9: =BP9*'Reagent cost'!$C$34*60*7200 -> 419179.29 | EA9: =BQ9*'Reagent cost'!$C$14*'Reagent cost'!$C$36/1000*60*7200 -> 6948241.5 | EB9: =DA9*0.01 -> 39.6 | EC9: =DC9*0.02 -> 95.688272 | ED9: =0.1*BK9*60*7200*'Reagent cost'!$H$17*'Reagent cost'!$C$17/1000 -> 504921.6 | EE9: =BV9*0.1*'Reagent cost'!$C$16/1000*'Reagent cost'!$H$16*60*7200 -> 1723679.1 | EF9: =BZ9/1000*'Reagent cost'!$H$19*'Reagent cost'!$C$19*60*7200 -> 144826.75 | EG9: =0.33*('Costing 100 Lmin Feed Orig'!BO9*'Reagent cost'!$C$13+'Costing 100 Lmin Feed Orig'!BP9*'Reagent cost'!$C$12+'Costing 100 Lmin Feed Orig'!BQ9*'Reagent cost'!$C$14+'Costing 100 Lmin Feed Orig'!BV9*0.1*'Reagent cost'!$C$16+'Costing 100 Lmin Feed Orig'!BZ9*'Reagent cost'!$C$19)/1000*60*7200 -> 296311.85 | EH9: =CG9*'Reagent cost'!$C$35*60*7200 -> 1858335.7 | EI9: =CH9*'Reagent cost'!$C$34*60*7200 -> 442184.88 | EJ9: =CI9*'Reagent cost'!$C$14*'Reagent cost'!$C$36/1000*60*7200 -> 7329578.1 | EK9: =DB9*0.01 -> 39.6 | EL9: =DD9*0.02 -> 610.87664 | EM9: =0.1*BM9*60*7200*'Reagent cost'!$H$17*'Reagent cost'!$C$17/1000 -> 467974.14 | EN9: =CN9*0.1*'Reagent cost'!$C$16/1000*'Reagent cost'!$H$16*60*7200 -> 1818278.8 | EO9: =CR9/1000*'Reagent cost'!$H$19*'Reagent cost'!$C$19*60*7200 -> 152775.2 | EP9: =0.33*(CG9*'Reagent cost'!$C$13+CH9*'Reagent cost'!$C$12+CI9*'Reagent cost'!$C$14+CN9*0.1*'Reagent cost'!$C$16+CR9*'Reagent cost'!$C$19)/1000*60*7200 -> 312574.17 | EQ9: =(SUM(DY9:EF9)+SUM(EH9:EO9))*1.2 -> 28286895 | ER9: =EG9+EP9 -> 608886.03 | ES9: =0.499*((BK9/3.78541*15)^(-0.146))*BK9/3.78541*15*300*(1+(A9-2)/9) -> 27520.276 | ET9: =0.248*((BK9/3.78541*15)^(-0.144))*BK9/3.78541*15*300*(1+(A9-2)/3) -> 16610.44 | EU9: =0.105*((BK9/3.78541*15)^(-0.144))*BK9/3.78541*15*300*(1+(A9-2)/3) -> 7032.6458 | EV9: =0.058*((BK9/3.78541*15)^(-0.151))*BK9/3.78541*15*300*(1+(A9-2)/3) -> 3725.3887 | EW9: =0.056*((BK9/3.78541*15)^(-0.144))*BK9/3.78541*15*300*(1+(A9-2)/3) -> 3750.7444 | EX9: =SUM(ES9:EW9) -> 58639.495 | EY9: =0.499*((BM9/3.78541*15)^(-0.146))*BM9/3.78541*15*300*(1+(AF9-2)/9) -> 46423.887 | EZ9: =0.248*((BM9/3.78541*15)^(-0.144))*BM9/3.78541*15*300*(1+(AF9-2)/3) -> 46693.087 | FA9: =0.105*((BM9/3.78541*15)^(-0.144))*BM9/3.78541*15*300*(1+(AF9-2)/3) -> 19769.251 | FB9: =0.058*((BM9/3.78541*15)^(-0.151))*BM9/3.78541*15*300*(1+(AF9-2)/3) -> 10477.896 | FC9: =0.056*((BM9/3.78541*15)^(-0.144))*BM9/3.78541*15*300*(1+(AF9-2)/3) -> 10543.6 | FD9: =SUM(EY9:FC9) -> 133907.72 | FE9: =EQ9+ER9+EX9+FD9 -> 29088328 | FF9: =FE9+DX9 -> 29485183 | FG9: =BM9*AM9*195.08/1000*'PGM market prices'!$C$2*60*7200 -> 4.2373658e+08 | FH9: =BN9*AQ9*BA9*106.42/1000*'PGM market prices'!$C$3*60*7200 -> 2.2417623e+08 | FI9: =BK9*J9*102.91/1000*'PGM market prices'!$C$4*60*7200 -> 2.3748534e+08 | FJ9: =SUM(FG9:FI9) -> 8.8539814e+08 | FK9: =(1-0.26)*(FJ9-FF9) -> 6.3337559e+08 | FL9: =FF9/(BK9*60*7200) -> 0.68252739 | FM9: =FF9/7200/60/(BM9*AM9*195.08/1000) -> 2347.0826 | FN9: =FF9/7200/60/(BN9*BA9*AQ9*106.42/1000) -> 4331.1353 | FO9: =FF9/(J9*BK9*102.91/1000*60*7200) -> 20479.02
A10: 3 | B10: 0.0015414359 | C10: 0.0015414359 | D10: 0.0003425413 | E10: 0 | F10: 0 | G10: 0 | H10: 1.6300359e-05 | I10: 7.447486e-07 | J10: 0.00032385704 | K10: 0.080727109 | L10: 0.081550485 | M10: 0.00098897849 | N10: -9.8011876e-17 | O10: 1.9428903e-16 | P10: -4.3537493e-18 | Q10: 0.18892482 | R10: 94.5454 | S10: 500 | T10: 95 | U10: 1 | V10: 0.1 | W10: 52.931107 | X10: ddFc | Y10: 1 | Z10: 0.28318429 | AA10: 0.56945643 | AB10: 0.0037698629 | AC10: 1822.2108 | AD10: 2662.6059 | AE10: 2401.5031 | AF10: 12 | AG10: 0.0016455479 | AH10: 0.0016623316 | AI10: 2.0159417e-05 | AJ10: 0 | AK10: 0 | AL10: 0 | AM10: 0.0016083531 | AN10: 6.4624554e-05 | AO10: 2.002561e-05 | AP10: 0.0017297792 | AQ10: 0.074302965 | AR10: 6.2228302e-06 | AS10: 6.7762636e-20 | AT10: 2.1684043e-19 | AU10: 3.838118e-21 | AV10: 0.19929157 | AW10: 99.336255 | AX10: 500 | AY10: 95 | AZ10: 0.92682535 | BA10: 0.1 | BB10: 46.506 | BC10: coeFc | BD10: 1 | BE10: 0.018775015 | BF10: 0.10492961 | BG10: 0.001814625 | BH10: 285.19514 | BI10: 2169.8945 | BJ10: 866.49409 | BK10: =U10*100 -> 100 | BL10: =Q10*100 -> 18.892482 | BM10: =AZ10*100 -> 92.682535 | BN10: =AV10*100 -> 19.929157 | BO10: =0.6*1.2*BL10/2 -> 6.8012937 | BP10: =0.04*1.2*BL10/2 -> 0.45341958 | BQ10: =0.2*1.2*BL10/2 -> 2.2670979 | BR10: =0.1*1.2*BL10/2 -> 1.1335489 | BS10: =V10*BL10 -> 1.8892482 | BT10: =0.6*BL10*1 -> 11.335489 | BU10: =1.6*BL10*1 -> 30.227972 | BV10: =1*V10*BL10/0.2 -> 9.4462412 | BW10: =BM10-BV10 -> 83.236294 | BX10: =(SUM(BV10:BW10)+BL10)*1 -> 111.57502 | BY10: =BM10 -> 92.682535 | BZ10: =BL10*0.1*1.4 -> 2.6449475 | CA10: =7963.6*(BT10/1000)^0.6*1.7*('CAPEX+OPEX'!$G$116/'CAPEX+OPEX'!$G$115) -> 1086.1882 | CB10: =7963.6*(BU10/1000)^0.6*1.7*('CAPEX+OPEX'!$G$116/'CAPEX+OPEX'!$G$115) -> 1956.5292 | CC10: =7963.6*(BX10/1000)^0.6*1.7*('CAPEX+OPEX'!$G$116/'CAPEX+OPEX'!$G$115) -> 4283.3258 | CD10: =7963.6*(BY10/1000)^0.6*1.7*('CAPEX+OPEX'!$G$116/'CAPEX+OPEX'!$G$115) -> 3832.125 | CE10: 300 | CF10: 30 | CG10: =0.6*1.2*BN10/2 -> 7.1744964 | CH10: =0.04*1.2*BN10/2 -> 0.47829976 | CI10: =0.2*1.2*BN10/2 -> 2.3914988 | CJ10: =0.1*1.2*BN10/2 -> 1.1957494 | CK10: =0.1*BN10 -> 1.9929157 | CL10: =0.6*BN10*1 -> 11.957494 | CM10: =1.6*BN10*1 -> 31.886651 | CN10: =1*BA10*BN10/0.2 -> 9.9645783 | CO10: 0 | CP10: =(SUM(CN10:CO10)+BN10)*1 -> 29.893735 | CQ10: =CN10 -> 9.9645783 | CR10: =BN10*0.1*1.4 -> 2.7900819 | CS10: =7963.6*(CL10/1000)^0.6*1.7*('CAPEX+OPEX'!$G$116/'CAPEX+OPEX'!$G$115) -> 1121.5665 | CT10: =7963.6*(CM10/1000)^0.6*1.7*('CAPEX+OPEX'!$G$116/'CAPEX+OPEX'!$G$115) -> 2020.2554 | CU10: =7963.6*(CP10/1000)^0.6*1.7*('CAPEX+OPEX'!$G$116/'CAPEX+OPEX'!$G$115) -> 1943.5201 | CV10: =7963.6*(CQ10/1000)^0.6*1.7*('CAPEX+OPEX'!$G$116/'CAPEX+OPEX'!$G$115) -> 1005.3477 | CW10: 300 | CX10: =0.1*CW10 -> 30 | CY10: =0.1*BK10 -> 10 | CZ10: =0.1*BM10 -> 9.2682535 | DA10: =CE10*1.32*10 -> 3960 | DB10: =CW10*1.32*10 -> 3960 | DC10: =CF10*'Reagent cost'!$C$18/1000*'Reagent cost'!$H$18 -> 4784.4136 | DD10: =CX10*'Ligand cost'!$B$56*'Ligand cost'!$J$56 -> 30543.832 | DE10: =10000*1/3.78541*15 -> 39625.827 | DF10: =2510*(DE10^0.571)+89*DE10 -> 4586243.4 | DG10: =4810*(DE10^0.6)+228*DE10 -> 11794835 | DH10: =1030*(DE10^0.59)+44*DE10 -> 2275209.2 | DI10: =5640*(DE10^0.602)+272*DE10 -> 14083914 | DJ10: =688*(DE10^0.6)+32*DE10 -> 1662824.9 | DK10: =DF10*($BK$2/10000)^0.72*0.6*((A10+1)/3)^0.6*('CAPEX+OPEX'!$G$116/'CAPEX+OPEX'!$G$114) -> 277110.06 | DL10: =DG10*($BK$2/10000)^0.72*0.6*((A10+1)/3)^0.6*('CAPEX+OPEX'!$G$116/'CAPEX+OPEX'!$G$114) -> 712667.65 | DM10: =DH10*($BK$2/10000)^0.72*0.6*((A10+1)/3)^0.6*('CAPEX+OPEX'!$G$116/'CAPEX+OPEX'!$G$114) -> 137472.72 | DN10: =DI10*($BK$2/10000)^0.72*0.6*((A10+1)/3)^0.6*('CAPEX+OPEX'!$G$116/'CAPEX+OPEX'!$G$114) -> 850978.45 | DO10: =DJ10*($BK$2/10000)^0.72*0.6*((A10+1)/3)^0.6*('CAPEX+OPEX'!$G$116/'CAPEX+OPEX'!$G$114) -> 100471.23 | DP10: =SUM(DK10:DO10) -> 2078700.1 | DQ10: =DF10*(BM10/10000)^0.72*0.6*((AF10+1)/3)^0.6*('CAPEX+OPEX'!$G$116/'CAPEX+OPEX'!$G$114) -> 532133.74 | DR10: =DG10*(BM10/10000)^0.72*0.6*((AF10+1)/3)^0.6*('CAPEX+OPEX'!$G$116/'CAPEX+OPEX'!$G$114) -> 1368533.9 | DS10: =DH10*(BM10/10000)^0.72*0.6*((AF10+1)/3)^0.6*('CAPEX+OPEX'!$G$116/'CAPEX+OPEX'!$G$114) -> 263988.51 | DT10: =DI10*(BM10/10000)^0.72*0.6*((AF10+1)/3)^0.6*('CAPEX+OPEX'!$G$116/'CAPEX+OPEX'!$G$114) -> 1634131.8 | DU10: =DJ10*(BM10/10000)^0.72*0.6*((AF10+1)/3)^0.6*('CAPEX+OPEX'!$G$116/'CAPEX+OPEX'!$G$114) -> 192934.64 | DV10: =SUM(DQ10:DU10) -> 3991722.5 | DW10: =DV10+DP10+SUM(DA10:DD10)*1.15+SUM(CS10:CV10)*1.15+SUM(CA10:CD10)*1.15 -> 6139994.3 | DX10: =DW10/15 -> 409332.95 | DY10: =BO10*'Reagent cost'!$C$35*60*7200 -> 1761651.9 | DZ10: =BP10*'Reagent cost'!$C$34*60*7200 -> 419179.29 | EA10: =BQ10*'Reagent cost'!$C$14*'Reagent cost'!$C$36/1000*60*7200 -> 6948241.5 | EB10: =DA10*0.01 -> 39.6 | EC10: =DC10*0.02 -> 95.688272 | ED10: =0.1*BK10*60*7200*'Reagent cost'!$H$17*'Reagent cost'!$C$17/1000 -> 504921.6 | EE10: =BV10*0.1*'Reagent cost'!$C$16/1000*'Reagent cost'!$H$16*60*7200 -> 1723679.1 | EF10: =BZ10/1000*'Reagent cost'!$H$19*'Reagent cost'!$C$19*60*7200 -> 144826.75 | EG10: =0.33*('Costing 100 Lmin Feed Orig'!BO10*'Reagent cost'!$C$13+'Costing 100 Lmin Feed Orig'!BP10*'Reagent cost'!$C$12+'Costing 100 Lmin Feed Orig'!BQ10*'Reagent cost'!$C$14+'Costing 100 Lmin Feed Orig'!BV10*0.1*'Reagent cost'!$C$16+'Costing 100 Lmin Feed Orig'!BZ10*'Reagent cost'!$C$19)/1000*60*7200 -> 296311.85 | EH10: =CG10*'Reagent cost'!$C$35*60*7200 -> 1858317.8 | EI10: =CH10*'Reagent cost'!$C$34*60*7200 -> 442180.63 | EJ10: =CI10*'Reagent cost'!$C$14*'Reagent cost'!$C$36/1000*60*7200 -> 7329507.6 | EK10: =DB10*0.01 -> 39.6 | EL10: =DD10*0.02 -> 610.87664 | EM10: =0.1*BM10*60*7200*'Reagent cost'!$H$17*'Reagent cost'!$C$17/1000 -> 467974.14 | EN10: =CN10*0.1*'Reagent cost'!$C$16/1000*'Reagent cost'!$H$16*60*7200 -> 1818261.3 | EO10: =CR10/1000*'Reagent cost'!$H$19*'Reagent cost'!$C$19*60*7200 -> 152773.73 | EP10: =0.33*(CG10*'Reagent cost'!$C$13+CH10*'Reagent cost'!$C$12+CI10*'Reagent cost'!$C$14+CN10*0.1*'Reagent cost'!$C$16+CR10*'Reagent cost'!$C$19)/1000*60*7200 -> 312571.17 | EQ10: =(SUM(DY10:EF10)+SUM(EH10:EO10))*1.2 -> 28286761 | ER10: =EG10+EP10 -> 608883.02 | ES10: =0.499*((BK10/3.78541*15)^(-0.146))*BK10/3.78541*15*300*(1+(A10-2)/9) -> 27520.276 | ET10: =0.248*((BK10/3.78541*15)^(-0.144))*BK10/3.78541*15*300*(1+(A10-2)/3) -> 16610.44 | EU10: =0.105*((BK10/3.78541*15)^(-0.144))*BK10/3.78541*15*300*(1+(A10-2)/3) -> 7032.6458 | EV10: =0.058*((BK10/3.78541*15)^(-0.151))*BK10/3.78541*15*300*(1+(A10-2)/3) -> 3725.3887 | EW10: =0.056*((BK10/3.78541*15)^(-0.144))*BK10/3.78541*15*300*(1+(A10-2)/3) -> 3750.7444 | EX10: =SUM(ES10:EW10) -> 58639.495 | EY10: =0.499*((BM10/3.78541*15)^(-0.146))*BM10/3.78541*15*300*(1+(AF10-2)/9) -> 49002.992 | EZ10: =0.248*((BM10/3.78541*15)^(-0.144))*BM10/3.78541*15*300*(1+(AF10-2)/3) -> 50584.178 | FA10: =0.105*((BM10/3.78541*15)^(-0.144))*BM10/3.78541*15*300*(1+(AF10-2)/3) -> 21416.688 | FB10: =0.058*((BM10/3.78541*15)^(-0.151))*BM10/3.78541*15*300*(1+(AF10-2)/3) -> 11351.054 | FC10: =0.056*((BM10/3.78541*15)^(-0.144))*BM10/3.78541*15*300*(1+(AF10-2)/3) -> 11422.234 | FD10: =SUM(EY10:FC10) -> 143777.15 | FE10: =EQ10+ER10+EX10+FD10 -> 29098061 | FF10: =FE10+DX10 -> 29507394 | FG10: =BM10*AM10*195.08/1000*'PGM market prices'!$C$2*60*7200 -> 4.2373691e+08 | FH10: =BN10*AQ10*BA10*106.42/1000*'PGM market prices'!$C$3*60*7200 -> 2.2417622e+08 | FI10: =BK10*J10*102.91/1000*'PGM market prices'!$C$4*60*7200 -> 2.3748534e+08 | FJ10: =SUM(FG10:FI10) -> 8.8539847e+08 | FK10: =(1-0.26)*(FJ10-FF10) -> 6.333594e+08 | FL10: =FF10/(BK10*60*7200) -> 0.68304153 | FM10: =FF10/7200/60/(BM10*AM10*195.08/1000) -> 2348.8487 | FN10: =FF10/7200/60/(BN10*BA10*AQ10*106.42/1000) -> 4334.398 | FO10: =FF10/(J10*BK10*102.91/1000*60*7200) -> 20494.446
A11: 3 | B11: 0.0015414359 | C11: 0.0015414359 | D11: 0.0003425413 | E11: 0 | F11: 0 | G11: 0 | H11: 1.6300359e-05 | I11: 7.447486e-07 | J11: 0.00032385704 | K11: 0.080727109 | L11: 0.081550485 | M11: 0.00098897849 | N11: -9.8011876e-17 | O11: 1.9428903e-16 | P11: -4.3537493e-18 | Q11: 0.18892482 | R11: 94.5454 | S11: 500 | T11: 95 | U11: 1 | V11: 0.1 | W11: 52.931107 | X11: ddFc | Y11: 1 | Z11: 0.28318429 | AA11: 0.56945643 | AB11: 0.0037698629 | AC11: 1822.2108 | AD11: 2662.6059 | AE11: 2401.5031 | AF11: 13 | AG11: 0.0016455479 | AH11: 0.0016623316 | AI11: 2.0159417e-05 | AJ11: 0 | AK11: 0 | AL11: 0 | AM11: 0.0016083535 | AN11: 6.4624572e-05 | AO11: 2.0025611e-05 | AP11: 0.0017297671 | AQ11: 0.074303169 | AR11: 6.222789e-06 | AS11: 2.6305455e-17 | AT11: -2.1278552e-15 | AU11: -5.2939559e-22 | AV11: 0.19929102 | AW11: 99.336262 | AX11: 500 | AY11: 95 | AZ11: 0.92682535 | BA11: 0.1 | BB11: 46.506128 | BC11: coeFc | BD11: 1 | BE11: 0.018775015 | BF11: 0.10492961 | BG11: 0.001814625 | BH11: 285.19514 | BI11: 2169.8945 | BJ11: 866.49409 | BK11: =U11*100 -> 100 | BL11: =Q11*100 -> 18.892482 | BM11: =AZ11*100 -> 92.682535 | BN11: =AV11*100 -> 19.929102 | BO11: =0.6*1.2*BL11/2 -> 6.8012937 | BP11: =0.04*1.2*BL11/2 -> 0.45341958 | BQ11: =0.2*1.2*BL11/2 -> 2.2670979 | BR11: =0.1*1.2*BL11/2 -> 1.1335489 | BS11: =V11*BL11 -> 1.8892482 | BT11: =0.6*BL11*1 -> 11.335489 | BU11: =1.6*BL11*1 -> 30.227972 | BV11: =1*V11*BL11/0.2 -> 9.4462412 | BW11: =BM11-BV11 -> 83.236294 | BX11: =(SUM(BV11:BW11)+BL11)*1 -> 111.57502 | BY11: =BM11 -> 92.682535 | BZ11: =BL11*0.1*1.4 -> 2.6449475 | CA11: =7963.6*(BT11/1000)^0.6*1.7*('CAPEX+OPEX'!$G$116/'CAPEX+OPEX'!$G$115) -> 1086.1882 | CB11: =7963.6*(BU11/1000)^0.6*1.7*('CAPEX+OPEX'!$G$116/'CAPEX+OPEX'!$G$115) -> 1956.5292 | CC11: =7963.6*(BX11/1000)^0.6*1.7*('CAPEX+OPEX'!$G$116/'CAPEX+OPEX'!$G$115) -> 4283.3258 | CD11: =7963.6*(BY11/1000)^0.6*1.7*('CAPEX+OPEX'!$G$116/'CAPEX+OPEX'!$G$115) -> 3832.125 | CE11: 300 | CF11: 30 | CG11: =0.6*1.2*BN11/2 -> 7.1744766 | CH11: =0.04*1.2*BN11/2 -> 0.47829844 | CI11: =0.2*1.2*BN11/2 -> 2.3914922 | CJ11: =0.1*1.2*BN11/2 -> 1.1957461 | CK11: =0.1*BN11 -> 1.9929102 | CL11: =0.6*BN11*1 -> 11.957461 | CM11: =1.6*BN11*1 -> 31.886563 | CN11: =1*BA11*BN11/0.2 -> 9.9645509 | CO11: 0 | CP11: =(SUM(CN11:CO11)+BN11)*1 -> 29.893653 | CQ11: =CN11 -> 9.9645509 | CR11: =BN11*0.1*1.4 -> 2.7900743 | CS11: =7963.6*(CL11/1000)^0.6*1.7*('CAPEX+OPEX'!$G$116/'CAPEX+OPEX'!$G$115) -> 1121.5647 | CT11: =7963.6*(CM11/1000)^0.6*1.7*('CAPEX+OPEX'!$G$116/'CAPEX+OPEX'!$G$115) -> 2020.252 | CU11: =7963.6*(CP11/1000)^0.6*1.7*('CAPEX+OPEX'!$G$116/'CAPEX+OPEX'!$G$115) -> 1943.5169 | CV11: =7963.6*(CQ11/1000)^0.6*1.7*('CAPEX+OPEX'!$G$116/'CAPEX+OPEX'!$G$115) -> 1005.346 | CW11: 300 | CX11: =0.1*CW11 -> 30 | CY11: =0.1*BK11 -> 10 | CZ11: =0.1*BM11 -> 9.2682535 | DA11: =CE11*1.32*10 -> 3960 | DB11: =CW11*1.32*10 -> 3960 | DC11: =CF11*'Reagent cost'!$C$18/1000*'Reagent cost'!$H$18 -> 4784.4136 | DD11: =CX11*'Ligand cost'!$B$56*'Ligand cost'!$J$56 -> 30543.832 | DE11: =10000*1/3.78541*15 -> 39625.827 | DF11: =2510*(DE11^0.571)+89*DE11 -> 4586243.4 | DG11: =4810*(DE11^0.6)+228*DE11 -> 11794835 | DH11: =1030*(DE11^0.59)+44*DE11 -> 2275209.2 | DI11: =5640*(DE11^0.602)+272*DE11 -> 14083914 | DJ11: =688*(DE11^0.6)+32*DE11 -> 1662824.9 | DK11: =DF11*($BK$2/10000)^0.72*0.6*((A11+1)/3)^0.6*('CAPEX+OPEX'!$G$116/'CAPEX+OPEX'!$G$114) -> 277110.06 | DL11: =DG11*($BK$2/10000)^0.72*0.6*((A11+1)/3)^0.6*('CAPEX+OPEX'!$G$116/'CAPEX+OPEX'!$G$114) -> 712667.65 | DM11: =DH11*($BK$2/10000)^0.72*0.6*((A11+1)/3)^0.6*('CAPEX+OPEX'!$G$116/'CAPEX+OPEX'!$G$114) -> 137472.72 | DN11: =DI11*($BK$2/10000)^0.72*0.6*((A11+1)/3)^0.6*('CAPEX+OPEX'!$G$116/'CAPEX+OPEX'!$G$114) -> 850978.45 | DO11: =DJ11*($BK$2/10000)^0.72*0.6*((A11+1)/3)^0.6*('CAPEX+OPEX'!$G$116/'CAPEX+OPEX'!$G$114) -> 100471.23 | DP11: =SUM(DK11:DO11) -> 2078700.1 | DQ11: =DF11*(BM11/10000)^0.72*0.6*((AF11+1)/3)^0.6*('CAPEX+OPEX'!$G$116/'CAPEX+OPEX'!$G$114) -> 556328.88 | DR11: =DG11*(BM11/10000)^0.72*0.6*((AF11+1)/3)^0.6*('CAPEX+OPEX'!$G$116/'CAPEX+OPEX'!$G$114) -> 1430758.6 | DS11: =DH11*(BM11/10000)^0.72*0.6*((AF11+1)/3)^0.6*('CAPEX+OPEX'!$G$116/'CAPEX+OPEX'!$G$114) -> 275991.58 | DT11: =DI11*(BM11/10000)^0.72*0.6*((AF11+1)/3)^0.6*('CAPEX+OPEX'!$G$116/'CAPEX+OPEX'!$G$114) -> 1708432.7 | DU11: =DJ11*(BM11/10000)^0.72*0.6*((AF11+1)/3)^0.6*('CAPEX+OPEX'!$G$116/'CAPEX+OPEX'!$G$114) -> 201707.03 | DV11: =SUM(DQ11:DU11) -> 4173218.8 | DW11: =DV11+DP11+SUM(DA11:DD11)*1.15+SUM(CS11:CV11)*1.15+SUM(CA11:CD11)*1.15 -> 6321490.6 | DX11: =DW11/15 -> 421432.7 | DY11: =BO11*'Reagent cost'!$C$35*60*7200 -> 1761651.9 | DZ11: =BP11*'Reagent cost'!$C$34*60*7200 -> 419179.29 | EA11: =BQ11*'Reagent cost'!$C$14*'Reagent cost'!$C$36/1000*60*7200 -> 6948241.5 | EB11: =DA11*0.01 -> 39.6 | EC11: =DC11*0.02 -> 95.688272 | ED11: =0.1*BK11*60*7200*'Reagent cost'!$H$17*'Reagent cost'!$C$17/1000 -> 504921.6 | EE11: =BV11*0.1*'Reagent cost'!$C$16/1000*'Reagent cost'!$H$16*60*7200 -> 1723679.1 | EF11: =BZ11/1000*'Reagent cost'!$H$19*'Reagent cost'!$C$19*60*7200 -> 144826.75 | EG11: =0.33*('Costing 100 Lmin Feed Orig'!BO11*'Reagent cost'!$C$13+'Costing 100 Lmin Feed Orig'!BP11*'Reagent cost'!$C$12+'Costing 100 Lmin Feed Orig'!BQ11*'Reagent cost'!$C$14+'Costing 100 Lmin Feed Orig'!BV11*0.1*'Reagent cost'!$C$16+'Costing 100 Lmin Feed Orig'!BZ11*'Reagent cost'!$C$19)/1000*60*7200 -> 296311.85 | EH11: =CG11*'Reagent cost'!$C$35*60*7200 -> 1858312.7 | EI11: =CH11*'Reagent cost'!$C$34*60*7200 -> 442179.41 | EJ11: =CI11*'Reagent cost'!$C$14*'Reagent cost'!$C$36/1000*60*7200 -> 7329487.4 | EK11: =DB11*0.01 -> 39.6 | EL11: =DD11*0.02 -> 610.87664 | EM11: =0.1*BM11*60*7200*'Reagent cost'!$H$17*'Reagent cost'!$C$17/1000 -> 467974.14 | EN11: =CN11*0.1*'Reagent cost'!$C$16/1000*'Reagent cost'!$H$16*60*7200 -> 1818256.3 | EO11: =CR11/1000*'Reagent cost'!$H$19*'Reagent cost'!$C$19*60*7200 -> 152773.31 | EP11: =0.33*(CG11*'Reagent cost'!$C$13+CH11*'Reagent cost'!$C$12+CI11*'Reagent cost'!$C$14+CN11*0.1*'Reagent cost'!$C$16+CR11*'Reagent cost'!$C$19)/1000*60*7200 -> 312570.31 | EQ11: =(SUM(DY11:EF11)+SUM(EH11:EO11))*1.2 -> 28286723 | ER11: =EG11+EP11 -> 608882.16 | ES11: =0.499*((BK11/3.78541*15)^(-0.146))*BK11/3.78541*15*300*(1+(A11-2)/9) -> 27520.276 | ET11: =0.248*((BK11/3.78541*15)^(-0.144))*BK11/3.78541*15*300*(1+(A11-2)/3) -> 16610.44 | EU11: =0.105*((BK11/3.78541*15)^(-0.144))*BK11/3.78541*15*300*(1+(A11-2)/3) -> 7032.6458 | EV11: =0.058*((BK11/3.78541*15)^(-0.151))*BK11/3.78541*15*300*(1+(A11-2)/3) -> 3725.3887 | EW11: =0.056*((BK11/3.78541*15)^(-0.144))*BK11/3.78541*15*300*(1+(A11-2)/3) -> 3750.7444 | EX11: =SUM(ES11:EW11) -> 58639.495 | EY11: =0.499*((BM11/3.78541*15)^(-0.146))*BM11/3.78541*15*300*(1+(AF11-2)/9) -> 51582.097 | EZ11: =0.248*((BM11/3.78541*15)^(-0.144))*BM11/3.78541*15*300*(1+(AF11-2)/3) -> 54475.268 | FA11: =0.105*((BM11/3.78541*15)^(-0.144))*BM11/3.78541*15*300*(1+(AF11-2)/3) -> 23064.126 | FB11: =0.058*((BM11/3.78541*15)^(-0.151))*BM11/3.78541*15*300*(1+(AF11-2)/3) -> 12224.212 | FC11: =0.056*((BM11/3.78541*15)^(-0.144))*BM11/3.78541*15*300*(1+(AF11-2)/3) -> 12300.867 | FD11: =SUM(EY11:FC11) -> 153646.57 | FE11: =EQ11+ER11+EX11+FD11 -> 29107891 | FF11: =FE11+DX11 -> 29529324 | FG11: =BM11*AM11*195.08/1000*'PGM market prices'!$C$2*60*7200 -> 4.2373701e+08 | FH11: =BN11*AQ11*BA11*106.42/1000*'PGM market prices'!$C$3*60*7200 -> 2.2417622e+08 | FI11: =BK11*J11*102.91/1000*'PGM market prices'!$C$4*60*7200 -> 2.3748534e+08 | FJ11: =SUM(FG11:FI11) -> 8.8539856e+08 | FK11: =(1-0.26)*(FJ11-FF11) -> 6.3334324e+08 | FL11: =FF11/(BK11*60*7200) -> 0.68354917 | FM11: =FF11/7200/60/(BM11*AM11*195.08/1000) -> 2350.5939 | FN11: =FF11/7200/60/(BN11*BA11*AQ11*106.42/1000) -> 4337.6194 | FO11: =FF11/(J11*BK11*102.91/1000*60*7200) -> 20509.678
A12: 4 | B12: 0.0015414359 | C12: 0.0015414359 | D12: 0.0003425413 | E12: 0 | F12: 0 | G12: 0 | H12: 1.7208961e-05 | I12: 2.8768785e-07 | J12: 0.00033243633 | K12: 0.10920586 | L12: 0.11041822 | M12: 0.00072398826 | N12: -2.1684043e-18 | O12: 2.3635607e-17 | P12: -7.4538899e-20 | Q12: 0.13957372 | R12: 97.049998 | S12: 500 | T12: 95 | U12: 1 | V12: 0.1 | W12: 71.646723 | X12: ddFc | Y12: 1 | Z12: 0.28318429 | AA12: 0.56945643 | AB12: 0.0037698629 | AC12: 1822.2108 | AD12: 2662.6059 | AE12: 2401.5031 | AF12: 4 | AG12: 0.001648165 | AH12: 0.0016664622 | AI12: 1.0926631e-05 | AJ12: 0 | AK12: 0 | AL12: 0 | AM12: 0.0016024674 | AN12: 7.3502024e-05 | AO12: 1.0838365e-05 | AP12: 0.0020055299 | AQ12: 0.069910132 | AR12: 3.8737261e-06 | AS12: -3.2526065e-19 | AT12: 2.6020852e-18 | AU12: 7.9409339e-23 | AV12: 0.21072386 | AW12: 99.192193 | AX12: 500 | AY12: 95 | AZ12: 0.92480234 | BA12: 0.1 | BB12: 43.88693 | BC12: coeFc | BD12: 1 | BE12: 0.018775015 | BF12: 0.10492961 | BG12: 0.001814625 | BH12: 285.19514 | BI12: 2169.8945 | BJ12: 866.49409 | BK12: =U12*100 -> 100 | BL12: =Q12*100 -> 13.957372 | BM12: =AZ12*100 -> 92.480234 | BN12: =AV12*100 -> 21.072386 | BO12: =0.6*1.2*BL12/2 -> 5.0246541 | BP12: =0.04*1.2*BL12/2 -> 0.33497694 | BQ12: =0.2*1.2*BL12/2 -> 1.6748847 | BR12: =0.1*1.2*BL12/2 -> 0.83744235 | BS12: =V12*BL12 -> 1.3957372 | BT12: =0.6*BL12*1 -> 8.3744235 | BU12: =1.6*BL12*1 -> 22.331796 | BV12: =1*V12*BL12/0.2 -> 6.9786862 | BW12: =BM12-BV12 -> 85.501548 | BX12: =(SUM(BV12:BW12)+BL12)*1 -> 106.43761 | BY12: =BM12 -> 92.480234 | BZ12: =BL12*0.1*1.4 -> 1.9540321 | CA12: =7963.6*(BT12/1000)^0.6*1.7*('CAPEX+OPEX'!$G$116/'CAPEX+OPEX'!$G$115) -> 905.76155 | CB12: =7963.6*(BU12/1000)^0.6*1.7*('CAPEX+OPEX'!$G$116/'CAPEX+OPEX'!$G$115) -> 1631.5302 | CC12: =7963.6*(BX12/1000)^0.6*1.7*('CAPEX+OPEX'!$G$116/'CAPEX+OPEX'!$G$115) -> 4163.8779 | CD12: =7963.6*(BY12/1000)^0.6*1.7*('CAPEX+OPEX'!$G$116/'CAPEX+OPEX'!$G$115) -> 3827.1041 | CE12: 300 | CF12: 30 | CG12: =0.6*1.2*BN12/2 -> 7.5860591 | CH12: =0.04*1.2*BN12/2 -> 0.50573727 | CI12: =0.2*1.2*BN12/2 -> 2.5286864 | CJ12: =0.1*1.2*BN12/2 -> 1.2643432 | CK12: =0.1*BN12 -> 2.1072386 | CL12: =0.6*BN12*1 -> 12.643432 | CM12: =1.6*BN12*1 -> 33.715818 | CN12: =1*BA12*BN12/0.2 -> 10.536193 | CO12: 0 | CP12: =(SUM(CN12:CO12)+BN12)*1 -> 31.60858 | CQ12: =CN12 -> 10.536193 | CR12: =BN12*0.1*1.4 -> 2.9501341 | CS12: =7963.6*(CL12/1000)^0.6*1.7*('CAPEX+OPEX'!$G$116/'CAPEX+OPEX'!$G$115) -> 1159.7381 | CT12: =7963.6*(CM12/1000)^0.6*1.7*('CAPEX+OPEX'!$G$116/'CAPEX+OPEX'!$G$115) -> 2089.013 | CU12: =7963.6*(CP12/1000)^0.6*1.7*('CAPEX+OPEX'!$G$116/'CAPEX+OPEX'!$G$115) -> 2009.6661 | CV12: =7963.6*(CQ12/1000)^0.6*1.7*('CAPEX+OPEX'!$G$116/'CAPEX+OPEX'!$G$115) -> 1039.5638 | CW12: 300 | CX12: =0.1*CW12 -> 30 | CY12: =0.1*BK12 -> 10 | CZ12: =0.1*BM12 -> 9.2480234 | DA12: =CE12*1.32*10 -> 3960 | DB12: =CW12*1.32*10 -> 3960 | DC12: =CF12*'Reagent cost'!$C$18/1000*'Reagent cost'!$H$18 -> 4784.4136 | DD12: =CX12*'Ligand cost'!$B$56*'Ligand cost'!$J$56 -> 30543.832 | DE12: =10000*1/3.78541*15 -> 39625.827 | DF12: =2510*(DE12^0.571)+89*DE12 -> 4586243.4 | DG12: =4810*(DE12^0.6)+228*DE12 -> 11794835 | DH12: =1030*(DE12^0.59)+44*DE12 -> 2275209.2 | DI12: =5640*(DE12^0.602)+272*DE12 -> 14083914 | DJ12: =688*(DE12^0.6)+32*DE12 -> 1662824.9 | DK12: =DF12*($BK$2/10000)^0.72*0.6*((A12+1)/3)^0.6*('CAPEX+OPEX'!$G$116/'CAPEX+OPEX'!$G$114) -> 316809.57 | DL12: =DG12*($BK$2/10000)^0.72*0.6*((A12+1)/3)^0.6*('CAPEX+OPEX'!$G$116/'CAPEX+OPEX'!$G$114) -> 814766.29 | DM12: =DH12*($BK$2/10000)^0.72*0.6*((A12+1)/3)^0.6*('CAPEX+OPEX'!$G$116/'CAPEX+OPEX'!$G$114) -> 157167.42 | DN12: =DI12*($BK$2/10000)^0.72*0.6*((A12+1)/3)^0.6*('CAPEX+OPEX'!$G$116/'CAPEX+OPEX'!$G$114) -> 972891.86 | DO12: =DJ12*($BK$2/10000)^0.72*0.6*((A12+1)/3)^0.6*('CAPEX+OPEX'!$G$116/'CAPEX+OPEX'!$G$114) -> 114865 | DP12: =SUM(DK12:DO12) -> 2376500.1 | DQ12: =DF12*(BM12/10000)^0.72*0.6*((AF12+1)/3)^0.6*('CAPEX+OPEX'!$G$116/'CAPEX+OPEX'!$G$114) -> 299470.14 | DR12: =DG12*(BM12/10000)^0.72*0.6*((AF12+1)/3)^0.6*('CAPEX+OPEX'!$G$116/'CAPEX+OPEX'!$G$114) -> 770172.97 | DS12: =DH12*(BM12/10000)^0.72*0.6*((AF12+1)/3)^0.6*('CAPEX+OPEX'!$G$116/'CAPEX+OPEX'!$G$114) -> 148565.42 | DT12: =DI12*(BM12/10000)^0.72*0.6*((AF12+1)/3)^0.6*('CAPEX+OPEX'!$G$116/'CAPEX+OPEX'!$G$114) -> 919644.11 | DU12: =DJ12*(BM12/10000)^0.72*0.6*((AF12+1)/3)^0.6*('CAPEX+OPEX'!$G$116/'CAPEX+OPEX'!$G$114) -> 108578.27 | DV12: =SUM(DQ12:DU12) -> 2246430.9 | DW12: =DV12+DP12+SUM(DA12:DD12)*1.15+SUM(CS12:CV12)*1.15+SUM(CA12:CD12)*1.15 -> 4692016.7 | DX12: =DW12/15 -> 312801.12 | DY12: =BO12*'Reagent cost'!$C$35*60*7200 -> 1301471.7 | DZ12: =BP12*'Reagent cost'!$C$34*60*7200 -> 309680.93 | EA12: =BQ12*'Reagent cost'!$C$14*'Reagent cost'!$C$36/1000*60*7200 -> 5133216.1 | EB12: =DA12*0.01 -> 39.6 | EC12: =DC12*0.02 -> 95.688272 | ED12: =0.1*BK12*60*7200*'Reagent cost'!$H$17*'Reagent cost'!$C$17/1000 -> 504921.6 | EE12: =BV12*0.1*'Reagent cost'!$C$16/1000*'Reagent cost'!$H$16*60*7200 -> 1273418.2 | EF12: =BZ12/1000*'Reagent cost'!$H$19*'Reagent cost'!$C$19*60*7200 -> 106994.98 | EG12: =0.33*('Costing 100 Lmin Feed Orig'!BO12*'Reagent cost'!$C$13+'Costing 100 Lmin Feed Orig'!BP12*'Reagent cost'!$C$12+'Costing 100 Lmin Feed Orig'!BQ12*'Reagent cost'!$C$14+'Costing 100 Lmin Feed Orig'!BV12*0.1*'Reagent cost'!$C$16+'Costing 100 Lmin Feed Orig'!BZ12*'Reagent cost'!$C$19)/1000*60*7200 -> 218909.02 | EH12: =CG12*'Reagent cost'!$C$35*60*7200 -> 1964919.6 | EI12: =CH12*'Reagent cost'!$C$34*60*7200 -> 467546.18 | EJ12: =CI12*'Reagent cost'!$C$14*'Reagent cost'!$C$36/1000*60*7200 -> 7749962.5 | EK12: =DB12*0.01 -> 39.6 | EL12: =DD12*0.02 -> 610.87664 | EM12: =0.1*BM12*60*7200*'Reagent cost'!$H$17*'Reagent cost'!$C$17/1000 -> 466952.68 | EN12: =CN12*0.1*'Reagent cost'!$C$16/1000*'Reagent cost'!$H$16*60*7200 -> 1922565.3 | EO12: =CR12/1000*'Reagent cost'!$H$19*'Reagent cost'!$C$19*60*7200 -> 161537.54 | EP12: =0.33*(CG12*'Reagent cost'!$C$13+CH12*'Reagent cost'!$C$12+CI12*'Reagent cost'!$C$14+CN12*0.1*'Reagent cost'!$C$16+CR12*'Reagent cost'!$C$19)/1000*60*7200 -> 330501.71 | EQ12: =(SUM(DY12:EF12)+SUM(EH12:EO12))*1.2 -> 25636768 | ER12: =EG12+EP12 -> 549410.74 | ES12: =0.499*((BK12/3.78541*15)^(-0.146))*BK12/3.78541*15*300*(1+(A12-2)/9) -> 30272.304 | ET12: =0.248*((BK12/3.78541*15)^(-0.144))*BK12/3.78541*15*300*(1+(A12-2)/3) -> 20763.049 | EU12: =0.105*((BK12/3.78541*15)^(-0.144))*BK12/3.78541*15*300*(1+(A12-2)/3) -> 8790.8072 | EV12: =0.058*((BK12/3.78541*15)^(-0.151))*BK12/3.78541*15*300*(1+(A12-2)/3) -> 4656.7358 | EW12: =0.056*((BK12/3.78541*15)^(-0.144))*BK12/3.78541*15*300*(1+(A12-2)/3) -> 4688.4305 | EX12: =SUM(ES12:EW12) -> 69171.327 | EY12: =0.499*((BM12/3.78541*15)^(-0.146))*BM12/3.78541*15*300*(1+(AF12-2)/9) -> 28317.261 | EZ12: =0.248*((BM12/3.78541*15)^(-0.144))*BM12/3.78541*15*300*(1+(AF12-2)/3) -> 19419.096 | FA12: =0.105*((BM12/3.78541*15)^(-0.144))*BM12/3.78541*15*300*(1+(AF12-2)/3) -> 8221.7948 | FB12: =0.058*((BM12/3.78541*15)^(-0.151))*BM12/3.78541*15*300*(1+(AF12-2)/3) -> 4357.6981 | FC12: =0.056*((BM12/3.78541*15)^(-0.144))*BM12/3.78541*15*300*(1+(AF12-2)/3) -> 4384.9572 | FD12: =SUM(EY12:FC12) -> 64700.808 | FE12: =EQ12+ER12+EX12+FD12 -> 26320051 | FF12: =FE12+DX12 -> 26632852 | FG12: =BM12*AM12*195.08/1000*'PGM market prices'!$C$2*60*7200 -> 4.2126474e+08 | FH12: =BN12*AQ12*BA12*106.42/1000*'PGM market prices'!$C$3*60*7200 -> 2.2302232e+08 | FI12: =BK12*J12*102.91/1000*'PGM market prices'!$C$4*60*7200 -> 2.4377655e+08 | FJ12: =SUM(FG12:FI12) -> 8.880636e+08 | FK12: =(1-0.26)*(FJ12-FF12) -> 6.3745876e+08 | FL12: =FF12/(BK12*60*7200) -> 0.6165012 | FM12: =FF12/7200/60/(BM12*AM12*195.08/1000) -> 2132.4706 | FN12: =FF12/7200/60/(BN12*BA12*AQ12*106.42/1000) -> 3932.3922 | FO12: =FF12/(J12*BK12*102.91/1000*60*7200) -> 18020.543
A13: 4 | B13: 0.0015414359 | C13: 0.0015414359 | D13: 0.0003425413 | E13: 0 | F13: 0 | G13: 0 | H13: 1.7208961e-05 | I13: 2.8768785e-07 | J13: 0.00033243633 | K13: 0.10920586 | L13: 0.11041822 | M13: 0.00072398826 | N13: -2.1684043e-18 | O13: 2.3635607e-17 | P13: -7.4538899e-20 | Q13: 0.13957372 | R13: 97.049998 | S13: 500 | T13: 95 | U13: 1 | V13: 0.1 | W13: 71.646723 | X13: ddFc | Y13: 1 | Z13: 0.28318429 | AA13: 0.56945643 | AB13: 0.0037698629 | AC13: 1822.2108 | AD13: 2662.6059 | AE13: 2401.5031 | AF13: 5 | AG13: 0.001648165 | AH13: 0.0016664622 | AI13: 1.0926631e-05 | AJ13: 0 | AK13: 0 | AL13: 0 | AM13: 0.0016085253 | AN13: 7.3809557e-05 | AO13: 1.0849671e-05 | AP13: 0.0018177669 | AQ13: 0.073034601 | AR13: 3.5291806e-06 | AS13: -2.4283418e-16 | AT13: -3.6784811e-15 | AU13: -2.6574335e-19 | AV13: 0.20167001 | AW13: 99.295664 | AX13: 500 | AY13: 95 | AZ13: 0.92480234 | BA13: 0.1 | BB13: 45.857206 | BC13: coeFc | BD13: 1 | BE13: 0.018775015 | BF13: 0.10492961 | BG13: 0.001814625 | BH13: 285.19514 | BI13: 2169.8945 | BJ13: 866.49409 | BK13: =U13*100 -> 100 | BL13: =Q13*100 -> 13.957372 | BM13: =AZ13*100 -> 92.480234 | BN13: =AV13*100 -> 20.167001 | BO13: =0.6*1.2*BL13/2 -> 5.0246541 | BP13: =0.04*1.2*BL13/2 -> 0.33497694 | BQ13: =0.2*1.2*BL13/2 -> 1.6748847 | BR13: =0.1*1.2*BL13/2 -> 0.83744235 | BS13: =V13*BL13 -> 1.3957372 | BT13: =0.6*BL13*1 -> 8.3744235 | BU13: =1.6*BL13*1 -> 22.331796 | BV13: =1*V13*BL13/0.2 -> 6.9786862 | BW13: =BM13-BV13 -> 85.501548 | BX13: =(SUM(BV13:BW13)+BL13)*1 -> 106.43761 | BY13: =BM13 -> 92.480234 | BZ13: =BL13*0.1*1.4 -> 1.9540321 | CA13: =7963.6*(BT13/1000)^0.6*1.7*('CAPEX+OPEX'!$G$116/'CAPEX+OPEX'!$G$115) -> 905.76155 | CB13: =7963.6*(BU13/1000)^0.6*1.7*('CAPEX+OPEX'!$G$116/'CAPEX+OPEX'!$G$115) -> 1631.5302 | CC13: =7963.6*(BX13/1000)^0.6*1.7*('CAPEX+OPEX'!$G$116/'CAPEX+OPEX'!$G$115) -> 4163.8779 | CD13: =7963.6*(BY13/1000)^0.6*1.7*('CAPEX+OPEX'!$G$116/'CAPEX+OPEX'!$G$115) -> 3827.1041 | CE13: 300 | CF13: 30 | CG13: =0.6*1.2*BN13/2 -> 7.2601205 | CH13: =0.04*1.2*BN13/2 -> 0.48400803 | CI13: =0.2*1.2*BN13/2 -> 2.4200402 | CJ13: =0.1*1.2*BN13/2 -> 1.2100201 | CK13: =0.1*BN13 -> 2.0167001 | CL13: =0.6*BN13*1 -> 12.100201 | CM13: =1.6*BN13*1 -> 32.267202 | CN13: =1*BA13*BN13/0.2 -> 10.083501 | CO13: 0 | CP13: =(SUM(CN13:CO13)+BN13)*1 -> 30.250502 | CQ13: =CN13 -> 10.083501 | CR13: =BN13*0.1*1.4 -> 2.8233802 | CS13: =7963.6*(CL13/1000)^0.6*1.7*('CAPEX+OPEX'!$G$116/'CAPEX+OPEX'!$G$115) -> 1129.5787 | CT13: =7963.6*(CM13/1000)^0.6*1.7*('CAPEX+OPEX'!$G$116/'CAPEX+OPEX'!$G$115) -> 2034.6875 | CU13: =7963.6*(CP13/1000)^0.6*1.7*('CAPEX+OPEX'!$G$116/'CAPEX+OPEX'!$G$115) -> 1957.404 | CV13: =7963.6*(CQ13/1000)^0.6*1.7*('CAPEX+OPEX'!$G$116/'CAPEX+OPEX'!$G$115) -> 1012.5296 | CW13: 300 | CX13: =0.1*CW13 -> 30 | CY13: =0.1*BK13 -> 10 | CZ13: =0.1*BM13 -> 9.2480234 | DA13: =CE13*1.32*10 -> 3960 | DB13: =CW13*1.32*10 -> 3960 | DC13: =CF13*'Reagent cost'!$C$18/1000*'Reagent cost'!$H$18 -> 4784.4136 | DD13: =CX13*'Ligand cost'!$B$56*'Ligand cost'!$J$56 -> 30543.832 | DE13: =10000*1/3.78541*15 -> 39625.827 | DF13: =2510*(DE13^0.571)+89*DE13 -> 4586243.4 | DG13: =4810*(DE13^0.6)+228*DE13 -> 11794835 | DH13: =1030*(DE13^0.59)+44*DE13 -> 2275209.2 | DI13: =5640*(DE13^0.602)+272*DE13 -> 14083914 | DJ13: =688*(DE13^0.6)+32*DE13 -> 1662824.9 | DK13: =DF13*($BK$2/10000)^0.72*0.6*((A13+1)/3)^0.6*('CAPEX+OPEX'!$G$116/'CAPEX+OPEX'!$G$114) -> 316809.57 | DL13: =DG13*($BK$2/10000)^0.72*0.6*((A13+1)/3)^0.6*('CAPEX+OPEX'!$G$116/'CAPEX+OPEX'!$G$114) -> 814766.29 | DM13: =DH13*($BK$2/10000)^0.72*0.6*((A13+1)/3)^0.6*('CAPEX+OPEX'!$G$116/'CAPEX+OPEX'!$G$114) -> 157167.42 | DN13: =DI13*($BK$2/10000)^0.72*0.6*((A13+1)/3)^0.6*('CAPEX+OPEX'!$G$116/'CAPEX+OPEX'!$G$114) -> 972891.86 | DO13: =DJ13*($BK$2/10000)^0.72*0.6*((A13+1)/3)^0.6*('CAPEX+OPEX'!$G$116/'CAPEX+OPEX'!$G$114) -> 114865 | DP13: =SUM(DK13:DO13) -> 2376500.1 | DQ13: =DF13*(BM13/10000)^0.72*0.6*((AF13+1)/3)^0.6*('CAPEX+OPEX'!$G$116/'CAPEX+OPEX'!$G$114) -> 334089.07 | DR13: =DG13*(BM13/10000)^0.72*0.6*((AF13+1)/3)^0.6*('CAPEX+OPEX'!$G$116/'CAPEX+OPEX'!$G$114) -> 859205.44 | DS13: =DH13*(BM13/10000)^0.72*0.6*((AF13+1)/3)^0.6*('CAPEX+OPEX'!$G$116/'CAPEX+OPEX'!$G$114) -> 165739.68 | DT13: =DI13*(BM13/10000)^0.72*0.6*((AF13+1)/3)^0.6*('CAPEX+OPEX'!$G$116/'CAPEX+OPEX'!$G$114) -> 1025955.5 | DU13: =DJ13*(BM13/10000)^0.72*0.6*((AF13+1)/3)^0.6*('CAPEX+OPEX'!$G$116/'CAPEX+OPEX'!$G$114) -> 121129.99 | DV13: =SUM(DQ13:DU13) -> 2506119.7 | DW13: =DV13+DP13+SUM(DA13:DD13)*1.15+SUM(CS13:CV13)*1.15+SUM(CA13:CD13)*1.15 -> 4951517.2 | DX13: =DW13/15 -> 330101.15 | DY13: =BO13*'Reagent cost'!$C$35*60*7200 -> 1301471.7 | DZ13: =BP13*'Reagent cost'!$C$34*60*7200 -> 309680.93 | EA13: =BQ13*'Reagent cost'!$C$14*'Reagent cost'!$C$36/1000*60*7200 -> 5133216.1 | EB13: =DA13*0.01 -> 39.6 | EC13: =DC13*0.02 -> 95.688272 | ED13: =0.1*BK13*60*7200*'Reagent cost'!$H$17*'Reagent cost'!$C$17/1000 -> 504921.6 | EE13: =BV13*0.1*'Reagent cost'!$C$16/1000*'Reagent cost'!$H$16*60*7200 -> 1273418.2 | EF13: =BZ13/1000*'Reagent cost'!$H$19*'Reagent cost'!$C$19*60*7200 -> 106994.98 | EG13: =0.33*('Costing 100 Lmin Feed Orig'!BO13*'Reagent cost'!$C$13+'Costing 100 Lmin Feed Orig'!BP13*'Reagent cost'!$C$12+'Costing 100 Lmin Feed Orig'!BQ13*'Reagent cost'!$C$14+'Costing 100 Lmin Feed Orig'!BV13*0.1*'Reagent cost'!$C$16+'Costing 100 Lmin Feed Orig'!BZ13*'Reagent cost'!$C$19)/1000*60*7200 -> 218909.02 | EH13: =CG13*'Reagent cost'!$C$35*60*7200 -> 1880495.9 | EI13: =CH13*'Reagent cost'!$C$34*60*7200 -> 447457.84 | EJ13: =CI13*'Reagent cost'!$C$14*'Reagent cost'!$C$36/1000*60*7200 -> 7416981.7 | EK13: =DB13*0.01 -> 39.6 | EL13: =DD13*0.02 -> 610.87664 | EM13: =0.1*BM13*60*7200*'Reagent cost'!$H$17*'Reagent cost'!$C$17/1000 -> 466952.68 | EN13: =CN13*0.1*'Reagent cost'!$C$16/1000*'Reagent cost'!$H$16*60*7200 -> 1839961.4 | EO13: =CR13/1000*'Reagent cost'!$H$19*'Reagent cost'!$C$19*60*7200 -> 154597.01 | EP13: =0.33*(CG13*'Reagent cost'!$C$13+CH13*'Reagent cost'!$C$12+CI13*'Reagent cost'!$C$14+CN13*0.1*'Reagent cost'!$C$16+CR13*'Reagent cost'!$C$19)/1000*60*7200 -> 316301.55 | EQ13: =(SUM(DY13:EF13)+SUM(EH13:EO13))*1.2 -> 25004323 | ER13: =EG13+EP13 -> 535210.58 | ES13: =0.499*((BK13/3.78541*15)^(-0.146))*BK13/3.78541*15*300*(1+(A13-2)/9) -> 30272.304 | ET13: =0.248*((BK13/3.78541*15)^(-0.144))*BK13/3.78541*15*300*(1+(A13-2)/3) -> 20763.049 | EU13: =0.105*((BK13/3.78541*15)^(-0.144))*BK13/3.78541*15*300*(1+(A13-2)/3) -> 8790.8072 | EV13: =0.058*((BK13/3.78541*15)^(-0.151))*BK13/3.78541*15*300*(1+(A13-2)/3) -> 4656.7358 | EW13: =0.056*((BK13/3.78541*15)^(-0.144))*BK13/3.78541*15*300*(1+(A13-2)/3) -> 4688.4305 | EX13: =SUM(ES13:EW13) -> 69171.327 | EY13: =0.499*((BM13/3.78541*15)^(-0.146))*BM13/3.78541*15*300*(1+(AF13-2)/9) -> 30891.558 | EZ13: =0.248*((BM13/3.78541*15)^(-0.144))*BM13/3.78541*15*300*(1+(AF13-2)/3) -> 23302.915 | FA13: =0.105*((BM13/3.78541*15)^(-0.144))*BM13/3.78541*15*300*(1+(AF13-2)/3) -> 9866.1537 | FB13: =0.058*((BM13/3.78541*15)^(-0.151))*BM13/3.78541*15*300*(1+(AF13-2)/3) -> 5229.2377 | FC13: =0.056*((BM13/3.78541*15)^(-0.144))*BM13/3.78541*15*300*(1+(AF13-2)/3) -> 5261.9487 | FD13: =SUM(EY13:FC13) -> 74551.813 | FE13: =EQ13+ER13+EX13+FD13 -> 25683257 | FF13: =FE13+DX13 -> 26013358 | FG13: =BM13*AM13*195.08/1000*'PGM market prices'!$C$2*60*7200 -> 4.2285728e+08 | FH13: =BN13*AQ13*BA13*106.42/1000*'PGM market prices'!$C$3*60*7200 -> 2.2297926e+08 | FI13: =BK13*J13*102.91/1000*'PGM market prices'!$C$4*60*7200 -> 2.4377655e+08 | FJ13: =SUM(FG13:FI13) -> 8.8961309e+08 | FK13: =(1-0.26)*(FJ13-FF13) -> 6.390638e+08 | FL13: =FF13/(BK13*60*7200) -> 0.60216106 | FM13: =FF13/7200/60/(BM13*AM13*195.08/1000) -> 2075.0239 | FN13: =FF13/7200/60/(BN13*BA13*AQ13*106.42/1000) -> 3841.6644 | FO13: =FF13/(J13*BK13*102.91/1000*60*7200) -> 17601.376
... A101: 12 | B101: 0.0015414359 | C101: 0.0015414359 | D101: 0.0003425413 | E101: 0 | F101: 0 | G101: 0 | H101: 1.7771599e-05 | I101: 6.3113732e-11 | J101: 0.00033766156 | K101: 0.13911792 | L101: 0.14074054 | M101: 0.00044554366 | N101: -4.7646349e-15 | O101: -1.130029e-11 | P101: -4.6756219e-19 | Q101: 0.10952322 | R101: 98.575431 | S101: 500 | T101: 95 | U101: 1 | V101: 0.1 | W101: 91.304837 | X101: ddFc | Y101: 1 | Z101: 0.28318429 | AA101: 0.56945643 | AB101: 0.0037698629 | AC101: 1822.2108 | AD101: 2662.6059 | AE101: 2401.5031 | AF101: 13 | AG101: 0.0016497576 | AH101: 0.0016689998 | AI101: 5.2835684e-06 | AJ101: 0 | AK101: 0 | AL101: 0 | AM101: 0.001612811 | AN101: 7.9635968e-05 | AO101: 5.2488219e-06 | AP101: 0.0017332447 | AQ101: 0.07456056 | AR101: 1.6300356e-06 | AS101: -7.4538899e-20 | AT101: -1.3444107e-17 | AU101: 3.4410713e-22 | AV101: 0.19687171 | AW101: 99.342366 | AX101: 500 | AY101: 95 | AZ101: 0.92356858 | BA101: 0.1 | BB101: 46.912203 | BC101: coeFc | BD101: 1 | BE101: 0.018775015 | BF101: 0.10492961 | BG101: 0.001814625 | BH101: 285.19514 | BI101: 2169.8945 | BJ101: 866.49409 | BK101: =U101*100 -> 100 | BL101: =Q101*100 -> 10.952322 | BM101: =AZ101*100 -> 92.356858 | BN101: =AV101*100 -> 19.687171 | BO101: =0.6*1.2*BL101/2 -> 3.942836 | BP101: =0.04*1.2*BL101/2 -> 0.26285574 | BQ101: =0.2*1.2*BL101/2 -> 1.3142787 | BR101: =0.1*1.2*BL101/2 -> 0.65713934 | BS101: =V101*BL101 -> 1.0952322 | BT101: =0.6*BL101*1 -> 6.5713934 | BU101: =1.6*BL101*1 -> 17.523716 | BV101: =1*V101*BL101/0.2 -> 5.4761612 | BW101: =BM101-BV101 -> 86.880697 | BX101: =(SUM(BV101:BW101)+BL101)*1 -> 103.30918 | BY101: =BM101 -> 92.356858 | BZ101: =BL101*0.1*1.4 -> 1.5333251 | CA101: =7963.6*(BT101/1000)^0.6*1.7*('CAPEX+OPEX'!$G$116/'CAPEX+OPEX'!$G$115) -> 783.13279 | CB101: =7963.6*(BU101/1000)^0.6*1.7*('CAPEX+OPEX'!$G$116/'CAPEX+OPEX'!$G$115) -> 1410.6415 | CC101: =7963.6*(BX101/1000)^0.6*1.7*('CAPEX+OPEX'!$G$116/'CAPEX+OPEX'!$G$115) -> 4090.0091 | CD101: =7963.6*(BY101/1000)^0.6*1.7*('CAPEX+OPEX'!$G$116/'CAPEX+OPEX'!$G$115) -> 3824.0399 | CE101: 300 | CF101: 30 | CG101: =0.6*1.2*BN101/2 -> 7.0873817 | CH101: =0.04*1.2*BN101/2 -> 0.47249211 | CI101: =0.2*1.2*BN101/2 -> 2.3624606 | CJ101: =0.1*1.2*BN101/2 -> 1.1812303 | CK101: =0.1*BN101 -> 1.9687171 | CL101: =0.6*BN101*1 -> 11.812303 | CM101: =1.6*BN101*1 -> 31.499474 | CN101: =1*BA101*BN101/0.2 -> 9.8435856 | CO101: 0 | CP101: =(SUM(CN101:CO101)+BN101)*1 -> 29.530757 | CQ101: =CN101 -> 9.8435856 | CR101: =BN101*0.1*1.4 -> 2.756204 | CS101: =7963.6*(CL101/1000)^0.6*1.7*('CAPEX+OPEX'!$G$116/'CAPEX+OPEX'!$G$115) -> 1113.3755 | CT101: =7963.6*(CM101/1000)^0.6*1.7*('CAPEX+OPEX'!$G$116/'CAPEX+OPEX'!$G$115) -> 2005.5011 | CU101: =7963.6*(CP101/1000)^0.6*1.7*('CAPEX+OPEX'!$G$116/'CAPEX+OPEX'!$G$115) -> 1929.3263 | CV101: =7963.6*(CQ101/1000)^0.6*1.7*('CAPEX+OPEX'!$G$116/'CAPEX+OPEX'!$G$115) -> 998.00547 | CW101: 300 | CX101: =0.1*CW101 -> 30 | CY101: =0.1*BK101 -> 10 | CZ101: =0.1*BM101 -> 9.2356858 | DA101: =CE101*1.32*10 -> 3960 | DB101: =CW101*1.32*10 -> 3960 | DC101: =CF101*'Reagent cost'!$C$18/1000*'Reagent cost'!$H$18 -> 4784.4136 | DD101: =CX101*'Ligand cost'!$B$56*'Ligand cost'!$J$56 -> 30543.832 | DE101: =10000*1/3.78541*15 -> 39625.827 | DF101: =2510*(DE101^0.571)+89*DE101 -> 4586243.4 | DG101: =4810*(DE101^0.6)+228*DE101 -> 11794835 | DH101: =1030*(DE101^0.59)+44*DE101 -> 2275209.2 | DI101: =5640*(DE101^0.602)+272*DE101 -> 14083914 | DJ101: =688*(DE101^0.6)+32*DE101 -> 1662824.9 | DK101: =DF101*($BK$2/10000)^0.72*0.6*((A101+1)/3)^0.6*('CAPEX+OPEX'!$G$116/'CAPEX+OPEX'!$G$114) -> 562059.52 | DL101: =DG101*($BK$2/10000)^0.72*0.6*((A101+1)/3)^0.6*('CAPEX+OPEX'!$G$116/'CAPEX+OPEX'!$G$114) -> 1445496.6 | DM101: =DH101*($BK$2/10000)^0.72*0.6*((A101+1)/3)^0.6*('CAPEX+OPEX'!$G$116/'CAPEX+OPEX'!$G$114) -> 278834.52 | DN101: =DI101*($BK$2/10000)^0.72*0.6*((A101+1)/3)^0.6*('CAPEX+OPEX'!$G$116/'CAPEX+OPEX'!$G$114) -> 1726031 | DO101: =DJ101*($BK$2/10000)^0.72*0.6*((A101+1)/3)^0.6*('CAPEX+OPEX'!$G$116/'CAPEX+OPEX'!$G$114) -> 203784.77 | DP101: =SUM(DK101:DO101) -> 4216206.3 | DQ101: =DF101*(BM101/10000)^0.72*0.6*((AF101+1)/3)^0.6*('CAPEX+OPEX'!$G$116/'CAPEX+OPEX'!$G$114) -> 554920.67 | DR101: =DG101*(BM101/10000)^0.72*0.6*((AF101+1)/3)^0.6*('CAPEX+OPEX'!$G$116/'CAPEX+OPEX'!$G$114) -> 1427137 | DS101: =DH101*(BM101/10000)^0.72*0.6*((AF101+1)/3)^0.6*('CAPEX+OPEX'!$G$116/'CAPEX+OPEX'!$G$114) -> 275292.98 | DT101: =DI101*(BM101/10000)^0.72*0.6*((AF101+1)/3)^0.6*('CAPEX+OPEX'!$G$116/'CAPEX+OPEX'!$G$114) -> 1704108.2 | DU101: =DJ101*(BM101/10000)^0.72*0.6*((AF101+1)/3)^0.6*('CAPEX+OPEX'!$G$116/'CAPEX+OPEX'!$G$114) -> 201196.45 | DV101: =SUM(DQ101:DU101) -> 4162655.3 | DW101: =DV101+DP101+SUM(DA101:DD101)*1.15+SUM(CS101:CV101)*1.15+SUM(CA101:CD101)*1.15 -> 8447174.2 | DX101: =DW101/15 -> 563144.95 | DY101: =BO101*'Reagent cost'!$C$35*60*7200 -> 1021262.3 | DZ101: =BP101*'Reagent cost'!$C$34*60*7200 -> 243006.01 | EA101: =BQ101*'Reagent cost'!$C$14*'Reagent cost'!$C$36/1000*60*7200 -> 4028024.4 | EB101: =DA101*0.01 -> 39.6 | EC101: =DC101*0.02 -> 95.688272 | ED101: =0.1*BK101*60*7200*'Reagent cost'!$H$17*'Reagent cost'!$C$17/1000 -> 504921.6 | EE101: =BV101*0.1*'Reagent cost'!$C$16/1000*'Reagent cost'!$H$16*60*7200 -> 999248.71 | EF101: =BZ101/1000*'Reagent cost'!$H$19*'Reagent cost'!$C$19*60*7200 -> 83958.75 | EG101: =0.33*('Costing 100 Lmin Feed Orig'!BO101*'Reagent cost'!$C$13+'Costing 100 Lmin Feed Orig'!BP101*'Reagent cost'!$C$12+'Costing 100 Lmin Feed Orig'!BQ101*'Reagent cost'!$C$14+'Costing 100 Lmin Feed Orig'!BV101*0.1*'Reagent cost'!$C$16+'Costing 100 Lmin Feed Orig'!BZ101*'Reagent cost'!$C$19)/1000*60*7200 -> 171777.47 | EH101: =CG101*'Reagent cost'!$C$35*60*7200 -> 1835753.6 | EI101: =CH101*'Reagent cost'!$C$34*60*7200 -> 436811.55 | EJ101: =CI101*'Reagent cost'!$C$14*'Reagent cost'!$C$36/1000*60*7200 -> 7240510.7 | EK101: =DB101*0.01 -> 39.6 | EL101: =DD101*0.02 -> 610.87664 | EM101: =0.1*BM101*60*7200*'Reagent cost'!$H$17*'Reagent cost'!$C$17/1000 -> 466329.72 | EN101: =CN101*0.1*'Reagent cost'!$C$16/1000*'Reagent cost'!$H$16*60*7200 -> 1796183.5 | EO101: =CR101/1000*'Reagent cost'!$H$19*'Reagent cost'!$C$19*60*7200 -> 150918.7 | EP101: =0.33*(CG101*'Reagent cost'!$C$13+CH101*'Reagent cost'!$C$12+CI101*'Reagent cost'!$C$14+CN101*0.1*'Reagent cost'!$C$16+CR101*'Reagent cost'!$C$19)/1000*60*7200 -> 308775.84 | EQ101: =(SUM(DY101:EF101)+SUM(EH101:EO101))*1.2 -> 22569258 | ER101: =EG101+EP101 -> 480553.32 | ES101: =0.499*((BK101/3.78541*15)^(-0.146))*BK101/3.78541*15*300*(1+(A101-2)/9) -> 52288.525 | ET101: =0.248*((BK101/3.78541*15)^(-0.144))*BK101/3.78541*15*300*(1+(A101-2)/3) -> 53983.929 | EU101: =0.105*((BK101/3.78541*15)^(-0.144))*BK101/3.78541*15*300*(1+(A101-2)/3) -> 22856.099 | EV101: =0.058*((BK101/3.78541*15)^(-0.151))*BK101/3.78541*15*300*(1+(A101-2)/3) -> 12107.513 | EW101: =0.056*((BK101/3.78541*15)^(-0.144))*BK101/3.78541*15*300*(1+(A101-2)/3) -> 12189.919 | EX101: =SUM(ES101:EW101) -> 153425.98 | EY101: =0.499*((BM101/3.78541*15)^(-0.146))*BM101/3.78541*15*300*(1+(AF101-2)/9) -> 51427.266 | EZ101: =0.248*((BM101/3.78541*15)^(-0.144))*BM101/3.78541*15*300*(1+(AF101-2)/3) -> 54311.37 | FA101: =0.105*((BM101/3.78541*15)^(-0.144))*BM101/3.78541*15*300*(1+(AF101-2)/3) -> 22994.733 | FB101: =0.058*((BM101/3.78541*15)^(-0.151))*BM101/3.78541*15*300*(1+(AF101-2)/3) -> 12187.733 | FC101: =0.056*((BM101/3.78541*15)^(-0.144))*BM101/3.78541*15*300*(1+(AF101-2)/3) -> 12263.858 | FD101: =SUM(EY101:FC101) -> 153184.96 | FE101: =EQ101+ER101+EX101+FD101 -> 23356423 | FF101: =FE101+DX101 -> 23919568 | FG101: =BM101*AM101*195.08/1000*'PGM market prices'!$C$2*60*7200 -> 4.2341829e+08 | FH101: =BN101*AQ101*BA101*106.42/1000*'PGM market prices'!$C$3*60*7200 -> 2.2222195e+08 | FI101: =BK101*J101*102.91/1000*'PGM market prices'!$C$4*60*7200 -> 2.4760823e+08 | FJ101: =SUM(FG101:FI101) -> 8.9324848e+08 | FK101: =(1-0.26)*(FJ101-FF101) -> 6.4330339e+08 | FL101: =FF101/(BK101*60*7200) -> 0.55369369 | FM101: =FF101/7200/60/(BM101*AM101*195.08/1000) -> 1905.4792 | FN101: =FF101/7200/60/(BN101*BA101*AQ101*106.42/1000) -> 3544.4907 | FO101: =FF101/(J101*BK101*102.91/1000*60*7200) -> 15934.204

Sheet TEA Revised Non EYZ
A1: ='Costing 100 Lmin Feed Orig'!A1 -> S1 Stages | B1: ='Costing 100 Lmin Feed Orig'!B1 -> S1 C_Pt_in [M] | C1: ='Costing 100 Lmin Feed Orig'!C1 -> S1 C_Pd_in [M] | D1: ='Costing 100 Lmin Feed Orig'!D1 -> S1 C_Rh_in [M] | E1: ='Costing 100 Lmin Feed Orig'!E1 -> S1 q_Pt_in [mol PGM/mol ligand] | F1: ='Costing 100 Lmin Feed Orig'!F1 -> S1 q_Pd_in [mol PGM/mol ligand] | G1: ='Costing 100 Lmin Feed Orig'!G1 -> S1 q_Rh_in [mol PGM/mol ligand] | H1: ='Costing 100 Lmin Feed Orig'!H1 -> S1 C_Pt_out [M] | ... BN1: ='Costing 100 Lmin Feed Orig'!BN1 -> S2 Q_org Costing [L/min] | BO1: V_ddFc_Recycle [L] | BP1: V_coeFc_Recycle [L] | BQ1: ddFc_Recycle [mol] | BR1: coeFc_Recycle [mol] | BS1: Vol Flow Ox FF 1 [L/min] | BT1: Vol Flow Ox FF 2 [L/min] | BU1: Vol Flow Red FF 1 [L/min] | BV1: Vol Flow Red FF 2 [L/min] | BW1: Vol Flow Red Proc Water 1 [L/min] | BX1: OX1 Size [L] | BY1: RED1 Size [L] | BZ1: OX2 Size [L] | CA1: RED2 Size [L] | CB1: Cost DCM ddFc Recycle | CC1: Cost DCM coeFc Recycle | CD1: Cost ddFc ddFc Recycle | CE1: Cost coeFc coeFc Recycle | CF1: NaCl Flow Leachate Feed [mol/min] | CG1: NaCl Flow Red 1 Feed [mol/min] | CH1: NaCl Flow Red 2 Feed [mol/min] | CI1: OX1 Cost [$] | CJ1: RED1 Cost [$] | CK1: OX2 Cost [$] | CL1: RED2 Cost [$] | CM1: ='Costing 100 Lmin Feed Orig'!DE1 -> 10000 L/min to ST [for costing] | CN1: CAPEX Labor Ref | CO1: CAPEX Equip Ref | CP1: CAPEX Steel Ref | CQ1: CAPEX Const Ref | CR1: CAPEX Tax Ref | CS1: S1 labor | CT1: S1 Equip | CU1: S1 Steel | CV1: S1 Const | CW1: S1 Tax | CX1: CAPEX S1 LLE + EW | CY1: S2 labor | CZ1: S2 Equip | DA1: S2 Steel | DB1: S2 Const | DC1: S2 Tax | DD1: CAPEX S2 LLE + EW | DE1: Total CAPEX [2025 USD] | DF1: Annualized CAPEX assuming 15 year lifetime | DG1: Cost FF Aq OX1 + OX2 [annualized] | DH1: Cost FF Aq RED1 + RED2 [annualized] | DI1: Cost NaCl Leachate | DJ1: Annual Cost DCM Makeup LLE1 + LLE2 | DK1: Annual Cost Ligand Makeup | DL1: OPEX Chemical Purchase With Tariff | DM1: Mass Ions Entering Leachate [kg/min] | DN1: Mass Ions OX FF [kg/min] | DO1: Mass Ions RED FF [kg/min] | DP1: Mass PGM [kg/min] | DQ1: Mass Waste [kg/min] | DR1: Annual Waste Treatment Cost | DS1: EW Voltage [V] | DT1: EW1 Current [A] | DU1: EW2 Current [A] | DV1: Faradaic Efficiency | DW1: opex labor S1 | DX1: opex equip S1 | DY1: opex steel S1 | DZ1: opex lube S1 | EA1: opex sales tax S1 | EB1: OPEX Electricity S1 | EC1: opex labor S2 | ED1: opex equip S2 | EE1: opex steel S2 | EF1: opex lube S2 | EG1: opex sales tax S2 | EH1: opex electricity S2 | EI1: OPEX S1+S2 | EJ1: OPEX | EK1: TAC | EL1: Cost [$/L feed Process] | EM1: Cost [$/kg Pt Recov] | EN1: Cost [$/kg Pd Recov]
A2: ='Costing 100 Lmin Feed Orig'!A2 -> 3 | B2: ='Costing 100 Lmin Feed Orig'!B2 -> 0.0015414359 | C2: ='Costing 100 Lmin Feed Orig'!C2 -> 0.0015414359 | D2: ='Costing 100 Lmin Feed Orig'!D2 -> 0.0003425413 | E2: ='Costing 100 Lmin Feed Orig'!E2 -> 0 | F2: ='Costing 100 Lmin Feed Orig'!F2 -> 0 | G2: ='Costing 100 Lmin Feed Orig'!G2 -> 0 | H2: ='Costing 100 Lmin Feed Orig'!H2 -> 1.6300359e-05 | ... BN2: ='Costing 100 Lmin Feed Orig'!BN2 -> 21.439626 | BO2: =(A2+2)*2*BL2 -> 188.92482 | BP2: =(AF2+2)*2*BN2 -> 257.27551 | BQ2: =BO2*V2 -> 18.892482 | BR2: =BP2*BA2 -> 25.727551 | BS2: =1.2*0.5*BL2*V2/'Oxidant Feed Composition'!$N$22 -> 11.335489 | BT2: =1.2*0.5*BN2*BA2/'Oxidant Feed Composition'!$N$22 -> 12.863775 | BU2: =V2*BL2/0.2 -> 9.4462412 | BV2: =BA2*BN2/0.2 -> 10.719813 | BW2: =BM2-BU2 -> 83.236294 | BX2: =(BS2+BL2)*2 -> 60.455944 | BY2: =(BU2+BW2+BL2)*2 -> 223.15004 | BZ2: =(BT2+BN2)*2 -> 68.606802 | CA2: =(BV2+BN2)*2 -> 64.318877 | CB2: =BO2*'Reagent cost'!$G$11*'Reagent cost'!$H$11 -> 2493.8077 | CC2: =BP2*'Reagent cost'!$G$11*'Reagent cost'!$H$11 -> 3396.0367 | CD2: =BQ2*'Reagent cost'!$C$18/1000*'Reagent cost'!$H$18 -> 3012.9816 | CE2: =BR2*'Ligand cost'!$B$56*'Ligand cost'!$J$56 -> 26193.933 | CF2: =BK2*0.1 -> 10 | CG2: =BU2*0.4 -> 3.7784965 | CH2: =BV2*0.4 -> 4.2879251 | CI2: =7963.6*(BX2/1000)^0.6*1.7*('CAPEX+OPEX'!$G$116/'CAPEX+OPEX'!$G$115) -> 2965.5437 | CJ2: =7963.6*(BY2/1000)^0.6*1.7*('CAPEX+OPEX'!$G$116/'CAPEX+OPEX'!$G$115) -> 6492.3078 | CK2: =7963.6*(BZ2/1000)^0.6*1.7*('CAPEX+OPEX'!$G$116/'CAPEX+OPEX'!$G$115) -> 3199.3462 | CL2: =7963.6*(CA2/1000)^0.6*1.7*('CAPEX+OPEX'!$G$116/'CAPEX+OPEX'!$G$115) -> 3077.8255 | CM2: ='Costing 100 Lmin Feed Orig'!DE2 -> 39625.827 | CN2: ='Costing 100 Lmin Feed Orig'!DF2 -> 4586243.4 | CO2: ='Costing 100 Lmin Feed Orig'!DG2 -> 11794835 | CP2: ='Costing 100 Lmin Feed Orig'!DH2 -> 2275209.2 | CQ2: ='Costing 100 Lmin Feed Orig'!DI2 -> 14083914 | CR2: ='Costing 100 Lmin Feed Orig'!DJ2 -> 1662824.9 | CS2: =CN2*(BK2/10000)^0.72*((A2+1)/3)^0.6*('CAPEX+OPEX'!$G$116/'CAPEX+OPEX'!$G$114) -> 461850.1 | CT2: =CO2*(BK2/10000)^0.72*((A2+1)/3)^0.6*('CAPEX+OPEX'!$G$116/'CAPEX+OPEX'!$G$114) -> 1187779.4 | CU2: =CP2*(BK2/10000)^0.72*((A2+1)/3)^0.6*('CAPEX+OPEX'!$G$116/'CAPEX+OPEX'!$G$114) -> 229121.2 | CV2: =CQ2*(BK2/10000)^0.72*((A2+1)/3)^0.6*('CAPEX+OPEX'!$G$116/'CAPEX+OPEX'!$G$114) -> 1418297.4 | CW2: =CR2*(BK2/10000)^0.72*((A2+1)/3)^0.6*('CAPEX+OPEX'!$G$116/'CAPEX+OPEX'!$G$114) -> 167452.05 | CX2: =SUM(CS2:CW2) -> 3464500.2 | CY2: =CN2*(BM2/10000)^0.72*((AF2+1)/3)^0.6*('CAPEX+OPEX'!$G$116/'CAPEX+OPEX'!$G$114) -> 499902.77 | CZ2: =CO2*(BM2/10000)^0.72*((AF2+1)/3)^0.6*('CAPEX+OPEX'!$G$116/'CAPEX+OPEX'!$G$114) -> 1285642.7 | DA2: =CP2*(BM2/10000)^0.72*((AF2+1)/3)^0.6*('CAPEX+OPEX'!$G$116/'CAPEX+OPEX'!$G$114) -> 247998.91 | DB2: =CQ2*(BM2/10000)^0.72*((AF2+1)/3)^0.6*('CAPEX+OPEX'!$G$116/'CAPEX+OPEX'!$G$114) -> 1535153.5 | DC2: =CR2*(BM2/10000)^0.72*((AF2+1)/3)^0.6*('CAPEX+OPEX'!$G$116/'CAPEX+OPEX'!$G$114) -> 181248.72 | DD2: =SUM(CY2:DC2) -> 3749946.6 | DE2: =CX2+DD2+1.15*(SUM(CI2:CL2)+SUM(CB2:CE2)) -> 7272903.3 | DF2: =DE2/15 -> 484860.22 | DG2: =(BS2+BT2)*'Oxidant Feed Composition'!$N$25*60*7200 -> 19488955 | DH2: =((CG2+CH2)*'Reagent cost'!$C$17/1000*'Reagent cost'!$H$17+(CG2+CH2)*0.5*'Reagent cost'!$C$16/1000*'Reagent cost'!$H$16)*60*7200 -> 7766790.8 | DI2: =CF2*'Reagent cost'!$C$17/1000*'Reagent cost'!$H$17*60*7200 -> 504921.6 | DJ2: =(CB2+CC2)*0.01 -> 58.898444 | DK2: =(CD2+CE2)*0.02 -> 584.13829 | DL2: =SUM(DG2:DK2)*1.2 -> 33313573 | DM2: =BK2*(B2*(409.81+2)/1000+C2*(248.2+2*22.99)/1000+D2*(315.6+3*22.99)/1000+0.1*58.44/1000) -> 0.70639694 | DN2: =(BS2+BT2)/1000*('Oxidant Feed Composition'!$B$11*'Oxidant Feed Composition'!$O$20+'Oxidant Feed Composition'!$D$11*'Oxidant Feed Composition'!$O$21+'Oxidant Feed Composition'!$F$11*'Oxidant Feed Composition'!$O$27-'Oxidant Feed Composition'!$J$15*18.015) -> 2.8261 | DO2: =(BU2+BV2)/1000*(0.2*368.34+0.4*58.44) -> 1.9569945 | DP2: =BK2/1000*(B2*195.08+C2*106.42+D2*102.91) -> 0.049999383 | DQ2: =SUM(DM2:DO2)-DP2 -> 5.4394921 | DR2: =DQ2*60*7200*0.33 -> 775453.99 | DS2: 1.2 | DT2: =BM2/60*(AM2*4+AN2*2+AO2*3)*96485/DV2 -> 1401.3235 | DU2: =BN2*BA2*(AP2*4+AQ2*2+AR2*3)*96485/DV2/60 -> 720.88175 | DV2: 0.7 | DW2: =0.499*((BK2/3.78541*15)^(-0.146))*BK2/3.78541*15*300*(1+(A2-2)/9) -> 27520.276 | DX2: =0.248*((BK2/3.78541*15)^(-0.144))*BK2/3.78541*15*300*(1+(A2-2)/3) -> 16610.44 | DY2: =0.105*((BK2/3.78541*15)^(-0.144))*BK2/3.78541*15*300*(1+(A2-2)/3) -> 7032.6458 | DZ2: =0.058*((BK2/3.78541*15)^(-0.151))*BK2/3.78541*15*300*(1+(A2-2)/3) -> 3725.3887 | EA2: =0.056*((BK2/3.78541*15)^(-0.144))*BK2/3.78541*15*300*(1+(A2-2)/3) -> 3750.7444 | EB2: =DS2*DT2/(3.6*10^6)*3600*7200*0.07 -> 847.52046 | EC2: =0.499*((BM2/3.78541*15)^(-0.146))*BM2/3.78541*15*300*(1+(AF2-2)/9) -> 28370.153 | ED2: =0.248*((BM2/3.78541*15)^(-0.144))*BM2/3.78541*15*300*(1+(AF2-2)/3) -> 19455.453 | EE2: =0.105*((BM2/3.78541*15)^(-0.144))*BM2/3.78541*15*300*(1+(AF2-2)/3) -> 8237.1877 | EF2: =0.058*((BM2/3.78541*15)^(-0.151))*BM2/3.78541*15*300*(1+(AF2-2)/3) -> 4365.7898 | EG2: =0.056*((BM2/3.78541*15)^(-0.144))*BM2/3.78541*15*300*(1+(AF2-2)/3) -> 4393.1668 | EH2: =DS2*DU2/(3.6*10^6)*3600*7200*0.07 -> 435.98928 | EI2: =SUM(DW2:EH2) -> 124744.76 | EJ2: =EI2+DR2+DL2 -> 34213772 | EK2: =EJ2+DF2 -> 34698632 | EL2: =EK2/(BK2*60*7200) -> 0.80320907 | EM2: =EK2/(BM2*(AM2*195.084/1000+AN2*106.42/1000+AO2*102.911/1000)*60*7200) -> 2702.3576 | EN2: =EK2/(BN2*BA2*(AP2*195.084/1000+AQ2*106.42/1000+AR2*102.911/1000)*60*7200) -> 4833.1531
A3: ='Costing 100 Lmin Feed Orig'!A3 -> 3 | B3: ='Costing 100 Lmin Feed Orig'!B3 -> 0.0015414359 | C3: ='Costing 100 Lmin Feed Orig'!C3 -> 0.0015414359 | D3: ='Costing 100 Lmin Feed Orig'!D3 -> 0.0003425413 | E3: ='Costing 100 Lmin Feed Orig'!E3 -> 0 | F3: ='Costing 100 Lmin Feed Orig'!F3 -> 0 | G3: ='Costing 100 Lmin Feed Orig'!G3 -> 0 | H3: ='Costing 100 Lmin Feed Orig'!H3 -> 1.6300359e-05 | ... BN3: ='Costing 100 Lmin Feed Orig'!BN3 -> 20.391868 | BO3: =(A3+2)*2*BL3 -> 188.92482 | BP3: =(AF3+2)*2*BN3 -> 285.48615 | BQ3: =BO3*V3 -> 18.892482 | BR3: =BP3*BA3 -> 28.548615 | BS3: =1.2*0.5*BL3*V3/'Oxidant Feed Composition'!$N$22 -> 11.335489 | BT3: =1.2*0.5*BN3*BA3/'Oxidant Feed Composition'!$N$22 -> 12.235121 | BU3: =V3*BL3/0.2 -> 9.4462412 | BV3: =BA3*BN3/0.2 -> 10.195934 | BW3: =BM3-BU3 -> 83.236294 | BX3: =(BS3+BL3)*2 -> 60.455944 | BY3: =(BU3+BW3+BL3)*2 -> 223.15004 | BZ3: =(BT3+BN3)*2 -> 65.253978 | CA3: =(BV3+BN3)*2 -> 61.175604 | CB3: =BO3*'Reagent cost'!$G$11*'Reagent cost'!$H$11 -> 2493.8077 | CC3: =BP3*'Reagent cost'!$G$11*'Reagent cost'!$H$11 -> 3768.4172 | CD3: =BQ3*'Reagent cost'!$C$18/1000*'Reagent cost'!$H$18 -> 3012.9816 | CE3: =BR3*'Ligand cost'!$B$56*'Ligand cost'!$J$56 -> 29066.137 | CF3: =BK3*0.1 -> 10 | CG3: =BU3*0.4 -> 3.7784965 | CH3: =BV3*0.4 -> 4.0783736 | CI3: =7963.6*(BX3/1000)^0.6*1.7*('CAPEX+OPEX'!$G$116/'CAPEX+OPEX'!$G$115) -> 2965.5437 | CJ3: =7963.6*(BY3/1000)^0.6*1.7*('CAPEX+OPEX'!$G$116/'CAPEX+OPEX'!$G$115) -> 6492.3078 | CK3: =7963.6*(BZ3/1000)^0.6*1.7*('CAPEX+OPEX'!$G$116/'CAPEX+OPEX'!$G$115) -> 3104.5962 | CL3: =7963.6*(CA3/1000)^0.6*1.7*('CAPEX+OPEX'!$G$116/'CAPEX+OPEX'!$G$115) -> 2986.6745 | CM3: ='Costing 100 Lmin Feed Orig'!DE3 -> 39625.827 | CN3: ='Costing 100 Lmin Feed Orig'!DF3 -> 4586243.4 | CO3: ='Costing 100 Lmin Feed Orig'!DG3 -> 11794835 | CP3: ='Costing 100 Lmin Feed Orig'!DH3 -> 2275209.2 | CQ3: ='Costing 100 Lmin Feed Orig'!DI3 -> 14083914 | CR3: ='Costing 100 Lmin Feed Orig'!DJ3 -> 1662824.9 | CS3: =CN3*(BK3/10000)^0.72*((A3+1)/3)^0.6*('CAPEX+OPEX'!$G$116/'CAPEX+OPEX'!$G$114) -> 461850.1 | CT3: =CO3*(BK3/10000)^0.72*((A3+1)/3)^0.6*('CAPEX+OPEX'!$G$116/'CAPEX+OPEX'!$G$114) -> 1187779.4 | CU3: =CP3*(BK3/10000)^0.72*((A3+1)/3)^0.6*('CAPEX+OPEX'!$G$116/'CAPEX+OPEX'!$G$114) -> 229121.2 | CV3: =CQ3*(BK3/10000)^0.72*((A3+1)/3)^0.6*('CAPEX+OPEX'!$G$116/'CAPEX+OPEX'!$G$114) -> 1418297.4 | CW3: =CR3*(BK3/10000)^0.72*((A3+1)/3)^0.6*('CAPEX+OPEX'!$G$116/'CAPEX+OPEX'!$G$114) -> 167452.05 | CX3: =SUM(CS3:CW3) -> 3464500.2 | CY3: =CN3*(BM3/10000)^0.72*((AF3+1)/3)^0.6*('CAPEX+OPEX'!$G$116/'CAPEX+OPEX'!$G$114) -> 557691.84 | CZ3: =CO3*(BM3/10000)^0.72*((AF3+1)/3)^0.6*('CAPEX+OPEX'!$G$116/'CAPEX+OPEX'!$G$114) -> 1434263.8 | DA3: =CP3*(BM3/10000)^0.72*((AF3+1)/3)^0.6*('CAPEX+OPEX'!$G$116/'CAPEX+OPEX'!$G$114) -> 276667.73 | DB3: =CQ3*(BM3/10000)^0.72*((AF3+1)/3)^0.6*('CAPEX+OPEX'!$G$116/'CAPEX+OPEX'!$G$114) -> 1712618.2 | DC3: =CR3*(BM3/10000)^0.72*((AF3+1)/3)^0.6*('CAPEX+OPEX'!$G$116/'CAPEX+OPEX'!$G$114) -> 202201.19 | DD3: =SUM(CY3:DC3) -> 4183442.8 | DE3: =CX3+DD3+1.15*(SUM(CI3:CL3)+SUM(CB3:CE3)) -> 7709917 | DF3: =DE3/15 -> 513994.47 | DG3: =(BS3+BT3)*'Oxidant Feed Composition'!$N$25*60*7200 -> 18982666 | DH3: =((CG3+CH3)*'Reagent cost'!$C$17/1000*'Reagent cost'!$H$17+(CG3+CH3)*0.5*'Reagent cost'!$C$16/1000*'Reagent cost'!$H$16)*60*7200 -> 7565023.2 | DI3: =CF3*'Reagent cost'!$C$17/1000*'Reagent cost'!$H$17*60*7200 -> 504921.6 | DJ3: =(CB3+CC3)*0.01 -> 62.622249 | DK3: =(CD3+CE3)*0.02 -> 641.58237 | DL3: =SUM(DG3:DK3)*1.2 -> 32463978 | DM3: =BK3*(B3*(409.81+2)/1000+C3*(248.2+2*22.99)/1000+D3*(315.6+3*22.99)/1000+0.1*58.44/1000) -> 0.70639694 | DN3: =(BS3+BT3)/1000*('Oxidant Feed Composition'!$B$11*'Oxidant Feed Composition'!$O$20+'Oxidant Feed Composition'!$D$11*'Oxidant Feed Composition'!$O$21+'Oxidant Feed Composition'!$F$11*'Oxidant Feed Composition'!$O$27-'Oxidant Feed Composition'!$J$15*18.015) -> 2.7526829 | DO3: =(BU3+BV3)/1000*(0.2*368.34+0.4*58.44) -> 1.9061552 | DP3: =BK3/1000*(B3*195.08+C3*106.42+D3*102.91) -> 0.049999383 | DQ3: =SUM(DM3:DO3)-DP3 -> 5.3152357 | DR3: =DQ3*60*7200*0.33 -> 757740 | DS3: 1.2 | DT3: =BM3/60*(AM3*4+AN3*2+AO3*3)*96485/DV3 -> 1407.4026 | DU3: =BN3*BA3*(AP3*4+AQ3*2+AR3*3)*96485/DV3/60 -> 714.80262 | DV3: 0.7 | DW3: =0.499*((BK3/3.78541*15)^(-0.146))*BK3/3.78541*15*300*(1+(A3-2)/9) -> 27520.276 | DX3: =0.248*((BK3/3.78541*15)^(-0.144))*BK3/3.78541*15*300*(1+(A3-2)/3) -> 16610.44 | DY3: =0.105*((BK3/3.78541*15)^(-0.144))*BK3/3.78541*15*300*(1+(A3-2)/3) -> 7032.6458 | DZ3: =0.058*((BK3/3.78541*15)^(-0.151))*BK3/3.78541*15*300*(1+(A3-2)/3) -> 3725.3887 | EA3: =0.056*((BK3/3.78541*15)^(-0.144))*BK3/3.78541*15*300*(1+(A3-2)/3) -> 3750.7444 | EB3: =DS3*DT3/(3.6*10^6)*3600*7200*0.07 -> 851.19711 | EC3: =0.499*((BM3/3.78541*15)^(-0.146))*BM3/3.78541*15*300*(1+(AF3-2)/9) -> 30949.258 | ED3: =0.248*((BM3/3.78541*15)^(-0.144))*BM3/3.78541*15*300*(1+(AF3-2)/3) -> 23346.544 | EE3: =0.105*((BM3/3.78541*15)^(-0.144))*BM3/3.78541*15*300*(1+(AF3-2)/3) -> 9884.6253 | EF3: =0.058*((BM3/3.78541*15)^(-0.151))*BM3/3.78541*15*300*(1+(AF3-2)/3) -> 5238.9478 | EG3: =0.056*((BM3/3.78541*15)^(-0.144))*BM3/3.78541*15*300*(1+(AF3-2)/3) -> 5271.8002 | EH3: =DS3*DU3/(3.6*10^6)*3600*7200*0.07 -> 432.31262 | EI3: =SUM(DW3:EH3) -> 134614.18 | EJ3: =EI3+DR3+DL3 -> 33356333 | EK3: =EJ3+DF3 -> 33870327 | EL3: =EK3/(BK3*60*7200) -> 0.78403535 | EM3: =EK3/(BM3*(AM3*195.084/1000+AN3*106.42/1000+AO3*102.911/1000)*60*7200) -> 2626.4278 | EN3: =EK3/(BN3*BA3*(AP3*195.084/1000+AQ3*106.42/1000+AR3*102.911/1000)*60*7200) -> 4754.757
A4: ='Costing 100 Lmin Feed Orig'!A4 -> 3 | B4: ='Costing 100 Lmin Feed Orig'!B4 -> 0.0015414359 | C4: ='Costing 100 Lmin Feed Orig'!C4 -> 0.0015414359 | D4: ='Costing 100 Lmin Feed Orig'!D4 -> 0.0003425413 | E4: ='Costing 100 Lmin Feed Orig'!E4 -> 0 | F4: ='Costing 100 Lmin Feed Orig'!F4 -> 0 | G4: ='Costing 100 Lmin Feed Orig'!G4 -> 0 | H4: ='Costing 100 Lmin Feed Orig'!H4 -> 1.6300359e-05 | ... BN4: ='Costing 100 Lmin Feed Orig'!BN4 -> 20.066267 | BO4: =(A4+2)*2*BL4 -> 188.92482 | BP4: =(AF4+2)*2*BN4 -> 321.06027 | BQ4: =BO4*V4 -> 18.892482 | BR4: =BP4*BA4 -> 32.106027 | BS4: =1.2*0.5*BL4*V4/'Oxidant Feed Composition'!$N$22 -> 11.335489 | BT4: =1.2*0.5*BN4*BA4/'Oxidant Feed Composition'!$N$22 -> 12.03976 | BU4: =V4*BL4/0.2 -> 9.4462412 | BV4: =BA4*BN4/0.2 -> 10.033134 | BW4: =BM4-BU4 -> 83.236294 | BX4: =(BS4+BL4)*2 -> 60.455944 | BY4: =(BU4+BW4+BL4)*2 -> 223.15004 | BZ4: =(BT4+BN4)*2 -> 64.212055 | CA4: =(BV4+BN4)*2 -> 60.198801 | CB4: =BO4*'Reagent cost'!$G$11*'Reagent cost'!$H$11 -> 2493.8077 | CC4: =BP4*'Reagent cost'!$G$11*'Reagent cost'!$H$11 -> 4237.9956 | CD4: =BQ4*'Reagent cost'!$C$18/1000*'Reagent cost'!$H$18 -> 3012.9816 | CE4: =BR4*'Ligand cost'!$B$56*'Ligand cost'!$J$56 -> 32688.037 | CF4: =BK4*0.1 -> 10 | CG4: =BU4*0.4 -> 3.7784965 | CH4: =BV4*0.4 -> 4.0132534 | CI4: =7963.6*(BX4/1000)^0.6*1.7*('CAPEX+OPEX'!$G$116/'CAPEX+OPEX'!$G$115) -> 2965.5437 | CJ4: =7963.6*(BY4/1000)^0.6*1.7*('CAPEX+OPEX'!$G$116/'CAPEX+OPEX'!$G$115) -> 6492.3078 | CK4: =7963.6*(BZ4/1000)^0.6*1.7*('CAPEX+OPEX'!$G$116/'CAPEX+OPEX'!$G$115) -> 3074.7575 | CL4: =7963.6*(CA4/1000)^0.6*1.7*('CAPEX+OPEX'!$G$116/'CAPEX+OPEX'!$G$115) -> 2957.9691 | CM4: ='Costing 100 Lmin Feed Orig'!DE4 -> 39625.827 | CN4: ='Costing 100 Lmin Feed Orig'!DF4 -> 4586243.4 | CO4: ='Costing 100 Lmin Feed Orig'!DG4 -> 11794835 | CP4: ='Costing 100 Lmin Feed Orig'!DH4 -> 2275209.2 | CQ4: ='Costing 100 Lmin Feed Orig'!DI4 -> 14083914 | CR4: ='Costing 100 Lmin Feed Orig'!DJ4 -> 1662824.9 | CS4: =CN4*(BK4/10000)^0.72*((A4+1)/3)^0.6*('CAPEX+OPEX'!$G$116/'CAPEX+OPEX'!$G$114) -> 461850.1 | CT4: =CO4*(BK4/10000)^0.72*((A4+1)/3)^0.6*('CAPEX+OPEX'!$G$116/'CAPEX+OPEX'!$G$114) -> 1187779.4 | CU4: =CP4*(BK4/10000)^0.72*((A4+1)/3)^0.6*('CAPEX+OPEX'!$G$116/'CAPEX+OPEX'!$G$114) -> 229121.2 | CV4: =CQ4*(BK4/10000)^0.72*((A4+1)/3)^0.6*('CAPEX+OPEX'!$G$116/'CAPEX+OPEX'!$G$114) -> 1418297.4 | CW4: =CR4*(BK4/10000)^0.72*((A4+1)/3)^0.6*('CAPEX+OPEX'!$G$116/'CAPEX+OPEX'!$G$114) -> 167452.05 | CX4: =SUM(CS4:CW4) -> 3464500.2 | CY4: =CN4*(BM4/10000)^0.72*((AF4+1)/3)^0.6*('CAPEX+OPEX'!$G$116/'CAPEX+OPEX'!$G$114) -> 611733.64 | CZ4: =CO4*(BM4/10000)^0.72*((AF4+1)/3)^0.6*('CAPEX+OPEX'!$G$116/'CAPEX+OPEX'!$G$114) -> 1573247.7 | DA4: =CP4*(BM4/10000)^0.72*((AF4+1)/3)^0.6*('CAPEX+OPEX'!$G$116/'CAPEX+OPEX'!$G$114) -> 303477.56 | DB4: =CQ4*(BM4/10000)^0.72*((AF4+1)/3)^0.6*('CAPEX+OPEX'!$G$116/'CAPEX+OPEX'!$G$114) -> 1878575.4 | DC4: =CR4*(BM4/10000)^0.72*((AF4+1)/3)^0.6*('CAPEX+OPEX'!$G$116/'CAPEX+OPEX'!$G$114) -> 221795.01 | DD4: =SUM(CY4:DC4) -> 4588829.4 | DE4: =CX4+DD4+1.15*(SUM(CI4:CL4)+SUM(CB4:CE4)) -> 8119941.4 | DF4: =DE4/15 -> 541329.43 | DG4: =(BS4+BT4)*'Oxidant Feed Composition'!$N$25*60*7200 -> 18825332 | DH4: =((CG4+CH4)*'Reagent cost'!$C$17/1000*'Reagent cost'!$H$17+(CG4+CH4)*0.5*'Reagent cost'!$C$16/1000*'Reagent cost'!$H$16)*60*7200 -> 7502321.9 | DI4: =CF4*'Reagent cost'!$C$17/1000*'Reagent cost'!$H$17*60*7200 -> 504921.6 | DJ4: =(CB4+CC4)*0.01 -> 67.318033 | DK4: =(CD4+CE4)*0.02 -> 714.02037 | DL4: =SUM(DG4:DK4)*1.2 -> 32200028 | DM4: =BK4*(B4*(409.81+2)/1000+C4*(248.2+2*22.99)/1000+D4*(315.6+3*22.99)/1000+0.1*58.44/1000) -> 0.70639694 | DN4: =(BS4+BT4)/1000*('Oxidant Feed Composition'!$B$11*'Oxidant Feed Composition'!$O$20+'Oxidant Feed Composition'!$D$11*'Oxidant Feed Composition'!$O$21+'Oxidant Feed Composition'!$F$11*'Oxidant Feed Composition'!$O$27-'Oxidant Feed Composition'!$J$15*18.015) -> 2.7298678 | DO4: =(BU4+BV4)/1000*(0.2*368.34+0.4*58.44) -> 1.8903564 | DP4: =BK4/1000*(B4*195.08+C4*106.42+D4*102.91) -> 0.049999383 | DQ4: =SUM(DM4:DO4)-DP4 -> 5.2766218 | DR4: =DQ4*60*7200*0.33 -> 752235.2 | DS4: 1.2 | DT4: =BM4/60*(AM4*4+AN4*2+AO4*3)*96485/DV4 -> 1409.2918 | DU4: =BN4*BA4*(AP4*4+AQ4*2+AR4*3)*96485/DV4/60 -> 712.91343 | DV4: 0.7 | DW4: =0.499*((BK4/3.78541*15)^(-0.146))*BK4/3.78541*15*300*(1+(A4-2)/9) -> 27520.276 | DX4: =0.248*((BK4/3.78541*15)^(-0.144))*BK4/3.78541*15*300*(1+(A4-2)/3) -> 16610.44 | DY4: =0.105*((BK4/3.78541*15)^(-0.144))*BK4/3.78541*15*300*(1+(A4-2)/3) -> 7032.6458 | DZ4: =0.058*((BK4/3.78541*15)^(-0.151))*BK4/3.78541*15*300*(1+(A4-2)/3) -> 3725.3887 | EA4: =0.056*((BK4/3.78541*15)^(-0.144))*BK4/3.78541*15*300*(1+(A4-2)/3) -> 3750.7444 | EB4: =DS4*DT4/(3.6*10^6)*3600*7200*0.07 -> 852.33969 | EC4: =0.499*((BM4/3.78541*15)^(-0.146))*BM4/3.78541*15*300*(1+(AF4-2)/9) -> 33528.363 | ED4: =0.248*((BM4/3.78541*15)^(-0.144))*BM4/3.78541*15*300*(1+(AF4-2)/3) -> 27237.634 | EE4: =0.105*((BM4/3.78541*15)^(-0.144))*BM4/3.78541*15*300*(1+(AF4-2)/3) -> 11532.063 | EF4: =0.058*((BM4/3.78541*15)^(-0.151))*BM4/3.78541*15*300*(1+(AF4-2)/3) -> 6112.1058 | EG4: =0.056*((BM4/3.78541*15)^(-0.144))*BM4/3.78541*15*300*(1+(AF4-2)/3) -> 6150.4335 | EH4: =DS4*DU4/(3.6*10^6)*3600*7200*0.07 -> 431.17004 | EI4: =SUM(DW4:EH4) -> 144483.6 | EJ4: =EI4+DR4+DL4 -> 33096747 | EK4: =EJ4+DF4 -> 33638077 | EL4: =EK4/(BK4*60*7200) -> 0.77865918 | EM4: =EK4/(BM4*(AM4*195.084/1000+AN4*106.42/1000+AO4*102.911/1000)*60*7200) -> 2604.9134 | EN4: =EK4/(BN4*BA4*(AP4*195.084/1000+AQ4*106.42/1000+AR4*102.911/1000)*60*7200) -> 4733.6837
A5: ='Costing 100 Lmin Feed Orig'!A5 -> 3 | B5: ='Costing 100 Lmin Feed Orig'!B5 -> 0.0015414359 | C5: ='Costing 100 Lmin Feed Orig'!C5 -> 0.0015414359 | D5: ='Costing 100 Lmin Feed Orig'!D5 -> 0.0003425413 | E5: ='Costing 100 Lmin Feed Orig'!E5 -> 0 | F5: ='Costing 100 Lmin Feed Orig'!F5 -> 0 | G5: ='Costing 100 Lmin Feed Orig'!G5 -> 0 | H5: ='Costing 100 Lmin Feed Orig'!H5 -> 1.6300359e-05 | ... BN5: ='Costing 100 Lmin Feed Orig'!BN5 -> 19.968905 | BO5: =(A5+2)*2*BL5 -> 188.92482 | BP5: =(AF5+2)*2*BN5 -> 359.44029 | BQ5: =BO5*V5 -> 18.892482 | BR5: =BP5*BA5 -> 35.944029 | BS5: =1.2*0.5*BL5*V5/'Oxidant Feed Composition'!$N$22 -> 11.335489 | BT5: =1.2*0.5*BN5*BA5/'Oxidant Feed Composition'!$N$22 -> 11.981343 | BU5: =V5*BL5/0.2 -> 9.4462412 | BV5: =BA5*BN5/0.2 -> 9.9844526 | BW5: =BM5-BU5 -> 83.236294 | BX5: =(BS5+BL5)*2 -> 60.455944 | BY5: =(BU5+BW5+BL5)*2 -> 223.15004 | BZ5: =(BT5+BN5)*2 -> 63.900497 | CA5: =(BV5+BN5)*2 -> 59.906716 | CB5: =BO5*'Reagent cost'!$G$11*'Reagent cost'!$H$11 -> 2493.8077 | CC5: =BP5*'Reagent cost'!$G$11*'Reagent cost'!$H$11 -> 4744.6119 | CD5: =BQ5*'Reagent cost'!$C$18/1000*'Reagent cost'!$H$18 -> 3012.9816 | CE5: =BR5*'Ligand cost'!$B$56*'Ligand cost'!$J$56 -> 36595.613 | CF5: =BK5*0.1 -> 10 | CG5: =BU5*0.4 -> 3.7784965 | CH5: =BV5*0.4 -> 3.9937811 | CI5: =7963.6*(BX5/1000)^0.6*1.7*('CAPEX+OPEX'!$G$116/'CAPEX+OPEX'!$G$115) -> 2965.5437 | CJ5: =7963.6*(BY5/1000)^0.6*1.7*('CAPEX+OPEX'!$G$116/'CAPEX+OPEX'!$G$115) -> 6492.3078 | CK5: =7963.6*(BZ5/1000)^0.6*1.7*('CAPEX+OPEX'!$G$116/'CAPEX+OPEX'!$G$115) -> 3065.7975 | CL5: =7963.6*(CA5/1000)^0.6*1.7*('CAPEX+OPEX'!$G$116/'CAPEX+OPEX'!$G$115) -> 2949.3495 | CM5: ='Costing 100 Lmin Feed Orig'!DE5 -> 39625.827 | CN5: ='Costing 100 Lmin Feed Orig'!DF5 -> 4586243.4 | CO5: ='Costing 100 Lmin Feed Orig'!DG5 -> 11794835 | CP5: ='Costing 100 Lmin Feed Orig'!DH5 -> 2275209.2 | CQ5: ='Costing 100 Lmin Feed Orig'!DI5 -> 14083914 | CR5: ='Costing 100 Lmin Feed Orig'!DJ5 -> 1662824.9 | CS5: =CN5*(BK5/10000)^0.72*((A5+1)/3)^0.6*('CAPEX+OPEX'!$G$116/'CAPEX+OPEX'!$G$114) -> 461850.1 | CT5: =CO5*(BK5/10000)^0.72*((A5+1)/3)^0.6*('CAPEX+OPEX'!$G$116/'CAPEX+OPEX'!$G$114) -> 1187779.4 | CU5: =CP5*(BK5/10000)^0.72*((A5+1)/3)^0.6*('CAPEX+OPEX'!$G$116/'CAPEX+OPEX'!$G$114) -> 229121.2 | CV5: =CQ5*(BK5/10000)^0.72*((A5+1)/3)^0.6*('CAPEX+OPEX'!$G$116/'CAPEX+OPEX'!$G$114) -> 1418297.4 | CW5: =CR5*(BK5/10000)^0.72*((A5+1)/3)^0.6*('CAPEX+OPEX'!$G$116/'CAPEX+OPEX'!$G$114) -> 167452.05 | CX5: =SUM(CS5:CW5) -> 3464500.2 | CY5: =CN5*(BM5/10000)^0.72*((AF5+1)/3)^0.6*('CAPEX+OPEX'!$G$116/'CAPEX+OPEX'!$G$114) -> 662761.89 | CZ5: =CO5*(BM5/10000)^0.72*((AF5+1)/3)^0.6*('CAPEX+OPEX'!$G$116/'CAPEX+OPEX'!$G$114) -> 1704481.5 | DA5: =CP5*(BM5/10000)^0.72*((AF5+1)/3)^0.6*('CAPEX+OPEX'!$G$116/'CAPEX+OPEX'!$G$114) -> 328792.39 | DB5: =CQ5*(BM5/10000)^0.72*((AF5+1)/3)^0.6*('CAPEX+OPEX'!$G$116/'CAPEX+OPEX'!$G$114) -> 2035278.3 | DC5: =CR5*(BM5/10000)^0.72*((AF5+1)/3)^0.6*('CAPEX+OPEX'!$G$116/'CAPEX+OPEX'!$G$114) -> 240296.22 | DD5: =SUM(CY5:DC5) -> 4971610.3 | DE5: =CX5+DD5+1.15*(SUM(CI5:CL5)+SUM(CB5:CE5)) -> 8507778.4 | DF5: =DE5/15 -> 567185.23 | DG5: =(BS5+BT5)*'Oxidant Feed Composition'!$N$25*60*7200 -> 18778286 | DH5: =((CG5+CH5)*'Reagent cost'!$C$17/1000*'Reagent cost'!$H$17+(CG5+CH5)*0.5*'Reagent cost'!$C$16/1000*'Reagent cost'!$H$16)*60*7200 -> 7483572.9 | DI5: =CF5*'Reagent cost'!$C$17/1000*'Reagent cost'!$H$17*60*7200 -> 504921.6 | DJ5: =(CB5+CC5)*0.01 -> 72.384196 | DK5: =(CD5+CE5)*0.02 -> 792.1719 | DL5: =SUM(DG5:DK5)*1.2 -> 32121174 | DM5: =BK5*(B5*(409.81+2)/1000+C5*(248.2+2*22.99)/1000+D5*(315.6+3*22.99)/1000+0.1*58.44/1000) -> 0.70639694 | DN5: =(BS5+BT5)/1000*('Oxidant Feed Composition'!$B$11*'Oxidant Feed Composition'!$O$20+'Oxidant Feed Composition'!$D$11*'Oxidant Feed Composition'!$O$21+'Oxidant Feed Composition'!$F$11*'Oxidant Feed Composition'!$O$27-'Oxidant Feed Composition'!$J$15*18.015) -> 2.7230456 | DO5: =(BU5+BV5)/1000*(0.2*368.34+0.4*58.44) -> 1.8856323 | DP5: =BK5/1000*(B5*195.08+C5*106.42+D5*102.91) -> 0.049999383 | DQ5: =SUM(DM5:DO5)-DP5 -> 5.2650754 | DR5: =DQ5*60*7200*0.33 -> 750589.15 | DS5: 1.2 | DT5: =BM5/60*(AM5*4+AN5*2+AO5*3)*96485/DV5 -> 1409.8567 | DU5: =BN5*BA5*(AP5*4+AQ5*2+AR5*3)*96485/DV5/60 -> 712.34852 | DV5: 0.7 | DW5: =0.499*((BK5/3.78541*15)^(-0.146))*BK5/3.78541*15*300*(1+(A5-2)/9) -> 27520.276 | DX5: =0.248*((BK5/3.78541*15)^(-0.144))*BK5/3.78541*15*300*(1+(A5-2)/3) -> 16610.44 | DY5: =0.105*((BK5/3.78541*15)^(-0.144))*BK5/3.78541*15*300*(1+(A5-2)/3) -> 7032.6458 | DZ5: =0.058*((BK5/3.78541*15)^(-0.151))*BK5/3.78541*15*300*(1+(A5-2)/3) -> 3725.3887 | EA5: =0.056*((BK5/3.78541*15)^(-0.144))*BK5/3.78541*15*300*(1+(A5-2)/3) -> 3750.7444 | EB5: =DS5*DT5/(3.6*10^6)*3600*7200*0.07 -> 852.68135 | EC5: =0.499*((BM5/3.78541*15)^(-0.146))*BM5/3.78541*15*300*(1+(AF5-2)/9) -> 36107.468 | ED5: =0.248*((BM5/3.78541*15)^(-0.144))*BM5/3.78541*15*300*(1+(AF5-2)/3) -> 31128.725 | EE5: =0.105*((BM5/3.78541*15)^(-0.144))*BM5/3.78541*15*300*(1+(AF5-2)/3) -> 13179.5 | EF5: =0.058*((BM5/3.78541*15)^(-0.151))*BM5/3.78541*15*300*(1+(AF5-2)/3) -> 6985.2637 | EG5: =0.056*((BM5/3.78541*15)^(-0.144))*BM5/3.78541*15*300*(1+(AF5-2)/3) -> 7029.0669 | EH5: =DS5*DU5/(3.6*10^6)*3600*7200*0.07 -> 430.82839 | EI5: =SUM(DW5:EH5) -> 154353.03 | EJ5: =EI5+DR5+DL5 -> 33026116 | EK5: =EJ5+DF5 -> 33593301 | EL5: =EK5/(BK5*60*7200) -> 0.77762271 | EM5: =EK5/(BM5*(AM5*195.084/1000+AN5*106.42/1000+AO5*102.911/1000)*60*7200) -> 2600.4012 | EN5: =EK5/(BN5*BA5*(AP5*195.084/1000+AQ5*106.42/1000+AR5*102.911/1000)*60*7200) -> 4730.8368
A6: ='Costing 100 Lmin Feed Orig'!A6 -> 3 | B6: ='Costing 100 Lmin Feed Orig'!B6 -> 0.0015414359 | C6: ='Costing 100 Lmin Feed Orig'!C6 -> 0.0015414359 | D6: ='Costing 100 Lmin Feed Orig'!D6 -> 0.0003425413 | E6: ='Costing 100 Lmin Feed Orig'!E6 -> 0 | F6: ='Costing 100 Lmin Feed Orig'!F6 -> 0 | G6: ='Costing 100 Lmin Feed Orig'!G6 -> 0 | H6: ='Costing 100 Lmin Feed Orig'!H6 -> 1.6300359e-05 | ... BN6: ='Costing 100 Lmin Feed Orig'!BN6 -> 19.940532 | BO6: =(A6+2)*2*BL6 -> 188.92482 | BP6: =(AF6+2)*2*BN6 -> 398.81064 | BQ6: =BO6*V6 -> 18.892482 | BR6: =BP6*BA6 -> 39.881064 | BS6: =1.2*0.5*BL6*V6/'Oxidant Feed Composition'!$N$22 -> 11.335489 | BT6: =1.2*0.5*BN6*BA6/'Oxidant Feed Composition'!$N$22 -> 11.964319 | BU6: =V6*BL6/0.2 -> 9.4462412 | BV6: =BA6*BN6/0.2 -> 9.9702659 | BW6: =BM6-BU6 -> 83.236294 | BX6: =(BS6+BL6)*2 -> 60.455944 | BY6: =(BU6+BW6+BL6)*2 -> 223.15004 | BZ6: =(BT6+BN6)*2 -> 63.809702 | CA6: =(BV6+BN6)*2 -> 59.821596 | CB6: =BO6*'Reagent cost'!$G$11*'Reagent cost'!$H$11 -> 2493.8077 | CC6: =BP6*'Reagent cost'!$G$11*'Reagent cost'!$H$11 -> 5264.3004 | CD6: =BQ6*'Reagent cost'!$C$18/1000*'Reagent cost'!$H$18 -> 3012.9816 | CE6: =BR6*'Ligand cost'!$B$56*'Ligand cost'!$J$56 -> 40604.017 | CF6: =BK6*0.1 -> 10 | CG6: =BU6*0.4 -> 3.7784965 | CH6: =BV6*0.4 -> 3.9881064 | CI6: =7963.6*(BX6/1000)^0.6*1.7*('CAPEX+OPEX'!$G$116/'CAPEX+OPEX'!$G$115) -> 2965.5437 | CJ6: =7963.6*(BY6/1000)^0.6*1.7*('CAPEX+OPEX'!$G$116/'CAPEX+OPEX'!$G$115) -> 6492.3078 | CK6: =7963.6*(BZ6/1000)^0.6*1.7*('CAPEX+OPEX'!$G$116/'CAPEX+OPEX'!$G$115) -> 3063.1831 | CL6: =7963.6*(CA6/1000)^0.6*1.7*('CAPEX+OPEX'!$G$116/'CAPEX+OPEX'!$G$115) -> 2946.8344 | CM6: ='Costing 100 Lmin Feed Orig'!DE6 -> 39625.827 | CN6: ='Costing 100 Lmin Feed Orig'!DF6 -> 4586243.4 | CO6: ='Costing 100 Lmin Feed Orig'!DG6 -> 11794835 | CP6: ='Costing 100 Lmin Feed Orig'!DH6 -> 2275209.2 | CQ6: ='Costing 100 Lmin Feed Orig'!DI6 -> 14083914 | CR6: ='Costing 100 Lmin Feed Orig'!DJ6 -> 1662824.9 | CS6: =CN6*(BK6/10000)^0.72*((A6+1)/3)^0.6*('CAPEX+OPEX'!$G$116/'CAPEX+OPEX'!$G$114) -> 461850.1 | CT6: =CO6*(BK6/10000)^0.72*((A6+1)/3)^0.6*('CAPEX+OPEX'!$G$116/'CAPEX+OPEX'!$G$114) -> 1187779.4 | CU6: =CP6*(BK6/10000)^0.72*((A6+1)/3)^0.6*('CAPEX+OPEX'!$G$116/'CAPEX+OPEX'!$G$114) -> 229121.2 | CV6: =CQ6*(BK6/10000)^0.72*((A6+1)/3)^0.6*('CAPEX+OPEX'!$G$116/'CAPEX+OPEX'!$G$114) -> 1418297.4 | CW6: =CR6*(BK6/10000)^0.72*((A6+1)/3)^0.6*('CAPEX+OPEX'!$G$116/'CAPEX+OPEX'!$G$114) -> 167452.05 | CX6: =SUM(CS6:CW6) -> 3464500.2 | CY6: =CN6*(BM6/10000)^0.72*((AF6+1)/3)^0.6*('CAPEX+OPEX'!$G$116/'CAPEX+OPEX'!$G$114) -> 711293.83 | CZ6: =CO6*(BM6/10000)^0.72*((AF6+1)/3)^0.6*('CAPEX+OPEX'!$G$116/'CAPEX+OPEX'!$G$114) -> 1829295.2 | DA6: =CP6*(BM6/10000)^0.72*((AF6+1)/3)^0.6*('CAPEX+OPEX'!$G$116/'CAPEX+OPEX'!$G$114) -> 352868.81 | DB6: =CQ6*(BM6/10000)^0.72*((AF6+1)/3)^0.6*('CAPEX+OPEX'!$G$116/'CAPEX+OPEX'!$G$114) -> 2184315.2 | DC6: =CR6*(BM6/10000)^0.72*((AF6+1)/3)^0.6*('CAPEX+OPEX'!$G$116/'CAPEX+OPEX'!$G$114) -> 257892.35 | DD6: =SUM(CY6:DC6) -> 5335665.4 | DE6: =CX6+DD6+1.15*(SUM(CI6:CL6)+SUM(CB6:CE6)) -> 8877035 | DF6: =DE6/15 -> 591802.33 | DG6: =(BS6+BT6)*'Oxidant Feed Composition'!$N$25*60*7200 -> 18764575 | DH6: =((CG6+CH6)*'Reagent cost'!$C$17/1000*'Reagent cost'!$H$17+(CG6+CH6)*0.5*'Reagent cost'!$C$16/1000*'Reagent cost'!$H$16)*60*7200 -> 7478109 | DI6: =CF6*'Reagent cost'!$C$17/1000*'Reagent cost'!$H$17*60*7200 -> 504921.6 | DJ6: =(CB6+CC6)*0.01 -> 77.581081 | DK6: =(CD6+CE6)*0.02 -> 872.33997 | DL6: =SUM(DG6:DK6)*1.2 -> 32098267 | DM6: =BK6*(B6*(409.81+2)/1000+C6*(248.2+2*22.99)/1000+D6*(315.6+3*22.99)/1000+0.1*58.44/1000) -> 0.70639694 | DN6: =(BS6+BT6)/1000*('Oxidant Feed Composition'!$B$11*'Oxidant Feed Composition'!$O$20+'Oxidant Feed Composition'!$D$11*'Oxidant Feed Composition'!$O$21+'Oxidant Feed Composition'!$F$11*'Oxidant Feed Composition'!$O$27-'Oxidant Feed Composition'!$J$15*18.015) -> 2.7210574 | DO6: =(BU6+BV6)/1000*(0.2*368.34+0.4*58.44) -> 1.8842555 | DP6: =BK6/1000*(B6*195.08+C6*106.42+D6*102.91) -> 0.049999383 | DQ6: =SUM(DM6:DO6)-DP6 -> 5.2617105 | DR6: =DQ6*60*7200*0.33 -> 750109.45 | DS6: 1.2 | DT6: =BM6/60*(AM6*4+AN6*2+AO6*3)*96485/DV6 -> 1410.0214 | DU6: =BN6*BA6*(AP6*4+AQ6*2+AR6*3)*96485/DV6/60 -> 712.1839 | DV6: 0.7 | DW6: =0.499*((BK6/3.78541*15)^(-0.146))*BK6/3.78541*15*300*(1+(A6-2)/9) -> 27520.276 | DX6: =0.248*((BK6/3.78541*15)^(-0.144))*BK6/3.78541*15*300*(1+(A6-2)/3) -> 16610.44 | DY6: =0.105*((BK6/3.78541*15)^(-0.144))*BK6/3.78541*15*300*(1+(A6-2)/3) -> 7032.6458 | DZ6: =0.058*((BK6/3.78541*15)^(-0.151))*BK6/3.78541*15*300*(1+(A6-2)/3) -> 3725.3887 | EA6: =0.056*((BK6/3.78541*15)^(-0.144))*BK6/3.78541*15*300*(1+(A6-2)/3) -> 3750.7444 | EB6: =DS6*DT6/(3.6*10^6)*3600*7200*0.07 -> 852.78092 | EC6: =0.499*((BM6/3.78541*15)^(-0.146))*BM6/3.78541*15*300*(1+(AF6-2)/9) -> 38686.573 | ED6: =0.248*((BM6/3.78541*15)^(-0.144))*BM6/3.78541*15*300*(1+(AF6-2)/3) -> 35019.815 | EE6: =0.105*((BM6/3.78541*15)^(-0.144))*BM6/3.78541*15*300*(1+(AF6-2)/3) -> 14826.938 | EF6: =0.058*((BM6/3.78541*15)^(-0.151))*BM6/3.78541*15*300*(1+(AF6-2)/3) -> 7858.4217 | EG6: =0.056*((BM6/3.78541*15)^(-0.144))*BM6/3.78541*15*300*(1+(AF6-2)/3) -> 7907.7002 | EH6: =DS6*DU6/(3.6*10^6)*3600*7200*0.07 -> 430.72882 | EI6: =SUM(DW6:EH6) -> 164222.45 | EJ6: =EI6+DR6+DL6 -> 33012599 | EK6: =EJ6+DF6 -> 33604401 | EL6: =EK6/(BK6*60*7200) -> 0.77787966 | EM6: =EK6/(BM6*(AM6*195.084/1000+AN6*106.42/1000+AO6*102.911/1000)*60*7200) -> 2600.956 | EN6: =EK6/(BN6*BA6*(AP6*195.084/1000+AQ6*106.42/1000+AR6*102.911/1000)*60*7200) -> 4733.4079
A7: ='Costing 100 Lmin Feed Orig'!A7 -> 3 | B7: ='Costing 100 Lmin Feed Orig'!B7 -> 0.0015414359 | C7: ='Costing 100 Lmin Feed Orig'!C7 -> 0.0015414359 | D7: ='Costing 100 Lmin Feed Orig'!D7 -> 0.0003425413 | E7: ='Costing 100 Lmin Feed Orig'!E7 -> 0 | F7: ='Costing 100 Lmin Feed Orig'!F7 -> 0 | G7: ='Costing 100 Lmin Feed Orig'!G7 -> 0 | H7: ='Costing 100 Lmin Feed Orig'!H7 -> 1.6300359e-05 | ... BN7: ='Costing 100 Lmin Feed Orig'!BN7 -> 19.932361 | BO7: =(A7+2)*2*BL7 -> 188.92482 | BP7: =(AF7+2)*2*BN7 -> 438.51194 | BQ7: =BO7*V7 -> 18.892482 | BR7: =BP7*BA7 -> 43.851194 | BS7: =1.2*0.5*BL7*V7/'Oxidant Feed Composition'!$N$22 -> 11.335489 | BT7: =1.2*0.5*BN7*BA7/'Oxidant Feed Composition'!$N$22 -> 11.959416 | BU7: =V7*BL7/0.2 -> 9.4462412 | BV7: =BA7*BN7/0.2 -> 9.9661804 | BW7: =BM7-BU7 -> 83.236294 | BX7: =(BS7+BL7)*2 -> 60.455944 | BY7: =(BU7+BW7+BL7)*2 -> 223.15004 | BZ7: =(BT7+BN7)*2 -> 63.783555 | CA7: =(BV7+BN7)*2 -> 59.797082 | CB7: =BO7*'Reagent cost'!$G$11*'Reagent cost'!$H$11 -> 2493.8077 | CC7: =BP7*'Reagent cost'!$G$11*'Reagent cost'!$H$11 -> 5788.3576 | CD7: =BQ7*'Reagent cost'!$C$18/1000*'Reagent cost'!$H$18 -> 3012.9816 | CE7: =BR7*'Ligand cost'!$B$56*'Ligand cost'!$J$56 -> 44646.116 | CF7: =BK7*0.1 -> 10 | CG7: =BU7*0.4 -> 3.7784965 | CH7: =BV7*0.4 -> 3.9864722 | CI7: =7963.6*(BX7/1000)^0.6*1.7*('CAPEX+OPEX'!$G$116/'CAPEX+OPEX'!$G$115) -> 2965.5437 | CJ7: =7963.6*(BY7/1000)^0.6*1.7*('CAPEX+OPEX'!$G$116/'CAPEX+OPEX'!$G$115) -> 6492.3078 | CK7: =7963.6*(BZ7/1000)^0.6*1.7*('CAPEX+OPEX'!$G$116/'CAPEX+OPEX'!$G$115) -> 3062.4299 | CL7: =7963.6*(CA7/1000)^0.6*1.7*('CAPEX+OPEX'!$G$116/'CAPEX+OPEX'!$G$115) -> 2946.1098 | CM7: ='Costing 100 Lmin Feed Orig'!DE7 -> 39625.827 | CN7: ='Costing 100 Lmin Feed Orig'!DF7 -> 4586243.4 | CO7: ='Costing 100 Lmin Feed Orig'!DG7 -> 11794835 | CP7: ='Costing 100 Lmin Feed Orig'!DH7 -> 2275209.2 | CQ7: ='Costing 100 Lmin Feed Orig'!DI7 -> 14083914 | CR7: ='Costing 100 Lmin Feed Orig'!DJ7 -> 1662824.9 | CS7: =CN7*(BK7/10000)^0.72*((A7+1)/3)^0.6*('CAPEX+OPEX'!$G$116/'CAPEX+OPEX'!$G$114) -> 461850.1 | CT7: =CO7*(BK7/10000)^0.72*((A7+1)/3)^0.6*('CAPEX+OPEX'!$G$116/'CAPEX+OPEX'!$G$114) -> 1187779.4 | CU7: =CP7*(BK7/10000)^0.72*((A7+1)/3)^0.6*('CAPEX+OPEX'!$G$116/'CAPEX+OPEX'!$G$114) -> 229121.2 | CV7: =CQ7*(BK7/10000)^0.72*((A7+1)/3)^0.6*('CAPEX+OPEX'!$G$116/'CAPEX+OPEX'!$G$114) -> 1418297.4 | CW7: =CR7*(BK7/10000)^0.72*((A7+1)/3)^0.6*('CAPEX+OPEX'!$G$116/'CAPEX+OPEX'!$G$114) -> 167452.05 | CX7: =SUM(CS7:CW7) -> 3464500.2 | CY7: =CN7*(BM7/10000)^0.72*((AF7+1)/3)^0.6*('CAPEX+OPEX'!$G$116/'CAPEX+OPEX'!$G$114) -> 757710.9 | CZ7: =CO7*(BM7/10000)^0.72*((AF7+1)/3)^0.6*('CAPEX+OPEX'!$G$116/'CAPEX+OPEX'!$G$114) -> 1948670 | DA7: =CP7*(BM7/10000)^0.72*((AF7+1)/3)^0.6*('CAPEX+OPEX'!$G$116/'CAPEX+OPEX'!$G$114) -> 375896.05 | DB7: =CQ7*(BM7/10000)^0.72*((AF7+1)/3)^0.6*('CAPEX+OPEX'!$G$116/'CAPEX+OPEX'!$G$114) -> 2326857.6 | DC7: =CR7*(BM7/10000)^0.72*((AF7+1)/3)^0.6*('CAPEX+OPEX'!$G$116/'CAPEX+OPEX'!$G$114) -> 274721.69 | DD7: =SUM(CY7:DC7) -> 5683856.2 | DE7: =CX7+DD7+1.15*(SUM(CI7:CL7)+SUM(CB7:CE7)) -> 9230475.2 | DF7: =DE7/15 -> 615365.01 | DG7: =(BS7+BT7)*'Oxidant Feed Composition'!$N$25*60*7200 -> 18760627 | DH7: =((CG7+CH7)*'Reagent cost'!$C$17/1000*'Reagent cost'!$H$17+(CG7+CH7)*0.5*'Reagent cost'!$C$16/1000*'Reagent cost'!$H$16)*60*7200 -> 7476535.5 | DI7: =CF7*'Reagent cost'!$C$17/1000*'Reagent cost'!$H$17*60*7200 -> 504921.6 | DJ7: =(CB7+CC7)*0.01 -> 82.821653 | DK7: =(CD7+CE7)*0.02 -> 953.18196 | DL7: =SUM(DG7:DK7)*1.2 -> 32091744 | DM7: =BK7*(B7*(409.81+2)/1000+C7*(248.2+2*22.99)/1000+D7*(315.6+3*22.99)/1000+0.1*58.44/1000) -> 0.70639694 | DN7: =(BS7+BT7)/1000*('Oxidant Feed Composition'!$B$11*'Oxidant Feed Composition'!$O$20+'Oxidant Feed Composition'!$D$11*'Oxidant Feed Composition'!$O$21+'Oxidant Feed Composition'!$F$11*'Oxidant Feed Composition'!$O$27-'Oxidant Feed Composition'!$J$15*18.015) -> 2.7204849 | DO7: =(BU7+BV7)/1000*(0.2*368.34+0.4*58.44) -> 1.883859 | DP7: =BK7/1000*(B7*195.08+C7*106.42+D7*102.91) -> 0.049999383 | DQ7: =SUM(DM7:DO7)-DP7 -> 5.2607415 | DR7: =DQ7*60*7200*0.33 -> 749971.3 | DS7: 1.2 | DT7: =BM7/60*(AM7*4+AN7*2+AO7*3)*96485/DV7 -> 1410.0688 | DU7: =BN7*BA7*(AP7*4+AQ7*2+AR7*3)*96485/DV7/60 -> 712.13649 | DV7: 0.7 | DW7: =0.499*((BK7/3.78541*15)^(-0.146))*BK7/3.78541*15*300*(1+(A7-2)/9) -> 27520.276 | DX7: =0.248*((BK7/3.78541*15)^(-0.144))*BK7/3.78541*15*300*(1+(A7-2)/3) -> 16610.44 | DY7: =0.105*((BK7/3.78541*15)^(-0.144))*BK7/3.78541*15*300*(1+(A7-2)/3) -> 7032.6458 | DZ7: =0.058*((BK7/3.78541*15)^(-0.151))*BK7/3.78541*15*300*(1+(A7-2)/3) -> 3725.3887 | EA7: =0.056*((BK7/3.78541*15)^(-0.144))*BK7/3.78541*15*300*(1+(A7-2)/3) -> 3750.7444 | EB7: =DS7*DT7/(3.6*10^6)*3600*7200*0.07 -> 852.80959 | EC7: =0.499*((BM7/3.78541*15)^(-0.146))*BM7/3.78541*15*300*(1+(AF7-2)/9) -> 41265.678 | ED7: =0.248*((BM7/3.78541*15)^(-0.144))*BM7/3.78541*15*300*(1+(AF7-2)/3) -> 38910.906 | EE7: =0.105*((BM7/3.78541*15)^(-0.144))*BM7/3.78541*15*300*(1+(AF7-2)/3) -> 16474.375 | EF7: =0.058*((BM7/3.78541*15)^(-0.151))*BM7/3.78541*15*300*(1+(AF7-2)/3) -> 8731.5797 | EG7: =0.056*((BM7/3.78541*15)^(-0.144))*BM7/3.78541*15*300*(1+(AF7-2)/3) -> 8786.3336 | EH7: =DS7*DU7/(3.6*10^6)*3600*7200*0.07 -> 430.70015 | EI7: =SUM(DW7:EH7) -> 174091.88 | EJ7: =EI7+DR7+DL7 -> 33015807 | EK7: =EJ7+DF7 -> 33631172 | EL7: =EK7/(BK7*60*7200) -> 0.77849936 | EM7: =EK7/(BM7*(AM7*195.084/1000+AN7*106.42/1000+AO7*102.911/1000)*60*7200) -> 2602.9404 | EN7: =EK7/(BN7*BA7*(AP7*195.084/1000+AQ7*106.42/1000+AR7*102.911/1000)*60*7200) -> 4737.4694
A8: ='Costing 100 Lmin Feed Orig'!A8 -> 3 | B8: ='Costing 100 Lmin Feed Orig'!B8 -> 0.0015414359 | C8: ='Costing 100 Lmin Feed Orig'!C8 -> 0.0015414359 | D8: ='Costing 100 Lmin Feed Orig'!D8 -> 0.0003425413 | E8: ='Costing 100 Lmin Feed Orig'!E8 -> 0 | F8: ='Costing 100 Lmin Feed Orig'!F8 -> 0 | G8: ='Costing 100 Lmin Feed Orig'!G8 -> 0 | H8: ='Costing 100 Lmin Feed Orig'!H8 -> 1.6300359e-05 | ... BN8: ='Costing 100 Lmin Feed Orig'!BN8 -> 19.930019 | BO8: =(A8+2)*2*BL8 -> 188.92482 | BP8: =(AF8+2)*2*BN8 -> 478.32045 | BQ8: =BO8*V8 -> 18.892482 | BR8: =BP8*BA8 -> 47.832045 | BS8: =1.2*0.5*BL8*V8/'Oxidant Feed Composition'!$N$22 -> 11.335489 | BT8: =1.2*0.5*BN8*BA8/'Oxidant Feed Composition'!$N$22 -> 11.958011 | BU8: =V8*BL8/0.2 -> 9.4462412 | BV8: =BA8*BN8/0.2 -> 9.9650093 | BW8: =BM8-BU8 -> 83.236294 | BX8: =(BS8+BL8)*2 -> 60.455944 | BY8: =(BU8+BW8+BL8)*2 -> 223.15004 | BZ8: =(BT8+BN8)*2 -> 63.776059 | CA8: =(BV8+BN8)*2 -> 59.790056 | CB8: =BO8*'Reagent cost'!$G$11*'Reagent cost'!$H$11 -> 2493.8077 | CC8: =BP8*'Reagent cost'!$G$11*'Reagent cost'!$H$11 -> 6313.8299 | CD8: =BQ8*'Reagent cost'!$C$18/1000*'Reagent cost'!$H$18 -> 3012.9816 | CE8: =BR8*'Ligand cost'!$B$56*'Ligand cost'!$J$56 -> 48699.131 | CF8: =BK8*0.1 -> 10 | CG8: =BU8*0.4 -> 3.7784965 | CH8: =BV8*0.4 -> 3.9860037 | CI8: =7963.6*(BX8/1000)^0.6*1.7*('CAPEX+OPEX'!$G$116/'CAPEX+OPEX'!$G$115) -> 2965.5437 | CJ8: =7963.6*(BY8/1000)^0.6*1.7*('CAPEX+OPEX'!$G$116/'CAPEX+OPEX'!$G$115) -> 6492.3078 | CK8: =7963.6*(BZ8/1000)^0.6*1.7*('CAPEX+OPEX'!$G$116/'CAPEX+OPEX'!$G$115) -> 3062.214 | CL8: =7963.6*(CA8/1000)^0.6*1.7*('CAPEX+OPEX'!$G$116/'CAPEX+OPEX'!$G$115) -> 2945.9021 | CM8: ='Costing 100 Lmin Feed Orig'!DE8 -> 39625.827 | CN8: ='Costing 100 Lmin Feed Orig'!DF8 -> 4586243.4 | CO8: ='Costing 100 Lmin Feed Orig'!DG8 -> 11794835 | CP8: ='Costing 100 Lmin Feed Orig'!DH8 -> 2275209.2 | CQ8: ='Costing 100 Lmin Feed Orig'!DI8 -> 14083914 | CR8: ='Costing 100 Lmin Feed Orig'!DJ8 -> 1662824.9 | CS8: =CN8*(BK8/10000)^0.72*((A8+1)/3)^0.6*('CAPEX+OPEX'!$G$116/'CAPEX+OPEX'!$G$114) -> 461850.1 | CT8: =CO8*(BK8/10000)^0.72*((A8+1)/3)^0.6*('CAPEX+OPEX'!$G$116/'CAPEX+OPEX'!$G$114) -> 1187779.4 | CU8: =CP8*(BK8/10000)^0.72*((A8+1)/3)^0.6*('CAPEX+OPEX'!$G$116/'CAPEX+OPEX'!$G$114) -> 229121.2 | CV8: =CQ8*(BK8/10000)^0.72*((A8+1)/3)^0.6*('CAPEX+OPEX'!$G$116/'CAPEX+OPEX'!$G$114) -> 1418297.4 | CW8: =CR8*(BK8/10000)^0.72*((A8+1)/3)^0.6*('CAPEX+OPEX'!$G$116/'CAPEX+OPEX'!$G$114) -> 167452.05 | CX8: =SUM(CS8:CW8) -> 3464500.2 | CY8: =CN8*(BM8/10000)^0.72*((AF8+1)/3)^0.6*('CAPEX+OPEX'!$G$116/'CAPEX+OPEX'!$G$114) -> 802304.35 | CZ8: =CO8*(BM8/10000)^0.72*((AF8+1)/3)^0.6*('CAPEX+OPEX'!$G$116/'CAPEX+OPEX'!$G$114) -> 2063354.7 | DA8: =CP8*(BM8/10000)^0.72*((AF8+1)/3)^0.6*('CAPEX+OPEX'!$G$116/'CAPEX+OPEX'!$G$114) -> 398018.61 | DB8: =CQ8*(BM8/10000)^0.72*((AF8+1)/3)^0.6*('CAPEX+OPEX'!$G$116/'CAPEX+OPEX'!$G$114) -> 2463799.8 | DC8: =CR8*(BM8/10000)^0.72*((AF8+1)/3)^0.6*('CAPEX+OPEX'!$G$116/'CAPEX+OPEX'!$G$114) -> 290889.85 | DD8: =SUM(CY8:DC8) -> 6018367.4 | DE8: =CX8+DD8+1.15*(SUM(CI8:CL8)+SUM(CB8:CE8)) -> 9570251.1 | DF8: =DE8/15 -> 638016.74 | DG8: =(BS8+BT8)*'Oxidant Feed Composition'!$N$25*60*7200 -> 18759495 | DH8: =((CG8+CH8)*'Reagent cost'!$C$17/1000*'Reagent cost'!$H$17+(CG8+CH8)*0.5*'Reagent cost'!$C$16/1000*'Reagent cost'!$H$16)*60*7200 -> 7476084.4 | DI8: =CF8*'Reagent cost'!$C$17/1000*'Reagent cost'!$H$17*60*7200 -> 504921.6 | DJ8: =(CB8+CC8)*0.01 -> 88.076376 | DK8: =(CD8+CE8)*0.02 -> 1034.2423 | DL8: =SUM(DG8:DK8)*1.2 -> 32089948 | DM8: =BK8*(B8*(409.81+2)/1000+C8*(248.2+2*22.99)/1000+D8*(315.6+3*22.99)/1000+0.1*58.44/1000) -> 0.70639694 | DN8: =(BS8+BT8)/1000*('Oxidant Feed Composition'!$B$11*'Oxidant Feed Composition'!$O$20+'Oxidant Feed Composition'!$D$11*'Oxidant Feed Composition'!$O$21+'Oxidant Feed Composition'!$F$11*'Oxidant Feed Composition'!$O$27-'Oxidant Feed Composition'!$J$15*18.015) -> 2.7203208 | DO8: =(BU8+BV8)/1000*(0.2*368.34+0.4*58.44) -> 1.8837454 | DP8: =BK8/1000*(B8*195.08+C8*106.42+D8*102.91) -> 0.049999383 | DQ8: =SUM(DM8:DO8)-DP8 -> 5.2604637 | DR8: =DQ8*60*7200*0.33 -> 749931.71 | DS8: 1.2 | DT8: =BM8/60*(AM8*4+AN8*2+AO8*3)*96485/DV8 -> 1410.0824 | DU8: =BN8*BA8*(AP8*4+AQ8*2+AR8*3)*96485/DV8/60 -> 712.1229 | DV8: 0.7 | DW8: =0.499*((BK8/3.78541*15)^(-0.146))*BK8/3.78541*15*300*(1+(A8-2)/9) -> 27520.276 | DX8: =0.248*((BK8/3.78541*15)^(-0.144))*BK8/3.78541*15*300*(1+(A8-2)/3) -> 16610.44 | DY8: =0.105*((BK8/3.78541*15)^(-0.144))*BK8/3.78541*15*300*(1+(A8-2)/3) -> 7032.6458 | DZ8: =0.058*((BK8/3.78541*15)^(-0.151))*BK8/3.78541*15*300*(1+(A8-2)/3) -> 3725.3887 | EA8: =0.056*((BK8/3.78541*15)^(-0.144))*BK8/3.78541*15*300*(1+(A8-2)/3) -> 3750.7444 | EB8: =DS8*DT8/(3.6*10^6)*3600*7200*0.07 -> 852.81781 | EC8: =0.499*((BM8/3.78541*15)^(-0.146))*BM8/3.78541*15*300*(1+(AF8-2)/9) -> 43844.783 | ED8: =0.248*((BM8/3.78541*15)^(-0.144))*BM8/3.78541*15*300*(1+(AF8-2)/3) -> 42801.996 | EE8: =0.105*((BM8/3.78541*15)^(-0.144))*BM8/3.78541*15*300*(1+(AF8-2)/3) -> 18121.813 | EF8: =0.058*((BM8/3.78541*15)^(-0.151))*BM8/3.78541*15*300*(1+(AF8-2)/3) -> 9604.7376 | EG8: =0.056*((BM8/3.78541*15)^(-0.144))*BM8/3.78541*15*300*(1+(AF8-2)/3) -> 9664.9669 | EH8: =DS8*DU8/(3.6*10^6)*3600*7200*0.07 -> 430.69193 | EI8: =SUM(DW8:EH8) -> 183961.3 | EJ8: =EI8+DR8+DL8 -> 33023841 | EK8: =EJ8+DF8 -> 33661858 | EL8: =EK8/(BK8*60*7200) -> 0.77920968 | EM8: =EK8/(BM8*(AM8*195.084/1000+AN8*106.42/1000+AO8*102.911/1000)*60*7200) -> 2605.2902 | EN8: =EK8/(BN8*BA8*(AP8*195.084/1000+AQ8*106.42/1000+AR8*102.911/1000)*60*7200) -> 4741.8753
A9: ='Costing 100 Lmin Feed Orig'!A9 -> 3 | B9: ='Costing 100 Lmin Feed Orig'!B9 -> 0.0015414359 | C9: ='Costing 100 Lmin Feed Orig'!C9 -> 0.0015414359 | D9: ='Costing 100 Lmin Feed Orig'!D9 -> 0.0003425413 | E9: ='Costing 100 Lmin Feed Orig'!E9 -> 0 | F9: ='Costing 100 Lmin Feed Orig'!F9 -> 0 | G9: ='Costing 100 Lmin Feed Orig'!G9 -> 0 | H9: ='Costing 100 Lmin Feed Orig'!H9 -> 1.6300359e-05 | ... BN9: ='Costing 100 Lmin Feed Orig'!BN9 -> 19.929348 | BO9: =(A9+2)*2*BL9 -> 188.92482 | BP9: =(AF9+2)*2*BN9 -> 518.16306 | BQ9: =BO9*V9 -> 18.892482 | BR9: =BP9*BA9 -> 51.816306 | BS9: =1.2*0.5*BL9*V9/'Oxidant Feed Composition'!$N$22 -> 11.335489 | BT9: =1.2*0.5*BN9*BA9/'Oxidant Feed Composition'!$N$22 -> 11.957609 | BU9: =V9*BL9/0.2 -> 9.4462412 | BV9: =BA9*BN9/0.2 -> 9.9646742 | BW9: =BM9-BU9 -> 83.236294 | BX9: =(BS9+BL9)*2 -> 60.455944 | BY9: =(BU9+BW9+BL9)*2 -> 223.15004 | BZ9: =(BT9+BN9)*2 -> 63.773915 | CA9: =(BV9+BN9)*2 -> 59.788045 | CB9: =BO9*'Reagent cost'!$G$11*'Reagent cost'!$H$11 -> 2493.8077 | CC9: =BP9*'Reagent cost'!$G$11*'Reagent cost'!$H$11 -> 6839.7523 | CD9: =BQ9*'Reagent cost'!$C$18/1000*'Reagent cost'!$H$18 -> 3012.9816 | CE9: =BR9*'Ligand cost'!$B$56*'Ligand cost'!$J$56 -> 52755.618 | CF9: =BK9*0.1 -> 10 | CG9: =BU9*0.4 -> 3.7784965 | CH9: =BV9*0.4 -> 3.9858697 | CI9: =7963.6*(BX9/1000)^0.6*1.7*('CAPEX+OPEX'!$G$116/'CAPEX+OPEX'!$G$115) -> 2965.5437 | CJ9: =7963.6*(BY9/1000)^0.6*1.7*('CAPEX+OPEX'!$G$116/'CAPEX+OPEX'!$G$115) -> 6492.3078 | CK9: =7963.6*(BZ9/1000)^0.6*1.7*('CAPEX+OPEX'!$G$116/'CAPEX+OPEX'!$G$115) -> 3062.1522 | CL9: =7963.6*(CA9/1000)^0.6*1.7*('CAPEX+OPEX'!$G$116/'CAPEX+OPEX'!$G$115) -> 2945.8426 | CM9: ='Costing 100 Lmin Feed Orig'!DE9 -> 39625.827 | CN9: ='Costing 100 Lmin Feed Orig'!DF9 -> 4586243.4 | CO9: ='Costing 100 Lmin Feed Orig'!DG9 -> 11794835 | CP9: ='Costing 100 Lmin Feed Orig'!DH9 -> 2275209.2 | CQ9: ='Costing 100 Lmin Feed Orig'!DI9 -> 14083914 | CR9: ='Costing 100 Lmin Feed Orig'!DJ9 -> 1662824.9 | CS9: =CN9*(BK9/10000)^0.72*((A9+1)/3)^0.6*('CAPEX+OPEX'!$G$116/'CAPEX+OPEX'!$G$114) -> 461850.1 | CT9: =CO9*(BK9/10000)^0.72*((A9+1)/3)^0.6*('CAPEX+OPEX'!$G$116/'CAPEX+OPEX'!$G$114) -> 1187779.4 | CU9: =CP9*(BK9/10000)^0.72*((A9+1)/3)^0.6*('CAPEX+OPEX'!$G$116/'CAPEX+OPEX'!$G$114) -> 229121.2 | CV9: =CQ9*(BK9/10000)^0.72*((A9+1)/3)^0.6*('CAPEX+OPEX'!$G$116/'CAPEX+OPEX'!$G$114) -> 1418297.4 | CW9: =CR9*(BK9/10000)^0.72*((A9+1)/3)^0.6*('CAPEX+OPEX'!$G$116/'CAPEX+OPEX'!$G$114) -> 167452.05 | CX9: =SUM(CS9:CW9) -> 3464500.2 | CY9: =CN9*(BM9/10000)^0.72*((AF9+1)/3)^0.6*('CAPEX+OPEX'!$G$116/'CAPEX+OPEX'!$G$114) -> 845302.76 | CZ9: =CO9*(BM9/10000)^0.72*((AF9+1)/3)^0.6*('CAPEX+OPEX'!$G$116/'CAPEX+OPEX'!$G$114) -> 2173937.4 | DA9: =CP9*(BM9/10000)^0.72*((AF9+1)/3)^0.6*('CAPEX+OPEX'!$G$116/'CAPEX+OPEX'!$G$114) -> 419349.87 | DB9: =CQ9*(BM9/10000)^0.72*((AF9+1)/3)^0.6*('CAPEX+OPEX'!$G$116/'CAPEX+OPEX'!$G$114) -> 2595843.8 | DC9: =CR9*(BM9/10000)^0.72*((AF9+1)/3)^0.6*('CAPEX+OPEX'!$G$116/'CAPEX+OPEX'!$G$114) -> 306479.69 | DD9: =SUM(CY9:DC9) -> 6340913.5 | DE9: =CX9+DD9+1.15*(SUM(CI9:CL9)+SUM(CB9:CE9)) -> 9898066.9 | DF9: =DE9/15 -> 659871.13 | DG9: =(BS9+BT9)*'Oxidant Feed Composition'!$N$25*60*7200 -> 18759171 | DH9: =((CG9+CH9)*'Reagent cost'!$C$17/1000*'Reagent cost'!$H$17+(CG9+CH9)*0.5*'Reagent cost'!$C$16/1000*'Reagent cost'!$H$16)*60*7200 -> 7475955.3 | DI9: =CF9*'Reagent cost'!$C$17/1000*'Reagent cost'!$H$17*60*7200 -> 504921.6 | DJ9: =(CB9+CC9)*0.01 -> 93.3356 | DK9: =(CD9+CE9)*0.02 -> 1115.372 | DL9: =SUM(DG9:DK9)*1.2 -> 32089508 | DM9: =BK9*(B9*(409.81+2)/1000+C9*(248.2+2*22.99)/1000+D9*(315.6+3*22.99)/1000+0.1*58.44/1000) -> 0.70639694 | DN9: =(BS9+BT9)/1000*('Oxidant Feed Composition'!$B$11*'Oxidant Feed Composition'!$O$20+'Oxidant Feed Composition'!$D$11*'Oxidant Feed Composition'!$O$21+'Oxidant Feed Composition'!$F$11*'Oxidant Feed Composition'!$O$27-'Oxidant Feed Composition'!$J$15*18.015) -> 2.7202738 | DO9: =(BU9+BV9)/1000*(0.2*368.34+0.4*58.44) -> 1.8837129 | DP9: =BK9/1000*(B9*195.08+C9*106.42+D9*102.91) -> 0.049999383 | DQ9: =SUM(DM9:DO9)-DP9 -> 5.2603842 | DR9: =DQ9*60*7200*0.33 -> 749920.37 | DS9: 1.2 | DT9: =BM9/60*(AM9*4+AN9*2+AO9*3)*96485/DV9 -> 1410.0862 | DU9: =BN9*BA9*(AP9*4+AQ9*2+AR9*3)*96485/DV9/60 -> 712.11901 | DV9: 0.7 | DW9: =0.499*((BK9/3.78541*15)^(-0.146))*BK9/3.78541*15*300*(1+(A9-2)/9) -> 27520.276 | DX9: =0.248*((BK9/3.78541*15)^(-0.144))*BK9/3.78541*15*300*(1+(A9-2)/3) -> 16610.44 | DY9: =0.105*((BK9/3.78541*15)^(-0.144))*BK9/3.78541*15*300*(1+(A9-2)/3) -> 7032.6458 | DZ9: =0.058*((BK9/3.78541*15)^(-0.151))*BK9/3.78541*15*300*(1+(A9-2)/3) -> 3725.3887 | EA9: =0.056*((BK9/3.78541*15)^(-0.144))*BK9/3.78541*15*300*(1+(A9-2)/3) -> 3750.7444 | EB9: =DS9*DT9/(3.6*10^6)*3600*7200*0.07 -> 852.82016 | EC9: =0.499*((BM9/3.78541*15)^(-0.146))*BM9/3.78541*15*300*(1+(AF9-2)/9) -> 46423.887 | ED9: =0.248*((BM9/3.78541*15)^(-0.144))*BM9/3.78541*15*300*(1+(AF9-2)/3) -> 46693.087 | EE9: =0.105*((BM9/3.78541*15)^(-0.144))*BM9/3.78541*15*300*(1+(AF9-2)/3) -> 19769.251 | EF9: =0.058*((BM9/3.78541*15)^(-0.151))*BM9/3.78541*15*300*(1+(AF9-2)/3) -> 10477.896 | EG9: =0.056*((BM9/3.78541*15)^(-0.144))*BM9/3.78541*15*300*(1+(AF9-2)/3) -> 10543.6 | EH9: =DS9*DU9/(3.6*10^6)*3600*7200*0.07 -> 430.68958 | EI9: =SUM(DW9:EH9) -> 193830.73 | EJ9: =EI9+DR9+DL9 -> 33033260 | EK9: =EJ9+DF9 -> 33693131 | EL9: =EK9/(BK9*60*7200) -> 0.77993358 | EM9: =EK9/(BM9*(AM9*195.084/1000+AN9*106.42/1000+AO9*102.911/1000)*60*7200) -> 2607.7033 | EN9: =EK9/(BN9*BA9*(AP9*195.084/1000+AQ9*106.42/1000+AR9*102.911/1000)*60*7200) -> 4746.3045
A10: ='Costing 100 Lmin Feed Orig'!A10 -> 3 | B10: ='Costing 100 Lmin Feed Orig'!B10 -> 0.0015414359 | C10: ='Costing 100 Lmin Feed Orig'!C10 -> 0.0015414359 | D10: ='Costing 100 Lmin Feed Orig'!D10 -> 0.0003425413 | E10: ='Costing 100 Lmin Feed Orig'!E10 -> 0 | F10: ='Costing 100 Lmin Feed Orig'!F10 -> 0 | G10: ='Costing 100 Lmin Feed Orig'!G10 -> 0 | H10: ='Costing 100 Lmin Feed Orig'!H10 -> 1.6300359e-05 | ... BN10: ='Costing 100 Lmin Feed Orig'!BN10 -> 19.929157 | BO10: =(A10+2)*2*BL10 -> 188.92482 | BP10: =(AF10+2)*2*BN10 -> 558.01638 | BQ10: =BO10*V10 -> 18.892482 | BR10: =BP10*BA10 -> 55.801638 | BS10: =1.2*0.5*BL10*V10/'Oxidant Feed Composition'!$N$22 -> 11.335489 | BT10: =1.2*0.5*BN10*BA10/'Oxidant Feed Composition'!$N$22 -> 11.957494 | BU10: =V10*BL10/0.2 -> 9.4462412 | BV10: =BA10*BN10/0.2 -> 9.9645783 | BW10: =BM10-BU10 -> 83.236294 | BX10: =(BS10+BL10)*2 -> 60.455944 | BY10: =(BU10+BW10+BL10)*2 -> 223.15004 | BZ10: =(BT10+BN10)*2 -> 63.773301 | CA10: =(BV10+BN10)*2 -> 59.78747 | CB10: =BO10*'Reagent cost'!$G$11*'Reagent cost'!$H$11 -> 2493.8077 | CC10: =BP10*'Reagent cost'!$G$11*'Reagent cost'!$H$11 -> 7365.8163 | CD10: =BQ10*'Reagent cost'!$C$18/1000*'Reagent cost'!$H$18 -> 3012.9816 | CE10: =BR10*'Ligand cost'!$B$56*'Ligand cost'!$J$56 -> 56813.196 | CF10: =BK10*0.1 -> 10 | CG10: =BU10*0.4 -> 3.7784965 | CH10: =BV10*0.4 -> 3.9858313 | CI10: =7963.6*(BX10/1000)^0.6*1.7*('CAPEX+OPEX'!$G$116/'CAPEX+OPEX'!$G$115) -> 2965.5437 | CJ10: =7963.6*(BY10/1000)^0.6*1.7*('CAPEX+OPEX'!$G$116/'CAPEX+OPEX'!$G$115) -> 6492.3078 | CK10: =7963.6*(BZ10/1000)^0.6*1.7*('CAPEX+OPEX'!$G$116/'CAPEX+OPEX'!$G$115) -> 3062.1345 | CL10: =7963.6*(CA10/1000)^0.6*1.7*('CAPEX+OPEX'!$G$116/'CAPEX+OPEX'!$G$115) -> 2945.8256 | CM10: ='Costing 100 Lmin Feed Orig'!DE10 -> 39625.827 | CN10: ='Costing 100 Lmin Feed Orig'!DF10 -> 4586243.4 | CO10: ='Costing 100 Lmin Feed Orig'!DG10 -> 11794835 | CP10: ='Costing 100 Lmin Feed Orig'!DH10 -> 2275209.2 | CQ10: ='Costing 100 Lmin Feed Orig'!DI10 -> 14083914 | CR10: ='Costing 100 Lmin Feed Orig'!DJ10 -> 1662824.9 | CS10: =CN10*(BK10/10000)^0.72*((A10+1)/3)^0.6*('CAPEX+OPEX'!$G$116/'CAPEX+OPEX'!$G$114) -> 461850.1 | CT10: =CO10*(BK10/10000)^0.72*((A10+1)/3)^0.6*('CAPEX+OPEX'!$G$116/'CAPEX+OPEX'!$G$114) -> 1187779.4 | CU10: =CP10*(BK10/10000)^0.72*((A10+1)/3)^0.6*('CAPEX+OPEX'!$G$116/'CAPEX+OPEX'!$G$114) -> 229121.2 | CV10: =CQ10*(BK10/10000)^0.72*((A10+1)/3)^0.6*('CAPEX+OPEX'!$G$116/'CAPEX+OPEX'!$G$114) -> 1418297.4 | CW10: =CR10*(BK10/10000)^0.72*((A10+1)/3)^0.6*('CAPEX+OPEX'!$G$116/'CAPEX+OPEX'!$G$114) -> 167452.05 | CX10: =SUM(CS10:CW10) -> 3464500.2 | CY10: =CN10*(BM10/10000)^0.72*((AF10+1)/3)^0.6*('CAPEX+OPEX'!$G$116/'CAPEX+OPEX'!$G$114) -> 886889.57 | CZ10: =CO10*(BM10/10000)^0.72*((AF10+1)/3)^0.6*('CAPEX+OPEX'!$G$116/'CAPEX+OPEX'!$G$114) -> 2280889.8 | DA10: =CP10*(BM10/10000)^0.72*((AF10+1)/3)^0.6*('CAPEX+OPEX'!$G$116/'CAPEX+OPEX'!$G$114) -> 439980.85 | DB10: =CQ10*(BM10/10000)^0.72*((AF10+1)/3)^0.6*('CAPEX+OPEX'!$G$116/'CAPEX+OPEX'!$G$114) -> 2723552.9 | DC10: =CR10*(BM10/10000)^0.72*((AF10+1)/3)^0.6*('CAPEX+OPEX'!$G$116/'CAPEX+OPEX'!$G$114) -> 321557.74 | DD10: =SUM(CY10:DC10) -> 6652870.9 | DE10: =CX10+DD10+1.15*(SUM(CI10:CL10)+SUM(CB10:CE10)) -> 10215295 | DF10: =DE10/15 -> 681019.69 | DG10: =(BS10+BT10)*'Oxidant Feed Composition'!$N$25*60*7200 -> 18759079 | DH10: =((CG10+CH10)*'Reagent cost'!$C$17/1000*'Reagent cost'!$H$17+(CG10+CH10)*0.5*'Reagent cost'!$C$16/1000*'Reagent cost'!$H$16)*60*7200 -> 7475918.4 | DI10: =CF10*'Reagent cost'!$C$17/1000*'Reagent cost'!$H$17*60*7200 -> 504921.6 | DJ10: =(CB10+CC10)*0.01 -> 98.59624 | DK10: =(CD10+CE10)*0.02 -> 1196.5235 | DL10: =SUM(DG10:DK10)*1.2 -> 32089457 | DM10: =BK10*(B10*(409.81+2)/1000+C10*(248.2+2*22.99)/1000+D10*(315.6+3*22.99)/1000+0.1*58.44/1000) -> 0.70639694 | DN10: =(BS10+BT10)/1000*('Oxidant Feed Composition'!$B$11*'Oxidant Feed Composition'!$O$20+'Oxidant Feed Composition'!$D$11*'Oxidant Feed Composition'!$O$21+'Oxidant Feed Composition'!$F$11*'Oxidant Feed Composition'!$O$27-'Oxidant Feed Composition'!$J$15*18.015) -> 2.7202604 | DO10: =(BU10+BV10)/1000*(0.2*368.34+0.4*58.44) -> 1.8837036 | DP10: =BK10/1000*(B10*195.08+C10*106.42+D10*102.91) -> 0.049999383 | DQ10: =SUM(DM10:DO10)-DP10 -> 5.2603615 | DR10: =DQ10*60*7200*0.33 -> 749917.13 | DS10: 1.2 | DT10: =BM10/60*(AM10*4+AN10*2+AO10*3)*96485/DV10 -> 1410.0874 | DU10: =BN10*BA10*(AP10*4+AQ10*2+AR10*3)*96485/DV10/60 -> 712.1179 | DV10: 0.7 | DW10: =0.499*((BK10/3.78541*15)^(-0.146))*BK10/3.78541*15*300*(1+(A10-2)/9) -> 27520.276 | DX10: =0.248*((BK10/3.78541*15)^(-0.144))*BK10/3.78541*15*300*(1+(A10-2)/3) -> 16610.44 | DY10: =0.105*((BK10/3.78541*15)^(-0.144))*BK10/3.78541*15*300*(1+(A10-2)/3) -> 7032.6458 | DZ10: =0.058*((BK10/3.78541*15)^(-0.151))*BK10/3.78541*15*300*(1+(A10-2)/3) -> 3725.3887 | EA10: =0.056*((BK10/3.78541*15)^(-0.144))*BK10/3.78541*15*300*(1+(A10-2)/3) -> 3750.7444 | EB10: =DS10*DT10/(3.6*10^6)*3600*7200*0.07 -> 852.82083 | EC10: =0.499*((BM10/3.78541*15)^(-0.146))*BM10/3.78541*15*300*(1+(AF10-2)/9) -> 49002.992 | ED10: =0.248*((BM10/3.78541*15)^(-0.144))*BM10/3.78541*15*300*(1+(AF10-2)/3) -> 50584.178 | EE10: =0.105*((BM10/3.78541*15)^(-0.144))*BM10/3.78541*15*300*(1+(AF10-2)/3) -> 21416.688 | EF10: =0.058*((BM10/3.78541*15)^(-0.151))*BM10/3.78541*15*300*(1+(AF10-2)/3) -> 11351.054 | EG10: =0.056*((BM10/3.78541*15)^(-0.144))*BM10/3.78541*15*300*(1+(AF10-2)/3) -> 11422.234 | EH10: =DS10*DU10/(3.6*10^6)*3600*7200*0.07 -> 430.6889 | EI10: =SUM(DW10:EH10) -> 203700.15 | EJ10: =EI10+DR10+DL10 -> 33043074 | EK10: =EJ10+DF10 -> 33724094 | EL10: =EK10/(BK10*60*7200) -> 0.78065032 | EM10: =EK10/(BM10*(AM10*195.084/1000+AN10*106.42/1000+AO10*102.911/1000)*60*7200) -> 2610.0977 | EN10: =EK10/(BN10*BA10*(AP10*195.084/1000+AQ10*106.42/1000+AR10*102.911/1000)*60*7200) -> 4750.6731
A11: ='Costing 100 Lmin Feed Orig'!A11 -> 3 | B11: ='Costing 100 Lmin Feed Orig'!B11 -> 0.0015414359 | C11: ='Costing 100 Lmin Feed Orig'!C11 -> 0.0015414359 | D11: ='Costing 100 Lmin Feed Orig'!D11 -> 0.0003425413 | E11: ='Costing 100 Lmin Feed Orig'!E11 -> 0 | F11: ='Costing 100 Lmin Feed Orig'!F11 -> 0 | G11: ='Costing 100 Lmin Feed Orig'!G11 -> 0 | H11: ='Costing 100 Lmin Feed Orig'!H11 -> 1.6300359e-05 | ... BN11: ='Costing 100 Lmin Feed Orig'!BN11 -> 19.929102 | BO11: =(A11+2)*2*BL11 -> 188.92482 | BP11: =(AF11+2)*2*BN11 -> 597.87305 | BQ11: =BO11*V11 -> 18.892482 | BR11: =BP11*BA11 -> 59.787305 | BS11: =1.2*0.5*BL11*V11/'Oxidant Feed Composition'!$N$22 -> 11.335489 | BT11: =1.2*0.5*BN11*BA11/'Oxidant Feed Composition'!$N$22 -> 11.957461 | BU11: =V11*BL11/0.2 -> 9.4462412 | BV11: =BA11*BN11/0.2 -> 9.9645509 | BW11: =BM11-BU11 -> 83.236294 | BX11: =(BS11+BL11)*2 -> 60.455944 | BY11: =(BU11+BW11+BL11)*2 -> 223.15004 | BZ11: =(BT11+BN11)*2 -> 63.773126 | CA11: =(BV11+BN11)*2 -> 59.787305 | CB11: =BO11*'Reagent cost'!$G$11*'Reagent cost'!$H$11 -> 2493.8077 | CC11: =BP11*'Reagent cost'!$G$11*'Reagent cost'!$H$11 -> 7891.9243 | CD11: =BQ11*'Reagent cost'!$C$18/1000*'Reagent cost'!$H$18 -> 3012.9816 | CE11: =BR11*'Ligand cost'!$B$56*'Ligand cost'!$J$56 -> 60871.114 | CF11: =BK11*0.1 -> 10 | CG11: =BU11*0.4 -> 3.7784965 | CH11: =BV11*0.4 -> 3.9858204 | CI11: =7963.6*(BX11/1000)^0.6*1.7*('CAPEX+OPEX'!$G$116/'CAPEX+OPEX'!$G$115) -> 2965.5437 | CJ11: =7963.6*(BY11/1000)^0.6*1.7*('CAPEX+OPEX'!$G$116/'CAPEX+OPEX'!$G$115) -> 6492.3078 | CK11: =7963.6*(BZ11/1000)^0.6*1.7*('CAPEX+OPEX'!$G$116/'CAPEX+OPEX'!$G$115) -> 3062.1295 | CL11: =7963.6*(CA11/1000)^0.6*1.7*('CAPEX+OPEX'!$G$116/'CAPEX+OPEX'!$G$115) -> 2945.8207 | CM11: ='Costing 100 Lmin Feed Orig'!DE11 -> 39625.827 | CN11: ='Costing 100 Lmin Feed Orig'!DF11 -> 4586243.4 | CO11: ='Costing 100 Lmin Feed Orig'!DG11 -> 11794835 | CP11: ='Costing 100 Lmin Feed Orig'!DH11 -> 2275209.2 | CQ11: ='Costing 100 Lmin Feed Orig'!DI11 -> 14083914 | CR11: ='Costing 100 Lmin Feed Orig'!DJ11 -> 1662824.9 | CS11: =CN11*(BK11/10000)^0.72*((A11+1)/3)^0.6*('CAPEX+OPEX'!$G$116/'CAPEX+OPEX'!$G$114) -> 461850.1 | CT11: =CO11*(BK11/10000)^0.72*((A11+1)/3)^0.6*('CAPEX+OPEX'!$G$116/'CAPEX+OPEX'!$G$114) -> 1187779.4 | CU11: =CP11*(BK11/10000)^0.72*((A11+1)/3)^0.6*('CAPEX+OPEX'!$G$116/'CAPEX+OPEX'!$G$114) -> 229121.2 | CV11: =CQ11*(BK11/10000)^0.72*((A11+1)/3)^0.6*('CAPEX+OPEX'!$G$116/'CAPEX+OPEX'!$G$114) -> 1418297.4 | CW11: =CR11*(BK11/10000)^0.72*((A11+1)/3)^0.6*('CAPEX+OPEX'!$G$116/'CAPEX+OPEX'!$G$114) -> 167452.05 | CX11: =SUM(CS11:CW11) -> 3464500.2 | CY11: =CN11*(BM11/10000)^0.72*((AF11+1)/3)^0.6*('CAPEX+OPEX'!$G$116/'CAPEX+OPEX'!$G$114) -> 927214.81 | CZ11: =CO11*(BM11/10000)^0.72*((AF11+1)/3)^0.6*('CAPEX+OPEX'!$G$116/'CAPEX+OPEX'!$G$114) -> 2384597.6 | DA11: =CP11*(BM11/10000)^0.72*((AF11+1)/3)^0.6*('CAPEX+OPEX'!$G$116/'CAPEX+OPEX'!$G$114) -> 459985.97 | DB11: =CQ11*(BM11/10000)^0.72*((AF11+1)/3)^0.6*('CAPEX+OPEX'!$G$116/'CAPEX+OPEX'!$G$114) -> 2847387.9 | DC11: =CR11*(BM11/10000)^0.72*((AF11+1)/3)^0.6*('CAPEX+OPEX'!$G$116/'CAPEX+OPEX'!$G$114) -> 336178.38 | DD11: =SUM(CY11:DC11) -> 6955364.7 | DE11: =CX11+DD11+1.15*(SUM(CI11:CL11)+SUM(CB11:CE11)) -> 10523061 | DF11: =DE11/15 -> 701537.39 | DG11: =(BS11+BT11)*'Oxidant Feed Composition'!$N$25*60*7200 -> 18759052 | DH11: =((CG11+CH11)*'Reagent cost'!$C$17/1000*'Reagent cost'!$H$17+(CG11+CH11)*0.5*'Reagent cost'!$C$16/1000*'Reagent cost'!$H$16)*60*7200 -> 7475907.9 | DI11: =CF11*'Reagent cost'!$C$17/1000*'Reagent cost'!$H$17*60*7200 -> 504921.6 | DJ11: =(CB11+CC11)*0.01 -> 103.85732 | DK11: =(CD11+CE11)*0.02 -> 1277.6819 | DL11: =SUM(DG11:DK11)*1.2 -> 32089516 | DM11: =BK11*(B11*(409.81+2)/1000+C11*(248.2+2*22.99)/1000+D11*(315.6+3*22.99)/1000+0.1*58.44/1000) -> 0.70639694 | DN11: =(BS11+BT11)/1000*('Oxidant Feed Composition'!$B$11*'Oxidant Feed Composition'!$O$20+'Oxidant Feed Composition'!$D$11*'Oxidant Feed Composition'!$O$21+'Oxidant Feed Composition'!$F$11*'Oxidant Feed Composition'!$O$27-'Oxidant Feed Composition'!$J$15*18.015) -> 2.7202565 | DO11: =(BU11+BV11)/1000*(0.2*368.34+0.4*58.44) -> 1.8837009 | DP11: =BK11/1000*(B11*195.08+C11*106.42+D11*102.91) -> 0.049999383 | DQ11: =SUM(DM11:DO11)-DP11 -> 5.260355 | DR11: =DQ11*60*7200*0.33 -> 749916.21 | DS11: 1.2 | DT11: =BM11/60*(AM11*4+AN11*2+AO11*3)*96485/DV11 -> 1410.0877 | DU11: =BN11*BA11*(AP11*4+AQ11*2+AR11*3)*96485/DV11/60 -> 712.11758 | DV11: 0.7 | DW11: =0.499*((BK11/3.78541*15)^(-0.146))*BK11/3.78541*15*300*(1+(A11-2)/9) -> 27520.276 | DX11: =0.248*((BK11/3.78541*15)^(-0.144))*BK11/3.78541*15*300*(1+(A11-2)/3) -> 16610.44 | DY11: =0.105*((BK11/3.78541*15)^(-0.144))*BK11/3.78541*15*300*(1+(A11-2)/3) -> 7032.6458 | DZ11: =0.058*((BK11/3.78541*15)^(-0.151))*BK11/3.78541*15*300*(1+(A11-2)/3) -> 3725.3887 | EA11: =0.056*((BK11/3.78541*15)^(-0.144))*BK11/3.78541*15*300*(1+(A11-2)/3) -> 3750.7444 | EB11: =DS11*DT11/(3.6*10^6)*3600*7200*0.07 -> 852.82103 | EC11: =0.499*((BM11/3.78541*15)^(-0.146))*BM11/3.78541*15*300*(1+(AF11-2)/9) -> 51582.097 | ED11: =0.248*((BM11/3.78541*15)^(-0.144))*BM11/3.78541*15*300*(1+(AF11-2)/3) -> 54475.268 | EE11: =0.105*((BM11/3.78541*15)^(-0.144))*BM11/3.78541*15*300*(1+(AF11-2)/3) -> 23064.126 | EF11: =0.058*((BM11/3.78541*15)^(-0.151))*BM11/3.78541*15*300*(1+(AF11-2)/3) -> 12224.212 | EG11: =0.056*((BM11/3.78541*15)^(-0.144))*BM11/3.78541*15*300*(1+(AF11-2)/3) -> 12300.867 | EH11: =DS11*DU11/(3.6*10^6)*3600*7200*0.07 -> 430.68871 | EI11: =SUM(DW11:EH11) -> 213569.57 | EJ11: =EI11+DR11+DL11 -> 33053002 | EK11: =EJ11+DF11 -> 33754539 | EL11: =EK11/(BK11*60*7200) -> 0.78135507 | EM11: =EK11/(BM11*(AM11*195.084/1000+AN11*106.42/1000+AO11*102.911/1000)*60*7200) -> 2612.4534 | EN11: =EK11/(BN11*BA11*(AP11*195.084/1000+AQ11*106.42/1000+AR11*102.911/1000)*60*7200) -> 4754.9638
A12: ='Costing 100 Lmin Feed Orig'!A12 -> 4 | B12: ='Costing 100 Lmin Feed Orig'!B12 -> 0.0015414359 | C12: ='Costing 100 Lmin Feed Orig'!C12 -> 0.0015414359 | D12: ='Costing 100 Lmin Feed Orig'!D12 -> 0.0003425413 | E12: ='Costing 100 Lmin Feed Orig'!E12 -> 0 | F12: ='Costing 100 Lmin Feed Orig'!F12 -> 0 | G12: ='Costing 100 Lmin Feed Orig'!G12 -> 0 | H12: ='Costing 100 Lmin Feed Orig'!H12 -> 1.7208961e-05 | ... BN12: ='Costing 100 Lmin Feed Orig'!BN12 -> 21.072386 | BO12: =(A12+2)*2*BL12 -> 167.48847 | BP12: =(AF12+2)*2*BN12 -> 252.86864 | BQ12: =BO12*V12 -> 16.748847 | BR12: =BP12*BA12 -> 25.286864 | BS12: =1.2*0.5*BL12*V12/'Oxidant Feed Composition'!$N$22 -> 8.3744235 | BT12: =1.2*0.5*BN12*BA12/'Oxidant Feed Composition'!$N$22 -> 12.643432 | BU12: =V12*BL12/0.2 -> 6.9786862 | BV12: =BA12*BN12/0.2 -> 10.536193 | BW12: =BM12-BU12 -> 85.501548 | BX12: =(BS12+BL12)*2 -> 44.663592 | BY12: =(BU12+BW12+BL12)*2 -> 212.87521 | BZ12: =(BT12+BN12)*2 -> 67.431636 | CA12: =(BV12+BN12)*2 -> 63.217159 | CB12: =BO12*'Reagent cost'!$G$11*'Reagent cost'!$H$11 -> 2210.8478 | CC12: =BP12*'Reagent cost'!$G$11*'Reagent cost'!$H$11 -> 3337.866 | CD12: =BQ12*'Reagent cost'!$C$18/1000*'Reagent cost'!$H$18 -> 2671.1137 | CE12: =BR12*'Ligand cost'!$B$56*'Ligand cost'!$J$56 -> 25745.257 | CF12: =BK12*0.1 -> 10 | CG12: =BU12*0.4 -> 2.7914745 | CH12: =BV12*0.4 -> 4.2144773 | CI12: =7963.6*(BX12/1000)^0.6*1.7*('CAPEX+OPEX'!$G$116/'CAPEX+OPEX'!$G$115) -> 2472.9374 | CJ12: =7963.6*(BY12/1000)^0.6*1.7*('CAPEX+OPEX'!$G$116/'CAPEX+OPEX'!$G$115) -> 6311.2587 | CK12: =7963.6*(BZ12/1000)^0.6*1.7*('CAPEX+OPEX'!$G$116/'CAPEX+OPEX'!$G$115) -> 3166.3517 | CL12: =7963.6*(CA12/1000)^0.6*1.7*('CAPEX+OPEX'!$G$116/'CAPEX+OPEX'!$G$115) -> 3046.0843 | CM12: ='Costing 100 Lmin Feed Orig'!DE12 -> 39625.827 | CN12: ='Costing 100 Lmin Feed Orig'!DF12 -> 4586243.4 | CO12: ='Costing 100 Lmin Feed Orig'!DG12 -> 11794835 | CP12: ='Costing 100 Lmin Feed Orig'!DH12 -> 2275209.2 | CQ12: ='Costing 100 Lmin Feed Orig'!DI12 -> 14083914 | CR12: ='Costing 100 Lmin Feed Orig'!DJ12 -> 1662824.9 | CS12: =CN12*(BK12/10000)^0.72*((A12+1)/3)^0.6*('CAPEX+OPEX'!$G$116/'CAPEX+OPEX'!$G$114) -> 528015.96 | CT12: =CO12*(BK12/10000)^0.72*((A12+1)/3)^0.6*('CAPEX+OPEX'!$G$116/'CAPEX+OPEX'!$G$114) -> 1357943.8 | CU12: =CP12*(BK12/10000)^0.72*((A12+1)/3)^0.6*('CAPEX+OPEX'!$G$116/'CAPEX+OPEX'!$G$114) -> 261945.7 | CV12: =CQ12*(BK12/10000)^0.72*((A12+1)/3)^0.6*('CAPEX+OPEX'!$G$116/'CAPEX+OPEX'!$G$114) -> 1621486.4 | CW12: =CR12*(BK12/10000)^0.72*((A12+1)/3)^0.6*('CAPEX+OPEX'!$G$116/'CAPEX+OPEX'!$G$114) -> 191441.67 | CX12: =SUM(CS12:CW12) -> 3960833.6 | CY12: =CN12*(BM12/10000)^0.72*((AF12+1)/3)^0.6*('CAPEX+OPEX'!$G$116/'CAPEX+OPEX'!$G$114) -> 499116.89 | CZ12: =CO12*(BM12/10000)^0.72*((AF12+1)/3)^0.6*('CAPEX+OPEX'!$G$116/'CAPEX+OPEX'!$G$114) -> 1283621.6 | DA12: =CP12*(BM12/10000)^0.72*((AF12+1)/3)^0.6*('CAPEX+OPEX'!$G$116/'CAPEX+OPEX'!$G$114) -> 247609.04 | DB12: =CQ12*(BM12/10000)^0.72*((AF12+1)/3)^0.6*('CAPEX+OPEX'!$G$116/'CAPEX+OPEX'!$G$114) -> 1532740.2 | DC12: =CR12*(BM12/10000)^0.72*((AF12+1)/3)^0.6*('CAPEX+OPEX'!$G$116/'CAPEX+OPEX'!$G$114) -> 180963.79 | DD12: =SUM(CY12:DC12) -> 3744051.5 | DE12: =CX12+DD12+1.15*(SUM(CI12:CL12)+SUM(CB12:CE12)) -> 7761191.1 | DF12: =DE12/15 -> 517412.74 | DG12: =(BS12+BT12)*'Oxidant Feed Composition'!$N$25*60*7200 -> 16926797 | DH12: =((CG12+CH12)*'Reagent cost'!$C$17/1000*'Reagent cost'!$H$17+(CG12+CH12)*0.5*'Reagent cost'!$C$16/1000*'Reagent cost'!$H$16)*60*7200 -> 6745712.6 | DI12: =CF12*'Reagent cost'!$C$17/1000*'Reagent cost'!$H$17*60*7200 -> 504921.6 | DJ12: =(CB12+CC12)*0.01 -> 55.487138 | DK12: =(CD12+CE12)*0.02 -> 568.32742 | DL12: =SUM(DG12:DK12)*1.2 -> 29013666 | DM12: =BK12*(B12*(409.81+2)/1000+C12*(248.2+2*22.99)/1000+D12*(315.6+3*22.99)/1000+0.1*58.44/1000) -> 0.70639694 | DN12: =(BS12+BT12)/1000*('Oxidant Feed Composition'!$B$11*'Oxidant Feed Composition'!$O$20+'Oxidant Feed Composition'!$D$11*'Oxidant Feed Composition'!$O$21+'Oxidant Feed Composition'!$F$11*'Oxidant Feed Composition'!$O$27-'Oxidant Feed Composition'!$J$15*18.015) -> 2.4545606 | DO12: =(BU12+BV12)/1000*(0.2*368.34+0.4*58.44) -> 1.699714 | DP12: =BK12/1000*(B12*195.08+C12*106.42+D12*102.91) -> 0.049999383 | DQ12: =SUM(DM12:DO12)-DP12 -> 4.8106721 | DR12: =DQ12*60*7200*0.33 -> 685809.41 | DS12: 1.2 | DT12: =BM12/60*(AM12*4+AN12*2+AO12*3)*96485/DV12 -> 1399.9243 | DU12: =BN12*BA12*(AP12*4+AQ12*2+AR12*3)*96485/DV12/60 -> 715.74336 | DV12: 0.7 | DW12: =0.499*((BK12/3.78541*15)^(-0.146))*BK12/3.78541*15*300*(1+(A12-2)/9) -> 30272.304 | DX12: =0.248*((BK12/3.78541*15)^(-0.144))*BK12/3.78541*15*300*(1+(A12-2)/3) -> 20763.049 | DY12: =0.105*((BK12/3.78541*15)^(-0.144))*BK12/3.78541*15*300*(1+(A12-2)/3) -> 8790.8072 | DZ12: =0.058*((BK12/3.78541*15)^(-0.151))*BK12/3.78541*15*300*(1+(A12-2)/3) -> 4656.7358 | EA12: =0.056*((BK12/3.78541*15)^(-0.144))*BK12/3.78541*15*300*(1+(A12-2)/3) -> 4688.4305 | EB12: =DS12*DT12/(3.6*10^6)*3600*7200*0.07 -> 846.67423 | EC12: =0.499*((BM12/3.78541*15)^(-0.146))*BM12/3.78541*15*300*(1+(AF12-2)/9) -> 28317.261 | ED12: =0.248*((BM12/3.78541*15)^(-0.144))*BM12/3.78541*15*300*(1+(AF12-2)/3) -> 19419.096 | EE12: =0.105*((BM12/3.78541*15)^(-0.144))*BM12/3.78541*15*300*(1+(AF12-2)/3) -> 8221.7948 | EF12: =0.058*((BM12/3.78541*15)^(-0.151))*BM12/3.78541*15*300*(1+(AF12-2)/3) -> 4357.6981 | EG12: =0.056*((BM12/3.78541*15)^(-0.144))*BM12/3.78541*15*300*(1+(AF12-2)/3) -> 4384.9572 | EH12: =DS12*DU12/(3.6*10^6)*3600*7200*0.07 -> 432.88158 | EI12: =SUM(DW12:EH12) -> 135151.69 | EJ12: =EI12+DR12+DL12 -> 29834627 | EK12: =EJ12+DF12 -> 30352040 | EL12: =EK12/(BK12*60*7200) -> 0.70259352 | EM12: =EK12/(BM12*(AM12*195.084/1000+AN12*106.42/1000+AO12*102.911/1000)*60*7200) -> 2362.6661 | EN12: =EK12/(BN12*BA12*(AP12*195.084/1000+AQ12*106.42/1000+AR12*102.911/1000)*60*7200) -> 4257.4198
